Workbook
Name oi: #REF!
Name Slicer_Classificação: #N/A
Name Slicer_Data: #N/A
Name Slicer_Data1: #N/A
Name Slicer_Data2: #N/A
Name Slicer_Data3: #N/A
Name Slicer_Data4: #N/A
Name Slicer_Instituição: #N/A
Name Slicer_Subclassificação: #N/A

Sheet Investimentos_Main
B3: Investimentos
B4: Data | C4: Nome | D4: Ticker | E4: Instituição | F4: Estratégia | G4: Quantidade | H4: Cotação Ativo | I4: Moeda Base | J4: Cotação Dolar | K4: Total (R$)
B5: 45078 | C5: Bitcoin | D5: BTC | E5: Ledger | G5: 0.179195 | H5: {=_xlfn.XLOOKUP(Table_Investimentos_Main[[#This Row],[Data]]&Table_Investimentos_Main[[#This Row],[Ticker]],Table_Cotacoes[Data]&Table_Cotacoes[Ticker],Table_Cotacoes[Valor],"")} -> 135052 | I5: =IF(Table_Investimentos_Main[[#This Row],[Ticker]]<>"",_xlfn.XLOOKUP(Table_Investimentos_Main[[#This Row],[Ticker]],Table_Cotacoes[Ticker],Table_Cotacoes[Moeda Base],""),"BRL") -> BTC | J5: {=_xlfn.SINGLE(_xlfn.XLOOKUP(Table_Investimentos_Main[[#This Row],[Data]]&"USD",Table_Cotacoes[Data]&Table_Cotacoes[Ticker],Table_Cotacoes[Valor],""))} -> 5.007 | K5: =IF(Table_Investimentos_Main[[#This Row],[Ticker]]<>"",Table_Investimentos_Main[[#This Row],[Quantidade]]*Table_Investimentos_Main[[#This Row],[Cotação Ativo]],Table_Investimentos_Main[[#This Row],[Quantidade]]) -> 24200.643
B6: 45078 | C6: Liquidez Diaria | E6: PicPay | G6: 3698.14 | H6: {=_xlfn.XLOOKUP(Table_Investimentos_Main[[#This Row],[Data]]&Table_Investimentos_Main[[#This Row],[Ticker]],Table_Cotacoes[Data]&Table_Cotacoes[Ticker],Table_Cotacoes[Valor],"")} | I6: =IF(Table_Investimentos_Main[[#This Row],[Ticker]]<>"",_xlfn.XLOOKUP(Table_Investimentos_Main[[#This Row],[Ticker]],Table_Cotacoes[Ticker],Table_Cotacoes[Moeda Base],""),"BRL") -> BRL | J6: {=_xlfn.SINGLE(_xlfn.XLOOKUP(Table_Investimentos_Main[[#This Row],[Data]]&"USD",Table_Cotacoes[Data]&Table_Cotacoes[Ticker],Table_Cotacoes[Valor],""))} -> 5.007 | K6: =IF(Table_Investimentos_Main[[#This Row],[Ticker]]<>"",Table_Investimentos_Main[[#This Row],[Quantidade]]*Table_Investimentos_Main[[#This Row],[Cotação Ativo]],Table_Investimentos_Main[[#This Row],[Quantidade]]) -> 3698.14
B7: 45078 | C7: CDB - 110% | E7: C6 | G7: 20017.71 | H7: {=_xlfn.XLOOKUP(Table_Investimentos_Main[[#This Row],[Data]]&Table_Investimentos_Main[[#This Row],[Ticker]],Table_Cotacoes[Data]&Table_Cotacoes[Ticker],Table_Cotacoes[Valor],"")} | I7: =IF(Table_Investimentos_Main[[#This Row],[Ticker]]<>"",_xlfn.XLOOKUP(Table_Investimentos_Main[[#This Row],[Ticker]],Table_Cotacoes[Ticker],Table_Cotacoes[Moeda Base],""),"BRL") -> BRL | J7: {=_xlfn.SINGLE(_xlfn.XLOOKUP(Table_Investimentos_Main[[#This Row],[Data]]&"USD",Table_Cotacoes[Data]&Table_Cotacoes[Ticker],Table_Cotacoes[Valor],""))} -> 5.007 | K7: =IF(Table_Investimentos_Main[[#This Row],[Ticker]]<>"",Table_Investimentos_Main[[#This Row],[Quantidade]]*Table_Investimentos_Main[[#This Row],[Cotação Ativo]],Table_Investimentos_Main[[#This Row],[Quantidade]]) -> 20017.71
B8: 45078 | C8: USDT | D8: USD | E8: Binance | G8: 1002 | H8: {=_xlfn.XLOOKUP(Table_Investimentos_Main[[#This Row],[Data]]&Table_Investimentos_Main[[#This Row],[Ticker]],Table_Cotacoes[Data]&Table_Cotacoes[Ticker],Table_Cotacoes[Valor],"")} -> 5.007 | I8: =IF(Table_Investimentos_Main[[#This Row],[Ticker]]<>"",_xlfn.XLOOKUP(Table_Investimentos_Main[[#This Row],[Ticker]],Table_Cotacoes[Ticker],Table_Cotacoes[Moeda Base],""),"BRL") -> USD | J8: {=_xlfn.SINGLE(_xlfn.XLOOKUP(Table_Investimentos_Main[[#This Row],[Data]]&"USD",Table_Cotacoes[Data]&Table_Cotacoes[Ticker],Table_Cotacoes[Valor],""))} -> 5.007 | K8: =IF(Table_Investimentos_Main[[#This Row],[Ticker]]<>"",Table_Investimentos_Main[[#This Row],[Quantidade]]*Table_Investimentos_Main[[#This Row],[Cotação Ativo]],Table_Investimentos_Main[[#This Row],[Quantidade]]) -> 5017.014
B9: 45078 | C9: BUSD | D9: USD | E9: Binance | G9: 2527 | H9: {=_xlfn.XLOOKUP(Table_Investimentos_Main[[#This Row],[Data]]&Table_Investimentos_Main[[#This Row],[Ticker]],Table_Cotacoes[Data]&Table_Cotacoes[Ticker],Table_Cotacoes[Valor],"")} -> 5.007 | I9: =IF(Table_Investimentos_Main[[#This Row],[Ticker]]<>"",_xlfn.XLOOKUP(Table_Investimentos_Main[[#This Row],[Ticker]],Table_Cotacoes[Ticker],Table_Cotacoes[Moeda Base],""),"BRL") -> USD | J9: {=_xlfn.SINGLE(_xlfn.XLOOKUP(Table_Investimentos_Main[[#This Row],[Data]]&"USD",Table_Cotacoes[Data]&Table_Cotacoes[Ticker],Table_Cotacoes[Valor],""))} -> 5.007 | K9: =IF(Table_Investimentos_Main[[#This Row],[Ticker]]<>"",Table_Investimentos_Main[[#This Row],[Quantidade]]*Table_Investimentos_Main[[#This Row],[Cotação Ativo]],Table_Investimentos_Main[[#This Row],[Quantidade]]) -> 12652.689
B10: 45078 | C10: Dolar | D10: USD | E10: Inter | G10: 99.79 | H10: {=_xlfn.XLOOKUP(Table_Investimentos_Main[[#This Row],[Data]]&Table_Investimentos_Main[[#This Row],[Ticker]],Table_Cotacoes[Data]&Table_Cotacoes[Ticker],Table_Cotacoes[Valor],"")} -> 5.007 | I10: =IF(Table_Investimentos_Main[[#This Row],[Ticker]]<>"",_xlfn.XLOOKUP(Table_Investimentos_Main[[#This Row],[Ticker]],Table_Cotacoes[Ticker],Table_Cotacoes[Moeda Base],""),"BRL") -> USD | J10: {=_xlfn.SINGLE(_xlfn.XLOOKUP(Table_Investimentos_Main[[#This Row],[Data]]&"USD",Table_Cotacoes[Data]&Table_Cotacoes[Ticker],Table_Cotacoes[Valor],""))} -> 5.007 | K10: =IF(Table_Investimentos_Main[[#This Row],[Ticker]]<>"",Table_Investimentos_Main[[#This Row],[Quantidade]]*Table_Investimentos_Main[[#This Row],[Cotação Ativo]],Table_Investimentos_Main[[#This Row],[Quantidade]]) -> 499.64853
B11: 45108 | C11: Bitcoin | D11: BTC | E11: Ledger | G11: 0.179195 | H11: {=_xlfn.XLOOKUP(Table_Investimentos_Main[[#This Row],[Data]]&Table_Investimentos_Main[[#This Row],[Ticker]],Table_Cotacoes[Data]&Table_Cotacoes[Ticker],Table_Cotacoes[Valor],"")} -> 151373.22 | I11: =IF(Table_Investimentos_Main[[#This Row],[Ticker]]<>"",_xlfn.XLOOKUP(Table_Investimentos_Main[[#This Row],[Ticker]],Table_Cotacoes[Ticker],Table_Cotacoes[Moeda Base],""),"BRL") -> BTC | J11: {=_xlfn.SINGLE(_xlfn.XLOOKUP(Table_Investimentos_Main[[#This Row],[Data]]&"USD",Table_Cotacoes[Data]&Table_Cotacoes[Ticker],Table_Cotacoes[Valor],""))} -> 4.89 | K11: =IF(Table_Investimentos_Main[[#This Row],[Ticker]]<>"",Table_Investimentos_Main[[#This Row],[Quantidade]]*Table_Investimentos_Main[[#This Row],[Cotação Ativo]],Table_Investimentos_Main[[#This Row],[Quantidade]]) -> 27125.324
B12: 45108 | C12: Liquidez Diaria | E12: PicPay | G12: 4238.83 | H12: {=_xlfn.XLOOKUP(Table_Investimentos_Main[[#This Row],[Data]]&Table_Investimentos_Main[[#This Row],[Ticker]],Table_Cotacoes[Data]&Table_Cotacoes[Ticker],Table_Cotacoes[Valor],"")} | I12: =IF(Table_Investimentos_Main[[#This Row],[Ticker]]<>"",_xlfn.XLOOKUP(Table_Investimentos_Main[[#This Row],[Ticker]],Table_Cotacoes[Ticker],Table_Cotacoes[Moeda Base],""),"BRL") -> BRL | J12: {=_xlfn.SINGLE(_xlfn.XLOOKUP(Table_Investimentos_Main[[#This Row],[Data]]&"USD",Table_Cotacoes[Data]&Table_Cotacoes[Ticker],Table_Cotacoes[Valor],""))} -> 4.89 | K12: =IF(Table_Investimentos_Main[[#This Row],[Ticker]]<>"",Table_Investimentos_Main[[#This Row],[Quantidade]]*Table_Investimentos_Main[[#This Row],[Cotação Ativo]],Table_Investimentos_Main[[#This Row],[Quantidade]]) -> 4238.83
B13: 45108 | C13: CDB - 110% | E13: C6 | G13: 20277.35 | H13: {=_xlfn.XLOOKUP(Table_Investimentos_Main[[#This Row],[Data]]&Table_Investimentos_Main[[#This Row],[Ticker]],Table_Cotacoes[Data]&Table_Cotacoes[Ticker],Table_Cotacoes[Valor],"")} | I13: =IF(Table_Investimentos_Main[[#This Row],[Ticker]]<>"",_xlfn.XLOOKUP(Table_Investimentos_Main[[#This Row],[Ticker]],Table_Cotacoes[Ticker],Table_Cotacoes[Moeda Base],""),"BRL") -> BRL | J13: {=_xlfn.SINGLE(_xlfn.XLOOKUP(Table_Investimentos_Main[[#This Row],[Data]]&"USD",Table_Cotacoes[Data]&Table_Cotacoes[Ticker],Table_Cotacoes[Valor],""))} -> 4.89 | K13: =IF(Table_Investimentos_Main[[#This Row],[Ticker]]<>"",Table_Investimentos_Main[[#This Row],[Quantidade]]*Table_Investimentos_Main[[#This Row],[Cotação Ativo]],Table_Investimentos_Main[[#This Row],[Quantidade]]) -> 20277.35
B14: 45108 | C14: USDT | D14: USD | E14: Binance | G14: 1009 | H14: {=_xlfn.XLOOKUP(Table_Investimentos_Main[[#This Row],[Data]]&Table_Investimentos_Main[[#This Row],[Ticker]],Table_Cotacoes[Data]&Table_Cotacoes[Ticker],Table_Cotacoes[Valor],"")} -> 4.89 | I14: =IF(Table_Investimentos_Main[[#This Row],[Ticker]]<>"",_xlfn.XLOOKUP(Table_Investimentos_Main[[#This Row],[Ticker]],Table_Cotacoes[Ticker],Table_Cotacoes[Moeda Base],""),"BRL") -> USD | J14: {=_xlfn.SINGLE(_xlfn.XLOOKUP(Table_Investimentos_Main[[#This Row],[Data]]&"USD",Table_Cotacoes[Data]&Table_Cotacoes[Ticker],Table_Cotacoes[Valor],""))} -> 4.89 | K14: =IF(Table_Investimentos_Main[[#This Row],[Ticker]]<>"",Table_Investimentos_Main[[#This Row],[Quantidade]]*Table_Investimentos_Main[[#This Row],[Cotação Ativo]],Table_Investimentos_Main[[#This Row],[Quantidade]]) -> 4934.01
B15: 45108 | C15: BUSD | D15: USD | E15: Binance | G15: 2529 | H15: {=_xlfn.XLOOKUP(Table_Investimentos_Main[[#This Row],[Data]]&Table_Investimentos_Main[[#This Row],[Ticker]],Table_Cotacoes[Data]&Table_Cotacoes[Ticker],Table_Cotacoes[Valor],"")} -> 4.89 | I15: =IF(Table_Investimentos_Main[[#This Row],[Ticker]]<>"",_xlfn.XLOOKUP(Table_Investimentos_Main[[#This Row],[Ticker]],Table_Cotacoes[Ticker],Table_Cotacoes[Moeda Base],""),"BRL") -> USD | J15: {=_xlfn.SINGLE(_xlfn.XLOOKUP(Table_Investimentos_Main[[#This Row],[Data]]&"USD",Table_Cotacoes[Data]&Table_Cotacoes[Ticker],Table_Cotacoes[Valor],""))} -> 4.89 | K15: =IF(Table_Investimentos_Main[[#This Row],[Ticker]]<>"",Table_Investimentos_Main[[#This Row],[Quantidade]]*Table_Investimentos_Main[[#This Row],[Cotação Ativo]],Table_Investimentos_Main[[#This Row],[Quantidade]]) -> 12366.81
B16: 45108 | C16: Dolar | D16: USD | E16: Inter | G16: 99.79 | H16: {=_xlfn.XLOOKUP(Table_Investimentos_Main[[#This Row],[Data]]&Table_Investimentos_Main[[#This Row],[Ticker]],Table_Cotacoes[Data]&Table_Cotacoes[Ticker],Table_Cotacoes[Valor],"")} -> 4.89 | I16: =IF(Table_Investimentos_Main[[#This Row],[Ticker]]<>"",_xlfn.XLOOKUP(Table_Investimentos_Main[[#This Row],[Ticker]],Table_Cotacoes[Ticker],Table_Cotacoes[Moeda Base],""),"BRL") -> USD | J16: {=_xlfn.SINGLE(_xlfn.XLOOKUP(Table_Investimentos_Main[[#This Row],[Data]]&"USD",Table_Cotacoes[Data]&Table_Cotacoes[Ticker],Table_Cotacoes[Valor],""))} -> 4.89 | K16: =IF(Table_Investimentos_Main[[#This Row],[Ticker]]<>"",Table_Investimentos_Main[[#This Row],[Quantidade]]*Table_Investimentos_Main[[#This Row],[Cotação Ativo]],Table_Investimentos_Main[[#This Row],[Quantidade]]) -> 487.9731
B17: 45200 | C17: Bitcoin | D17: BTC | E17: Binance | G17: 0.01745788 | H17: {=_xlfn.XLOOKUP(Table_Investimentos_Main[[#This Row],[Data]]&Table_Investimentos_Main[[#This Row],[Ticker]],Table_Cotacoes[Data]&Table_Cotacoes[Ticker],Table_Cotacoes[Valor],"")} -> 174262.84 | I17: =IF(Table_Investimentos_Main[[#This Row],[Ticker]]<>"",_xlfn.XLOOKUP(Table_Investimentos_Main[[#This Row],[Ticker]],Table_Cotacoes[Ticker],Table_Cotacoes[Moeda Base],""),"BRL") -> BTC | J17: {=_xlfn.SINGLE(_xlfn.XLOOKUP(Table_Investimentos_Main[[#This Row],[Data]]&"USD",Table_Cotacoes[Data]&Table_Cotacoes[Ticker],Table_Cotacoes[Valor],""))} -> 5.05 | K17: =IF(Table_Investimentos_Main[[#This Row],[Ticker]]<>"",Table_Investimentos_Main[[#This Row],[Quantidade]]*Table_Investimentos_Main[[#This Row],[Cotação Ativo]],Table_Investimentos_Main[[#This Row],[Quantidade]]) -> 3042.2597
B18: 45200 | C18: Bitcoin | D18: BTC | E18: Ledger | G18: 0.179195 | H18: {=_xlfn.XLOOKUP(Table_Investimentos_Main[[#This Row],[Data]]&Table_Investimentos_Main[[#This Row],[Ticker]],Table_Cotacoes[Data]&Table_Cotacoes[Ticker],Table_Cotacoes[Valor],"")} -> 174262.84 | I18: =IF(Table_Investimentos_Main[[#This Row],[Ticker]]<>"",_xlfn.XLOOKUP(Table_Investimentos_Main[[#This Row],[Ticker]],Table_Cotacoes[Ticker],Table_Cotacoes[Moeda Base],""),"BRL") -> BTC | J18: {=_xlfn.SINGLE(_xlfn.XLOOKUP(Table_Investimentos_Main[[#This Row],[Data]]&"USD",Table_Cotacoes[Data]&Table_Cotacoes[Ticker],Table_Cotacoes[Valor],""))} -> 5.05 | K18: =IF(Table_Investimentos_Main[[#This Row],[Ticker]]<>"",Table_Investimentos_Main[[#This Row],[Quantidade]]*Table_Investimentos_Main[[#This Row],[Cotação Ativo]],Table_Investimentos_Main[[#This Row],[Quantidade]]) -> 31227.03
B19: 45200 | C19: Inter | E19: Inter | G19: 5573.41 | H19: {=_xlfn.XLOOKUP(Table_Investimentos_Main[[#This Row],[Data]]&Table_Investimentos_Main[[#This Row],[Ticker]],Table_Cotacoes[Data]&Table_Cotacoes[Ticker],Table_Cotacoes[Valor],"")} | I19: =IF(Table_Investimentos_Main[[#This Row],[Ticker]]<>"",_xlfn.XLOOKUP(Table_Investimentos_Main[[#This Row],[Ticker]],Table_Cotacoes[Ticker],Table_Cotacoes[Moeda Base],""),"BRL") -> BRL | J19: {=_xlfn.SINGLE(_xlfn.XLOOKUP(Table_Investimentos_Main[[#This Row],[Data]]&"USD",Table_Cotacoes[Data]&Table_Cotacoes[Ticker],Table_Cotacoes[Valor],""))} -> 5.05 | K19: =IF(Table_Investimentos_Main[[#This Row],[Ticker]]<>"",Table_Investimentos_Main[[#This Row],[Quantidade]]*Table_Investimentos_Main[[#This Row],[Cotação Ativo]],Table_Investimentos_Main[[#This Row],[Quantidade]]) -> 5573.41
B20: 45200 | C20: C6 - CDB Diario 105% | E20: C6 | G20: 975 | H20: {=_xlfn.XLOOKUP(Table_Investimentos_Main[[#This Row],[Data]]&Table_Investimentos_Main[[#This Row],[Ticker]],Table_Cotacoes[Data]&Table_Cotacoes[Ticker],Table_Cotacoes[Valor],"")} | I20: =IF(Table_Investimentos_Main[[#This Row],[Ticker]]<>"",_xlfn.XLOOKUP(Table_Investimentos_Main[[#This Row],[Ticker]],Table_Cotacoes[Ticker],Table_Cotacoes[Moeda Base],""),"BRL") -> BRL | J20: {=_xlfn.SINGLE(_xlfn.XLOOKUP(Table_Investimentos_Main[[#This Row],[Data]]&"USD",Table_Cotacoes[Data]&Table_Cotacoes[Ticker],Table_Cotacoes[Valor],""))} -> 5.05 | K20: =IF(Table_Investimentos_Main[[#This Row],[Ticker]]<>"",Table_Investimentos_Main[[#This Row],[Quantidade]]*Table_Investimentos_Main[[#This Row],[Cotação Ativo]],Table_Investimentos_Main[[#This Row],[Quantidade]]) -> 975
B21: 45200 | C21: C6 - CDB Cartao 100% | E21: C6 | G21: 2500 | H21: {=_xlfn.XLOOKUP(Table_Investimentos_Main[[#This Row],[Data]]&Table_Investimentos_Main[[#This Row],[Ticker]],Table_Cotacoes[Data]&Table_Cotacoes[Ticker],Table_Cotacoes[Valor],"")} | I21: =IF(Table_Investimentos_Main[[#This Row],[Ticker]]<>"",_xlfn.XLOOKUP(Table_Investimentos_Main[[#This Row],[Ticker]],Table_Cotacoes[Ticker],Table_Cotacoes[Moeda Base],""),"BRL") -> BRL | J21: {=_xlfn.SINGLE(_xlfn.XLOOKUP(Table_Investimentos_Main[[#This Row],[Data]]&"USD",Table_Cotacoes[Data]&Table_Cotacoes[Ticker],Table_Cotacoes[Valor],""))} -> 5.05 | K21: =IF(Table_Investimentos_Main[[#This Row],[Ticker]]<>"",Table_Investimentos_Main[[#This Row],[Quantidade]]*Table_Investimentos_Main[[#This Row],[Cotação Ativo]],Table_Investimentos_Main[[#This Row],[Quantidade]]) -> 2500
B22: 45200 | C22: LCI DI 180 | E22: Inter | G22: 15748.75 | H22: {=_xlfn.XLOOKUP(Table_Investimentos_Main[[#This Row],[Data]]&Table_Investimentos_Main[[#This Row],[Ticker]],Table_Cotacoes[Data]&Table_Cotacoes[Ticker],Table_Cotacoes[Valor],"")} | I22: =IF(Table_Investimentos_Main[[#This Row],[Ticker]]<>"",_xlfn.XLOOKUP(Table_Investimentos_Main[[#This Row],[Ticker]],Table_Cotacoes[Ticker],Table_Cotacoes[Moeda Base],""),"BRL") -> BRL | J22: {=_xlfn.SINGLE(_xlfn.XLOOKUP(Table_Investimentos_Main[[#This Row],[Data]]&"USD",Table_Cotacoes[Data]&Table_Cotacoes[Ticker],Table_Cotacoes[Valor],""))} -> 5.05 | K22: =IF(Table_Investimentos_Main[[#This Row],[Ticker]]<>"",Table_Investimentos_Main[[#This Row],[Quantidade]]*Table_Investimentos_Main[[#This Row],[Cotação Ativo]],Table_Investimentos_Main[[#This Row],[Quantidade]]) -> 15748.75
B23: 45200 | C23: USDT | D23: USD | E23: Binance | G23: 1017.85 | H23: {=_xlfn.XLOOKUP(Table_Investimentos_Main[[#This Row],[Data]]&Table_Investimentos_Main[[#This Row],[Ticker]],Table_Cotacoes[Data]&Table_Cotacoes[Ticker],Table_Cotacoes[Valor],"")} -> 5.05 | I23: =IF(Table_Investimentos_Main[[#This Row],[Ticker]]<>"",_xlfn.XLOOKUP(Table_Investimentos_Main[[#This Row],[Ticker]],Table_Cotacoes[Ticker],Table_Cotacoes[Moeda Base],""),"BRL") -> USD | J23: {=_xlfn.SINGLE(_xlfn.XLOOKUP(Table_Investimentos_Main[[#This Row],[Data]]&"USD",Table_Cotacoes[Data]&Table_Cotacoes[Ticker],Table_Cotacoes[Valor],""))} -> 5.05 | K23: =IF(Table_Investimentos_Main[[#This Row],[Ticker]]<>"",Table_Investimentos_Main[[#This Row],[Quantidade]]*Table_Investimentos_Main[[#This Row],[Cotação Ativo]],Table_Investimentos_Main[[#This Row],[Quantidade]]) -> 5140.1425
B24: 45200 | C24: BUSD | D24: USD | E24: Binance | G24: 2531.36 | H24: {=_xlfn.XLOOKUP(Table_Investimentos_Main[[#This Row],[Data]]&Table_Investimentos_Main[[#This Row],[Ticker]],Table_Cotacoes[Data]&Table_Cotacoes[Ticker],Table_Cotacoes[Valor],"")} -> 5.05 | I24: =IF(Table_Investimentos_Main[[#This Row],[Ticker]]<>"",_xlfn.XLOOKUP(Table_Investimentos_Main[[#This Row],[Ticker]],Table_Cotacoes[Ticker],Table_Cotacoes[Moeda Base],""),"BRL") -> USD | J24: {=_xlfn.SINGLE(_xlfn.XLOOKUP(Table_Investimentos_Main[[#This Row],[Data]]&"USD",Table_Cotacoes[Data]&Table_Cotacoes[Ticker],Table_Cotacoes[Valor],""))} -> 5.05 | K24: =IF(Table_Investimentos_Main[[#This Row],[Ticker]]<>"",Table_Investimentos_Main[[#This Row],[Quantidade]]*Table_Investimentos_Main[[#This Row],[Cotação Ativo]],Table_Investimentos_Main[[#This Row],[Quantidade]]) -> 12783.368
B25: 45200 | C25: C6- Parado | E25: C6 | G25: 30.62 | H25: {=_xlfn.XLOOKUP(Table_Investimentos_Main[[#This Row],[Data]]&Table_Investimentos_Main[[#This Row],[Ticker]],Table_Cotacoes[Data]&Table_Cotacoes[Ticker],Table_Cotacoes[Valor],"")} | I25: =IF(Table_Investimentos_Main[[#This Row],[Ticker]]<>"",_xlfn.XLOOKUP(Table_Investimentos_Main[[#This Row],[Ticker]],Table_Cotacoes[Ticker],Table_Cotacoes[Moeda Base],""),"BRL") -> BRL | J25: {=_xlfn.SINGLE(_xlfn.XLOOKUP(Table_Investimentos_Main[[#This Row],[Data]]&"USD",Table_Cotacoes[Data]&Table_Cotacoes[Ticker],Table_Cotacoes[Valor],""))} -> 5.05 | K25: =IF(Table_Investimentos_Main[[#This Row],[Ticker]]<>"",Table_Investimentos_Main[[#This Row],[Quantidade]]*Table_Investimentos_Main[[#This Row],[Cotação Ativo]],Table_Investimentos_Main[[#This Row],[Quantidade]]) -> 30.62
B26: 45200 | C26: Dolar | D26: USD | E26: Inter | G26: 39.94 | H26: {=_xlfn.XLOOKUP(Table_Investimentos_Main[[#This Row],[Data]]&Table_Investimentos_Main[[#This Row],[Ticker]],Table_Cotacoes[Data]&Table_Cotacoes[Ticker],Table_Cotacoes[Valor],"")} -> 5.05 | I26: =IF(Table_Investimentos_Main[[#This Row],[Ticker]]<>"",_xlfn.XLOOKUP(Table_Investimentos_Main[[#This Row],[Ticker]],Table_Cotacoes[Ticker],Table_Cotacoes[Moeda Base],""),"BRL") -> USD | J26: {=_xlfn.SINGLE(_xlfn.XLOOKUP(Table_Investimentos_Main[[#This Row],[Data]]&"USD",Table_Cotacoes[Data]&Table_Cotacoes[Ticker],Table_Cotacoes[Valor],""))} -> 5.05 | K26: =IF(Table_Investimentos_Main[[#This Row],[Ticker]]<>"",Table_Investimentos_Main[[#This Row],[Quantidade]]*Table_Investimentos_Main[[#This Row],[Cotação Ativo]],Table_Investimentos_Main[[#This Row],[Quantidade]]) -> 201.697
B27: 45261 | C27: USDT | D27: USD | E27: Binance | G27: 1025.86 | H27: {=_xlfn.XLOOKUP(Table_Investimentos_Main[[#This Row],[Data]]&Table_Investimentos_Main[[#This Row],[Ticker]],Table_Cotacoes[Data]&Table_Cotacoes[Ticker],Table_Cotacoes[Valor],"")} -> 4.95 | I27: =IF(Table_Investimentos_Main[[#This Row],[Ticker]]<>"",_xlfn.XLOOKUP(Table_Investimentos_Main[[#This Row],[Ticker]],Table_Cotacoes[Ticker],Table_Cotacoes[Moeda Base],""),"BRL") -> USD | J27: {=_xlfn.SINGLE(_xlfn.XLOOKUP(Table_Investimentos_Main[[#This Row],[Data]]&"USD",Table_Cotacoes[Data]&Table_Cotacoes[Ticker],Table_Cotacoes[Valor],""))} -> 4.95 | K27: =IF(Table_Investimentos_Main[[#This Row],[Ticker]]<>"",Table_Investimentos_Main[[#This Row],[Quantidade]]*Table_Investimentos_Main[[#This Row],[Cotação Ativo]],Table_Investimentos_Main[[#This Row],[Quantidade]]) -> 5078.007
B28: 45261 | C28: BUSD | D28: USD | E28: Binance | G28: 2539.94 | H28: {=_xlfn.XLOOKUP(Table_Investimentos_Main[[#This Row],[Data]]&Table_Investimentos_Main[[#This Row],[Ticker]],Table_Cotacoes[Data]&Table_Cotacoes[Ticker],Table_Cotacoes[Valor],"")} -> 4.95 | I28: =IF(Table_Investimentos_Main[[#This Row],[Ticker]]<>"",_xlfn.XLOOKUP(Table_Investimentos_Main[[#This Row],[Ticker]],Table_Cotacoes[Ticker],Table_Cotacoes[Moeda Base],""),"BRL") -> USD | J28: {=_xlfn.SINGLE(_xlfn.XLOOKUP(Table_Investimentos_Main[[#This Row],[Data]]&"USD",Table_Cotacoes[Data]&Table_Cotacoes[Ticker],Table_Cotacoes[Valor],""))} -> 4.95 | K28: =IF(Table_Investimentos_Main[[#This Row],[Ticker]]<>"",Table_Investimentos_Main[[#This Row],[Quantidade]]*Table_Investimentos_Main[[#This Row],[Cotação Ativo]],Table_Investimentos_Main[[#This Row],[Quantidade]]) -> 12572.703
B29: 45261 | C29: Conta Bancária | E29: C6 | G29: 471.12 | H29: {=_xlfn.XLOOKUP(Table_Investimentos_Main[[#This Row],[Data]]&Table_Investimentos_Main[[#This Row],[Ticker]],Table_Cotacoes[Data]&Table_Cotacoes[Ticker],Table_Cotacoes[Valor],"")} | I29: =IF(Table_Investimentos_Main[[#This Row],[Ticker]]<>"",_xlfn.XLOOKUP(Table_Investimentos_Main[[#This Row],[Ticker]],Table_Cotacoes[Ticker],Table_Cotacoes[Moeda Base],""),"BRL") -> BRL | J29: {=_xlfn.SINGLE(_xlfn.XLOOKUP(Table_Investimentos_Main[[#This Row],[Data]]&"USD",Table_Cotacoes[Data]&Table_Cotacoes[Ticker],Table_Cotacoes[Valor],""))} -> 4.95 | K29: =IF(Table_Investimentos_Main[[#This Row],[Ticker]]<>"",Table_Investimentos_Main[[#This Row],[Quantidade]]*Table_Investimentos_Main[[#This Row],[Cotação Ativo]],Table_Investimentos_Main[[#This Row],[Quantidade]]) -> 471.12
B30: 45261 | C30: Dólar | D30: USD | E30: Inter | G30: 39.94 | H30: {=_xlfn.XLOOKUP(Table_Investimentos_Main[[#This Row],[Data]]&Table_Investimentos_Main[[#This Row],[Ticker]],Table_Cotacoes[Data]&Table_Cotacoes[Ticker],Table_Cotacoes[Valor],"")} -> 4.95 | I30: =IF(Table_Investimentos_Main[[#This Row],[Ticker]]<>"",_xlfn.XLOOKUP(Table_Investimentos_Main[[#This Row],[Ticker]],Table_Cotacoes[Ticker],Table_Cotacoes[Moeda Base],""),"BRL") -> USD | J30: {=_xlfn.SINGLE(_xlfn.XLOOKUP(Table_Investimentos_Main[[#This Row],[Data]]&"USD",Table_Cotacoes[Data]&Table_Cotacoes[Ticker],Table_Cotacoes[Valor],""))} -> 4.95 | K30: =IF(Table_Investimentos_Main[[#This Row],[Ticker]]<>"",Table_Investimentos_Main[[#This Row],[Quantidade]]*Table_Investimentos_Main[[#This Row],[Cotação Ativo]],Table_Investimentos_Main[[#This Row],[Quantidade]]) -> 197.703
B31: 45261 | C31: Bitcoin | D31: BTC | E31: Binance | G31: 0.01745788 | H31: {=_xlfn.XLOOKUP(Table_Investimentos_Main[[#This Row],[Data]]&Table_Investimentos_Main[[#This Row],[Ticker]],Table_Cotacoes[Data]&Table_Cotacoes[Ticker],Table_Cotacoes[Valor],"")} -> 207740.79 | I31: =IF(Table_Investimentos_Main[[#This Row],[Ticker]]<>"",_xlfn.XLOOKUP(Table_Investimentos_Main[[#This Row],[Ticker]],Table_Cotacoes[Ticker],Table_Cotacoes[Moeda Base],""),"BRL") -> BTC | J31: {=_xlfn.SINGLE(_xlfn.XLOOKUP(Table_Investimentos_Main[[#This Row],[Data]]&"USD",Table_Cotacoes[Data]&Table_Cotacoes[Ticker],Table_Cotacoes[Valor],""))} -> 4.95 | K31: =IF(Table_Investimentos_Main[[#This Row],[Ticker]]<>"",Table_Investimentos_Main[[#This Row],[Quantidade]]*Table_Investimentos_Main[[#This Row],[Cotação Ativo]],Table_Investimentos_Main[[#This Row],[Quantidade]]) -> 3626.7138
B32: 45261 | C32: Bitcoin | D32: BTC | E32: Ledger | G32: 0.179195 | H32: {=_xlfn.XLOOKUP(Table_Investimentos_Main[[#This Row],[Data]]&Table_Investimentos_Main[[#This Row],[Ticker]],Table_Cotacoes[Data]&Table_Cotacoes[Ticker],Table_Cotacoes[Valor],"")} -> 207740.79 | I32: =IF(Table_Investimentos_Main[[#This Row],[Ticker]]<>"",_xlfn.XLOOKUP(Table_Investimentos_Main[[#This Row],[Ticker]],Table_Cotacoes[Ticker],Table_Cotacoes[Moeda Base],""),"BRL") -> BTC | J32: {=_xlfn.SINGLE(_xlfn.XLOOKUP(Table_Investimentos_Main[[#This Row],[Data]]&"USD",Table_Cotacoes[Data]&Table_Cotacoes[Ticker],Table_Cotacoes[Valor],""))} -> 4.95 | K32: =IF(Table_Investimentos_Main[[#This Row],[Ticker]]<>"",Table_Investimentos_Main[[#This Row],[Quantidade]]*Table_Investimentos_Main[[#This Row],[Cotação Ativo]],Table_Investimentos_Main[[#This Row],[Quantidade]]) -> 37226.111
B33: 45261 | C33: CDB Diario 105% | E33: C6 | G33: 11887.95 | H33: {=_xlfn.XLOOKUP(Table_Investimentos_Main[[#This Row],[Data]]&Table_Investimentos_Main[[#This Row],[Ticker]],Table_Cotacoes[Data]&Table_Cotacoes[Ticker],Table_Cotacoes[Valor],"")} | I33: =IF(Table_Investimentos_Main[[#This Row],[Ticker]]<>"",_xlfn.XLOOKUP(Table_Investimentos_Main[[#This Row],[Ticker]],Table_Cotacoes[Ticker],Table_Cotacoes[Moeda Base],""),"BRL") -> BRL | J33: {=_xlfn.SINGLE(_xlfn.XLOOKUP(Table_Investimentos_Main[[#This Row],[Data]]&"USD",Table_Cotacoes[Data]&Table_Cotacoes[Ticker],Table_Cotacoes[Valor],""))} -> 4.95 | K33: =IF(Table_Investimentos_Main[[#This Row],[Ticker]]<>"",Table_Investimentos_Main[[#This Row],[Quantidade]]*Table_Investimentos_Main[[#This Row],[Cotação Ativo]],Table_Investimentos_Main[[#This Row],[Quantidade]]) -> 11887.95
B34: 45261 | C34: CDB Cartao 100% | E34: C6 | G34: 2567.31 | H34: {=_xlfn.XLOOKUP(Table_Investimentos_Main[[#This Row],[Data]]&Table_Investimentos_Main[[#This Row],[Ticker]],Table_Cotacoes[Data]&Table_Cotacoes[Ticker],Table_Cotacoes[Valor],"")} | I34: =IF(Table_Investimentos_Main[[#This Row],[Ticker]]<>"",_xlfn.XLOOKUP(Table_Investimentos_Main[[#This Row],[Ticker]],Table_Cotacoes[Ticker],Table_Cotacoes[Moeda Base],""),"BRL") -> BRL | J34: {=_xlfn.SINGLE(_xlfn.XLOOKUP(Table_Investimentos_Main[[#This Row],[Data]]&"USD",Table_Cotacoes[Data]&Table_Cotacoes[Ticker],Table_Cotacoes[Valor],""))} -> 4.95 | K34: =IF(Table_Investimentos_Main[[#This Row],[Ticker]]<>"",Table_Investimentos_Main[[#This Row],[Quantidade]]*Table_Investimentos_Main[[#This Row],[Cotação Ativo]],Table_Investimentos_Main[[#This Row],[Quantidade]]) -> 2567.31
B35: 45261 | C35: LCI DI 180 | E35: Inter | G35: 15900.21 | H35: {=_xlfn.XLOOKUP(Table_Investimentos_Main[[#This Row],[Data]]&Table_Investimentos_Main[[#This Row],[Ticker]],Table_Cotacoes[Data]&Table_Cotacoes[Ticker],Table_Cotacoes[Valor],"")} | I35: =IF(Table_Investimentos_Main[[#This Row],[Ticker]]<>"",_xlfn.XLOOKUP(Table_Investimentos_Main[[#This Row],[Ticker]],Table_Cotacoes[Ticker],Table_Cotacoes[Moeda Base],""),"BRL") -> BRL | J35: {=_xlfn.SINGLE(_xlfn.XLOOKUP(Table_Investimentos_Main[[#This Row],[Data]]&"USD",Table_Cotacoes[Data]&Table_Cotacoes[Ticker],Table_Cotacoes[Valor],""))} -> 4.95 | K35: =IF(Table_Investimentos_Main[[#This Row],[Ticker]]<>"",Table_Investimentos_Main[[#This Row],[Quantidade]]*Table_Investimentos_Main[[#This Row],[Cotação Ativo]],Table_Investimentos_Main[[#This Row],[Quantidade]]) -> 15900.21
B36: 45292 | C36: USDT | D36: USD | E36: Binance | G36: 1044.7 | H36: {=_xlfn.XLOOKUP(Table_Investimentos_Main[[#This Row],[Data]]&Table_Investimentos_Main[[#This Row],[Ticker]],Table_Cotacoes[Data]&Table_Cotacoes[Ticker],Table_Cotacoes[Valor],"")} -> 4.98 | I36: =IF(Table_Investimentos_Main[[#This Row],[Ticker]]<>"",_xlfn.XLOOKUP(Table_Investimentos_Main[[#This Row],[Ticker]],Table_Cotacoes[Ticker],Table_Cotacoes[Moeda Base],""),"BRL") -> USD | J36: {=_xlfn.SINGLE(_xlfn.XLOOKUP(Table_Investimentos_Main[[#This Row],[Data]]&"USD",Table_Cotacoes[Data]&Table_Cotacoes[Ticker],Table_Cotacoes[Valor],""))} -> 4.98 | K36: =IF(Table_Investimentos_Main[[#This Row],[Ticker]]<>"",Table_Investimentos_Main[[#This Row],[Quantidade]]*Table_Investimentos_Main[[#This Row],[Cotação Ativo]],Table_Investimentos_Main[[#This Row],[Quantidade]]) -> 5202.606
B37: 45292 | C37: BUSD | D37: USD | E37: Binance | G37: 2568.18 | H37: {=_xlfn.XLOOKUP(Table_Investimentos_Main[[#This Row],[Data]]&Table_Investimentos_Main[[#This Row],[Ticker]],Table_Cotacoes[Data]&Table_Cotacoes[Ticker],Table_Cotacoes[Valor],"")} -> 4.98 | I37: =IF(Table_Investimentos_Main[[#This Row],[Ticker]]<>"",_xlfn.XLOOKUP(Table_Investimentos_Main[[#This Row],[Ticker]],Table_Cotacoes[Ticker],Table_Cotacoes[Moeda Base],""),"BRL") -> USD | J37: {=_xlfn.SINGLE(_xlfn.XLOOKUP(Table_Investimentos_Main[[#This Row],[Data]]&"USD",Table_Cotacoes[Data]&Table_Cotacoes[Ticker],Table_Cotacoes[Valor],""))} -> 4.98 | K37: =IF(Table_Investimentos_Main[[#This Row],[Ticker]]<>"",Table_Investimentos_Main[[#This Row],[Quantidade]]*Table_Investimentos_Main[[#This Row],[Cotação Ativo]],Table_Investimentos_Main[[#This Row],[Quantidade]]) -> 12789.536
B38: 45292 | C38: Conta Bancária | E38: C6 | G38: 366.73 | H38: {=_xlfn.XLOOKUP(Table_Investimentos_Main[[#This Row],[Data]]&Table_Investimentos_Main[[#This Row],[Ticker]],Table_Cotacoes[Data]&Table_Cotacoes[Ticker],Table_Cotacoes[Valor],"")} | I38: =IF(Table_Investimentos_Main[[#This Row],[Ticker]]<>"",_xlfn.XLOOKUP(Table_Investimentos_Main[[#This Row],[Ticker]],Table_Cotacoes[Ticker],Table_Cotacoes[Moeda Base],""),"BRL") -> BRL | J38: {=_xlfn.SINGLE(_xlfn.XLOOKUP(Table_Investimentos_Main[[#This Row],[Data]]&"USD",Table_Cotacoes[Data]&Table_Cotacoes[Ticker],Table_Cotacoes[Valor],""))} -> 4.98 | K38: =IF(Table_Investimentos_Main[[#This Row],[Ticker]]<>"",Table_Investimentos_Main[[#This Row],[Quantidade]]*Table_Investimentos_Main[[#This Row],[Cotação Ativo]],Table_Investimentos_Main[[#This Row],[Quantidade]]) -> 366.73
B39: 45292 | C39: Dólar | D39: USD | E39: Inter | G39: 39.94 | H39: {=_xlfn.XLOOKUP(Table_Investimentos_Main[[#This Row],[Data]]&Table_Investimentos_Main[[#This Row],[Ticker]],Table_Cotacoes[Data]&Table_Cotacoes[Ticker],Table_Cotacoes[Valor],"")} -> 4.98 | I39: =IF(Table_Investimentos_Main[[#This Row],[Ticker]]<>"",_xlfn.XLOOKUP(Table_Investimentos_Main[[#This Row],[Ticker]],Table_Cotacoes[Ticker],Table_Cotacoes[Moeda Base],""),"BRL") -> USD | J39: {=_xlfn.SINGLE(_xlfn.XLOOKUP(Table_Investimentos_Main[[#This Row],[Data]]&"USD",Table_Cotacoes[Data]&Table_Cotacoes[Ticker],Table_Cotacoes[Valor],""))} -> 4.98 | K39: =IF(Table_Investimentos_Main[[#This Row],[Ticker]]<>"",Table_Investimentos_Main[[#This Row],[Quantidade]]*Table_Investimentos_Main[[#This Row],[Cotação Ativo]],Table_Investimentos_Main[[#This Row],[Quantidade]]) -> 198.9012
B40: 45292 | C40: Bitcoin | D40: BTC | E40: Binance | G40: 0.02 | H40: {=_xlfn.XLOOKUP(Table_Investimentos_Main[[#This Row],[Data]]&Table_Investimentos_Main[[#This Row],[Ticker]],Table_Cotacoes[Data]&Table_Cotacoes[Ticker],Table_Cotacoes[Valor],"")} -> 213280 | I40: =IF(Table_Investimentos_Main[[#This Row],[Ticker]]<>"",_xlfn.XLOOKUP(Table_Investimentos_Main[[#This Row],[Ticker]],Table_Cotacoes[Ticker],Table_Cotacoes[Moeda Base],""),"BRL") -> BTC | J40: {=_xlfn.SINGLE(_xlfn.XLOOKUP(Table_Investimentos_Main[[#This Row],[Data]]&"USD",Table_Cotacoes[Data]&Table_Cotacoes[Ticker],Table_Cotacoes[Valor],""))} -> 4.98 | K40: =IF(Table_Investimentos_Main[[#This Row],[Ticker]]<>"",Table_Investimentos_Main[[#This Row],[Quantidade]]*Table_Investimentos_Main[[#This Row],[Cotação Ativo]],Table_Investimentos_Main[[#This Row],[Quantidade]]) -> 4265.6
B41: 45292 | C41: Bitcoin | D41: BTC | E41: Carteira Cripto | G41: 0.18 | H41: {=_xlfn.XLOOKUP(Table_Investimentos_Main[[#This Row],[Data]]&Table_Investimentos_Main[[#This Row],[Ticker]],Table_Cotacoes[Data]&Table_Cotacoes[Ticker],Table_Cotacoes[Valor],"")} -> 213280 | I41: =IF(Table_Investimentos_Main[[#This Row],[Ticker]]<>"",_xlfn.XLOOKUP(Table_Investimentos_Main[[#This Row],[Ticker]],Table_Cotacoes[Ticker],Table_Cotacoes[Moeda Base],""),"BRL") -> BTC | J41: {=_xlfn.SINGLE(_xlfn.XLOOKUP(Table_Investimentos_Main[[#This Row],[Data]]&"USD",Table_Cotacoes[Data]&Table_Cotacoes[Ticker],Table_Cotacoes[Valor],""))} -> 4.98 | K41: =IF(Table_Investimentos_Main[[#This Row],[Ticker]]<>"",Table_Investimentos_Main[[#This Row],[Quantidade]]*Table_Investimentos_Main[[#This Row],[Cotação Ativo]],Table_Investimentos_Main[[#This Row],[Quantidade]]) -> 38390.4
B42: 45292 | C42: CDB Diario 105% | E42: C6 | G42: 29644.52 | H42: {=_xlfn.XLOOKUP(Table_Investimentos_Main[[#This Row],[Data]]&Table_Investimentos_Main[[#This Row],[Ticker]],Table_Cotacoes[Data]&Table_Cotacoes[Ticker],Table_Cotacoes[Valor],"")} | I42: =IF(Table_Investimentos_Main[[#This Row],[Ticker]]<>"",_xlfn.XLOOKUP(Table_Investimentos_Main[[#This Row],[Ticker]],Table_Cotacoes[Ticker],Table_Cotacoes[Moeda Base],""),"BRL") -> BRL | J42: {=_xlfn.SINGLE(_xlfn.XLOOKUP(Table_Investimentos_Main[[#This Row],[Data]]&"USD",Table_Cotacoes[Data]&Table_Cotacoes[Ticker],Table_Cotacoes[Valor],""))} -> 4.98 | K42: =IF(Table_Investimentos_Main[[#This Row],[Ticker]]<>"",Table_Investimentos_Main[[#This Row],[Quantidade]]*Table_Investimentos_Main[[#This Row],[Cotação Ativo]],Table_Investimentos_Main[[#This Row],[Quantidade]]) -> 29644.52
B43: 45292 | C43: CDB Cartao 100% | E43: C6 | G43: 2910.35 | H43: {=_xlfn.XLOOKUP(Table_Investimentos_Main[[#This Row],[Data]]&Table_Investimentos_Main[[#This Row],[Ticker]],Table_Cotacoes[Data]&Table_Cotacoes[Ticker],Table_Cotacoes[Valor],"")} | I43: =IF(Table_Investimentos_Main[[#This Row],[Ticker]]<>"",_xlfn.XLOOKUP(Table_Investimentos_Main[[#This Row],[Ticker]],Table_Cotacoes[Ticker],Table_Cotacoes[Moeda Base],""),"BRL") -> BRL | J43: {=_xlfn.SINGLE(_xlfn.XLOOKUP(Table_Investimentos_Main[[#This Row],[Data]]&"USD",Table_Cotacoes[Data]&Table_Cotacoes[Ticker],Table_Cotacoes[Valor],""))} -> 4.98 | K43: =IF(Table_Investimentos_Main[[#This Row],[Ticker]]<>"",Table_Investimentos_Main[[#This Row],[Quantidade]]*Table_Investimentos_Main[[#This Row],[Cotação Ativo]],Table_Investimentos_Main[[#This Row],[Quantidade]]) -> 2910.35
B44: 45323 | C44: CDB Cartao 100% | E44: C6 | G44: 2916.4 | H44: {=_xlfn.XLOOKUP(Table_Investimentos_Main[[#This Row],[Data]]&Table_Investimentos_Main[[#This Row],[Ticker]],Table_Cotacoes[Data]&Table_Cotacoes[Ticker],Table_Cotacoes[Valor],"")} | I44: =IF(Table_Investimentos_Main[[#This Row],[Ticker]]<>"",_xlfn.XLOOKUP(Table_Investimentos_Main[[#This Row],[Ticker]],Table_Cotacoes[Ticker],Table_Cotacoes[Moeda Base],""),"BRL") -> BRL | J44: {=_xlfn.SINGLE(_xlfn.XLOOKUP(Table_Investimentos_Main[[#This Row],[Data]]&"USD",Table_Cotacoes[Data]&Table_Cotacoes[Ticker],Table_Cotacoes[Valor],""))} -> 4.97 | K44: =IF(Table_Investimentos_Main[[#This Row],[Ticker]]<>"",Table_Investimentos_Main[[#This Row],[Quantidade]]*Table_Investimentos_Main[[#This Row],[Cotação Ativo]],Table_Investimentos_Main[[#This Row],[Quantidade]]) -> 2916.4
B45: 45323 | C45: CDB Diario 105% | E45: C6 | G45: 19156.67 | H45: {=_xlfn.XLOOKUP(Table_Investimentos_Main[[#This Row],[Data]]&Table_Investimentos_Main[[#This Row],[Ticker]],Table_Cotacoes[Data]&Table_Cotacoes[Ticker],Table_Cotacoes[Valor],"")} | I45: =IF(Table_Investimentos_Main[[#This Row],[Ticker]]<>"",_xlfn.XLOOKUP(Table_Investimentos_Main[[#This Row],[Ticker]],Table_Cotacoes[Ticker],Table_Cotacoes[Moeda Base],""),"BRL") -> BRL | J45: {=_xlfn.SINGLE(_xlfn.XLOOKUP(Table_Investimentos_Main[[#This Row],[Data]]&"USD",Table_Cotacoes[Data]&Table_Cotacoes[Ticker],Table_Cotacoes[Valor],""))} -> 4.97 | K45: =IF(Table_Investimentos_Main[[#This Row],[Ticker]]<>"",Table_Investimentos_Main[[#This Row],[Quantidade]]*Table_Investimentos_Main[[#This Row],[Cotação Ativo]],Table_Investimentos_Main[[#This Row],[Quantidade]]) -> 19156.67
B46: 45323 | C46: Conta Bancária | E46: C6 | G46: 470.37 | H46: {=_xlfn.XLOOKUP(Table_Investimentos_Main[[#This Row],[Data]]&Table_Investimentos_Main[[#This Row],[Ticker]],Table_Cotacoes[Data]&Table_Cotacoes[Ticker],Table_Cotacoes[Valor],"")} | I46: =IF(Table_Investimentos_Main[[#This Row],[Ticker]]<>"",_xlfn.XLOOKUP(Table_Investimentos_Main[[#This Row],[Ticker]],Table_Cotacoes[Ticker],Table_Cotacoes[Moeda Base],""),"BRL") -> BRL | J46: {=_xlfn.SINGLE(_xlfn.XLOOKUP(Table_Investimentos_Main[[#This Row],[Data]]&"USD",Table_Cotacoes[Data]&Table_Cotacoes[Ticker],Table_Cotacoes[Valor],""))} -> 4.97 | K46: =IF(Table_Investimentos_Main[[#This Row],[Ticker]]<>"",Table_Investimentos_Main[[#This Row],[Quantidade]]*Table_Investimentos_Main[[#This Row],[Cotação Ativo]],Table_Investimentos_Main[[#This Row],[Quantidade]]) -> 470.37
B47: 45323 | C47: Extra XP | E47: XP | G47: 148.08 | H47: {=_xlfn.XLOOKUP(Table_Investimentos_Main[[#This Row],[Data]]&Table_Investimentos_Main[[#This Row],[Ticker]],Table_Cotacoes[Data]&Table_Cotacoes[Ticker],Table_Cotacoes[Valor],"")} | I47: =IF(Table_Investimentos_Main[[#This Row],[Ticker]]<>"",_xlfn.XLOOKUP(Table_Investimentos_Main[[#This Row],[Ticker]],Table_Cotacoes[Ticker],Table_Cotacoes[Moeda Base],""),"BRL") -> BRL | J47: {=_xlfn.SINGLE(_xlfn.XLOOKUP(Table_Investimentos_Main[[#This Row],[Data]]&"USD",Table_Cotacoes[Data]&Table_Cotacoes[Ticker],Table_Cotacoes[Valor],""))} -> 4.97 | K47: =IF(Table_Investimentos_Main[[#This Row],[Ticker]]<>"",Table_Investimentos_Main[[#This Row],[Quantidade]]*Table_Investimentos_Main[[#This Row],[Cotação Ativo]],Table_Investimentos_Main[[#This Row],[Quantidade]]) -> 148.08
B48: 45323 | C48: LCI XP | E48: XP | G48: 9851.92 | H48: {=_xlfn.XLOOKUP(Table_Investimentos_Main[[#This Row],[Data]]&Table_Investimentos_Main[[#This Row],[Ticker]],Table_Cotacoes[Data]&Table_Cotacoes[Ticker],Table_Cotacoes[Valor],"")} | I48: =IF(Table_Investimentos_Main[[#This Row],[Ticker]]<>"",_xlfn.XLOOKUP(Table_Investimentos_Main[[#This Row],[Ticker]],Table_Cotacoes[Ticker],Table_Cotacoes[Moeda Base],""),"BRL") -> BRL | J48: {=_xlfn.SINGLE(_xlfn.XLOOKUP(Table_Investimentos_Main[[#This Row],[Data]]&"USD",Table_Cotacoes[Data]&Table_Cotacoes[Ticker],Table_Cotacoes[Valor],""))} -> 4.97 | K48: =IF(Table_Investimentos_Main[[#This Row],[Ticker]]<>"",Table_Investimentos_Main[[#This Row],[Quantidade]]*Table_Investimentos_Main[[#This Row],[Cotação Ativo]],Table_Investimentos_Main[[#This Row],[Quantidade]]) -> 9851.92
B49: 45323 | C49: Bitcoin 01 | D49: BTC | E49: Ledger | G49: 0.179195 | H49: {=_xlfn.XLOOKUP(Table_Investimentos_Main[[#This Row],[Data]]&Table_Investimentos_Main[[#This Row],[Ticker]],Table_Cotacoes[Data]&Table_Cotacoes[Ticker],Table_Cotacoes[Valor],"")} -> 258315 | I49: =IF(Table_Investimentos_Main[[#This Row],[Ticker]]<>"",_xlfn.XLOOKUP(Table_Investimentos_Main[[#This Row],[Ticker]],Table_Cotacoes[Ticker],Table_Cotacoes[Moeda Base],""),"BRL") -> BTC | J49: {=_xlfn.SINGLE(_xlfn.XLOOKUP(Table_Investimentos_Main[[#This Row],[Data]]&"USD",Table_Cotacoes[Data]&Table_Cotacoes[Ticker],Table_Cotacoes[Valor],""))} -> 4.97 | K49: =IF(Table_Investimentos_Main[[#This Row],[Ticker]]<>"",Table_Investimentos_Main[[#This Row],[Quantidade]]*Table_Investimentos_Main[[#This Row],[Cotação Ativo]],Table_Investimentos_Main[[#This Row],[Quantidade]]) -> 46288.756
B50: 45323 | C50: Bitcoin 02 | D50: BTC | E50: Binance | G50: 0.01745788 | H50: {=_xlfn.XLOOKUP(Table_Investimentos_Main[[#This Row],[Data]]&Table_Investimentos_Main[[#This Row],[Ticker]],Table_Cotacoes[Data]&Table_Cotacoes[Ticker],Table_Cotacoes[Valor],"")} -> 258315 | I50: =IF(Table_Investimentos_Main[[#This Row],[Ticker]]<>"",_xlfn.XLOOKUP(Table_Investimentos_Main[[#This Row],[Ticker]],Table_Cotacoes[Ticker],Table_Cotacoes[Moeda Base],""),"BRL") -> BTC | J50: {=_xlfn.SINGLE(_xlfn.XLOOKUP(Table_Investimentos_Main[[#This Row],[Data]]&"USD",Table_Cotacoes[Data]&Table_Cotacoes[Ticker],Table_Cotacoes[Valor],""))} -> 4.97 | K50: =IF(Table_Investimentos_Main[[#This Row],[Ticker]]<>"",Table_Investimentos_Main[[#This Row],[Quantidade]]*Table_Investimentos_Main[[#This Row],[Cotação Ativo]],Table_Investimentos_Main[[#This Row],[Quantidade]]) -> 4509.6323
B51: 45323 | C51: Bitcoin 03 | D51: BTC | E51: Binance | G51: 0.00769491 | H51: {=_xlfn.XLOOKUP(Table_Investimentos_Main[[#This Row],[Data]]&Table_Investimentos_Main[[#This Row],[Ticker]],Table_Cotacoes[Data]&Table_Cotacoes[Ticker],Table_Cotacoes[Valor],"")} -> 258315 | I51: =IF(Table_Investimentos_Main[[#This Row],[Ticker]]<>"",_xlfn.XLOOKUP(Table_Investimentos_Main[[#This Row],[Ticker]],Table_Cotacoes[Ticker],Table_Cotacoes[Moeda Base],""),"BRL") -> BTC | J51: {=_xlfn.SINGLE(_xlfn.XLOOKUP(Table_Investimentos_Main[[#This Row],[Data]]&"USD",Table_Cotacoes[Data]&Table_Cotacoes[Ticker],Table_Cotacoes[Valor],""))} -> 4.97 | K51: =IF(Table_Investimentos_Main[[#This Row],[Ticker]]<>"",Table_Investimentos_Main[[#This Row],[Quantidade]]*Table_Investimentos_Main[[#This Row],[Cotação Ativo]],Table_Investimentos_Main[[#This Row],[Quantidade]]) -> 1987.7107
B52: 45323 | C52: USDC | D52: USD | E52: Binance | G52: 3620.55 | H52: {=_xlfn.XLOOKUP(Table_Investimentos_Main[[#This Row],[Data]]&Table_Investimentos_Main[[#This Row],[Ticker]],Table_Cotacoes[Data]&Table_Cotacoes[Ticker],Table_Cotacoes[Valor],"")} -> 4.97 | I52: =IF(Table_Investimentos_Main[[#This Row],[Ticker]]<>"",_xlfn.XLOOKUP(Table_Investimentos_Main[[#This Row],[Ticker]],Table_Cotacoes[Ticker],Table_Cotacoes[Moeda Base],""),"BRL") -> USD | J52: {=_xlfn.SINGLE(_xlfn.XLOOKUP(Table_Investimentos_Main[[#This Row],[Data]]&"USD",Table_Cotacoes[Data]&Table_Cotacoes[Ticker],Table_Cotacoes[Valor],""))} -> 4.97 | K52: =IF(Table_Investimentos_Main[[#This Row],[Ticker]]<>"",Table_Investimentos_Main[[#This Row],[Quantidade]]*Table_Investimentos_Main[[#This Row],[Cotação Ativo]],Table_Investimentos_Main[[#This Row],[Quantidade]]) -> 17994.133
B53: 45352 | C53: CDB Cartao 100% | E53: C6 | G53: 39.57 | H53: {=_xlfn.XLOOKUP(Table_Investimentos_Main[[#This Row],[Data]]&Table_Investimentos_Main[[#This Row],[Ticker]],Table_Cotacoes[Data]&Table_Cotacoes[Ticker],Table_Cotacoes[Valor],"")} | I53: =IF(Table_Investimentos_Main[[#This Row],[Ticker]]<>"",_xlfn.XLOOKUP(Table_Investimentos_Main[[#This Row],[Ticker]],Table_Cotacoes[Ticker],Table_Cotacoes[Moeda Base],""),"BRL") -> BRL | J53: {=_xlfn.SINGLE(_xlfn.XLOOKUP(Table_Investimentos_Main[[#This Row],[Data]]&"USD",Table_Cotacoes[Data]&Table_Cotacoes[Ticker],Table_Cotacoes[Valor],""))} -> 4.97 | K53: =IF(Table_Investimentos_Main[[#This Row],[Ticker]]<>"",Table_Investimentos_Main[[#This Row],[Quantidade]]*Table_Investimentos_Main[[#This Row],[Cotação Ativo]],Table_Investimentos_Main[[#This Row],[Quantidade]]) -> 39.57
B54: 45352 | C54: CDB Diario 105% | E54: C6 | G54: 21231.66 | H54: {=_xlfn.XLOOKUP(Table_Investimentos_Main[[#This Row],[Data]]&Table_Investimentos_Main[[#This Row],[Ticker]],Table_Cotacoes[Data]&Table_Cotacoes[Ticker],Table_Cotacoes[Valor],"")} | I54: =IF(Table_Investimentos_Main[[#This Row],[Ticker]]<>"",_xlfn.XLOOKUP(Table_Investimentos_Main[[#This Row],[Ticker]],Table_Cotacoes[Ticker],Table_Cotacoes[Moeda Base],""),"BRL") -> BRL | J54: {=_xlfn.SINGLE(_xlfn.XLOOKUP(Table_Investimentos_Main[[#This Row],[Data]]&"USD",Table_Cotacoes[Data]&Table_Cotacoes[Ticker],Table_Cotacoes[Valor],""))} -> 4.97 | K54: =IF(Table_Investimentos_Main[[#This Row],[Ticker]]<>"",Table_Investimentos_Main[[#This Row],[Quantidade]]*Table_Investimentos_Main[[#This Row],[Cotação Ativo]],Table_Investimentos_Main[[#This Row],[Quantidade]]) -> 21231.66
B55: 45352 | C55: Conta Bancária | E55: C6 | G55: 487.27 | H55: {=_xlfn.XLOOKUP(Table_Investimentos_Main[[#This Row],[Data]]&Table_Investimentos_Main[[#This Row],[Ticker]],Table_Cotacoes[Data]&Table_Cotacoes[Ticker],Table_Cotacoes[Valor],"")} | I55: =IF(Table_Investimentos_Main[[#This Row],[Ticker]]<>"",_xlfn.XLOOKUP(Table_Investimentos_Main[[#This Row],[Ticker]],Table_Cotacoes[Ticker],Table_Cotacoes[Moeda Base],""),"BRL") -> BRL | J55: {=_xlfn.SINGLE(_xlfn.XLOOKUP(Table_Investimentos_Main[[#This Row],[Data]]&"USD",Table_Cotacoes[Data]&Table_Cotacoes[Ticker],Table_Cotacoes[Valor],""))} -> 4.97 | K55: =IF(Table_Investimentos_Main[[#This Row],[Ticker]]<>"",Table_Investimentos_Main[[#This Row],[Quantidade]]*Table_Investimentos_Main[[#This Row],[Cotação Ativo]],Table_Investimentos_Main[[#This Row],[Quantidade]]) -> 487.27
B56: 45352 | C56: LCI XP | E56: XP | G56: 9933.05 | H56: {=_xlfn.XLOOKUP(Table_Investimentos_Main[[#This Row],[Data]]&Table_Investimentos_Main[[#This Row],[Ticker]],Table_Cotacoes[Data]&Table_Cotacoes[Ticker],Table_Cotacoes[Valor],"")} | I56: =IF(Table_Investimentos_Main[[#This Row],[Ticker]]<>"",_xlfn.XLOOKUP(Table_Investimentos_Main[[#This Row],[Ticker]],Table_Cotacoes[Ticker],Table_Cotacoes[Moeda Base],""),"BRL") -> BRL | J56: {=_xlfn.SINGLE(_xlfn.XLOOKUP(Table_Investimentos_Main[[#This Row],[Data]]&"USD",Table_Cotacoes[Data]&Table_Cotacoes[Ticker],Table_Cotacoes[Valor],""))} -> 4.97 | K56: =IF(Table_Investimentos_Main[[#This Row],[Ticker]]<>"",Table_Investimentos_Main[[#This Row],[Quantidade]]*Table_Investimentos_Main[[#This Row],[Cotação Ativo]],Table_Investimentos_Main[[#This Row],[Quantidade]]) -> 9933.05
B57: 45352 | C57: Bitcoin 01 | D57: BTC | E57: Carteira Cripto | G57: 0.179195 | H57: {=_xlfn.XLOOKUP(Table_Investimentos_Main[[#This Row],[Data]]&Table_Investimentos_Main[[#This Row],[Ticker]],Table_Cotacoes[Data]&Table_Cotacoes[Ticker],Table_Cotacoes[Valor],"")} -> 365000 | I57: =IF(Table_Investimentos_Main[[#This Row],[Ticker]]<>"",_xlfn.XLOOKUP(Table_Investimentos_Main[[#This Row],[Ticker]],Table_Cotacoes[Ticker],Table_Cotacoes[Moeda Base],""),"BRL") -> BTC | J57: {=_xlfn.SINGLE(_xlfn.XLOOKUP(Table_Investimentos_Main[[#This Row],[Data]]&"USD",Table_Cotacoes[Data]&Table_Cotacoes[Ticker],Table_Cotacoes[Valor],""))} -> 4.97 | K57: =IF(Table_Investimentos_Main[[#This Row],[Ticker]]<>"",Table_Investimentos_Main[[#This Row],[Quantidade]]*Table_Investimentos_Main[[#This Row],[Cotação Ativo]],Table_Investimentos_Main[[#This Row],[Quantidade]]) -> 65406.175
B58: 45352 | C58: USDC | D58: USD | E58: Binance | G58: 5282.2 | H58: {=_xlfn.XLOOKUP(Table_Investimentos_Main[[#This Row],[Data]]&Table_Investimentos_Main[[#This Row],[Ticker]],Table_Cotacoes[Data]&Table_Cotacoes[Ticker],Table_Cotacoes[Valor],"")} -> 4.97 | I58: =IF(Table_Investimentos_Main[[#This Row],[Ticker]]<>"",_xlfn.XLOOKUP(Table_Investimentos_Main[[#This Row],[Ticker]],Table_Cotacoes[Ticker],Table_Cotacoes[Moeda Base],""),"BRL") -> USD | J58: {=_xlfn.SINGLE(_xlfn.XLOOKUP(Table_Investimentos_Main[[#This Row],[Data]]&"USD",Table_Cotacoes[Data]&Table_Cotacoes[Ticker],Table_Cotacoes[Valor],""))} -> 4.97 | K58: =IF(Table_Investimentos_Main[[#This Row],[Ticker]]<>"",Table_Investimentos_Main[[#This Row],[Quantidade]]*Table_Investimentos_Main[[#This Row],[Cotação Ativo]],Table_Investimentos_Main[[#This Row],[Quantidade]]) -> 26252.534
B59: 45383 | C59: CDB Itaú 100% | E59: Itaú | G59: 30106.64 | H59: {=_xlfn.XLOOKUP(Table_Investimentos_Main[[#This Row],[Data]]&Table_Investimentos_Main[[#This Row],[Ticker]],Table_Cotacoes[Data]&Table_Cotacoes[Ticker],Table_Cotacoes[Valor],"")} | I59: =IF(Table_Investimentos_Main[[#This Row],[Ticker]]<>"",_xlfn.XLOOKUP(Table_Investimentos_Main[[#This Row],[Ticker]],Table_Cotacoes[Ticker],Table_Cotacoes[Moeda Base],""),"BRL") -> BRL | J59: {=_xlfn.SINGLE(_xlfn.XLOOKUP(Table_Investimentos_Main[[#This Row],[Data]]&"USD",Table_Cotacoes[Data]&Table_Cotacoes[Ticker],Table_Cotacoes[Valor],""))} -> 5.1163 | K59: =IF(Table_Investimentos_Main[[#This Row],[Ticker]]<>"",Table_Investimentos_Main[[#This Row],[Quantidade]]*Table_Investimentos_Main[[#This Row],[Cotação Ativo]],Table_Investimentos_Main[[#This Row],[Quantidade]]) -> 30106.64
B60: 45383 | C60: Conta Bancária | E60: Itaú | G60: 279.34 | H60: {=_xlfn.XLOOKUP(Table_Investimentos_Main[[#This Row],[Data]]&Table_Investimentos_Main[[#This Row],[Ticker]],Table_Cotacoes[Data]&Table_Cotacoes[Ticker],Table_Cotacoes[Valor],"")} | I60: =IF(Table_Investimentos_Main[[#This Row],[Ticker]]<>"",_xlfn.XLOOKUP(Table_Investimentos_Main[[#This Row],[Ticker]],Table_Cotacoes[Ticker],Table_Cotacoes[Moeda Base],""),"BRL") -> BRL | J60: {=_xlfn.SINGLE(_xlfn.XLOOKUP(Table_Investimentos_Main[[#This Row],[Data]]&"USD",Table_Cotacoes[Data]&Table_Cotacoes[Ticker],Table_Cotacoes[Valor],""))} -> 5.1163 | K60: =IF(Table_Investimentos_Main[[#This Row],[Ticker]]<>"",Table_Investimentos_Main[[#This Row],[Quantidade]]*Table_Investimentos_Main[[#This Row],[Cotação Ativo]],Table_Investimentos_Main[[#This Row],[Quantidade]]) -> 279.34
B61: 45383 | C61: Bitcoin 01 | D61: BTC | E61: Carteira Cripto | G61: 0.179195 | H61: {=_xlfn.XLOOKUP(Table_Investimentos_Main[[#This Row],[Data]]&Table_Investimentos_Main[[#This Row],[Ticker]],Table_Cotacoes[Data]&Table_Cotacoes[Ticker],Table_Cotacoes[Valor],"")} -> 301966 | I61: =IF(Table_Investimentos_Main[[#This Row],[Ticker]]<>"",_xlfn.XLOOKUP(Table_Investimentos_Main[[#This Row],[Ticker]],Table_Cotacoes[Ticker],Table_Cotacoes[Moeda Base],""),"BRL") -> BTC | J61: {=_xlfn.SINGLE(_xlfn.XLOOKUP(Table_Investimentos_Main[[#This Row],[Data]]&"USD",Table_Cotacoes[Data]&Table_Cotacoes[Ticker],Table_Cotacoes[Valor],""))} -> 5.1163 | K61: =IF(Table_Investimentos_Main[[#This Row],[Ticker]]<>"",Table_Investimentos_Main[[#This Row],[Quantidade]]*Table_Investimentos_Main[[#This Row],[Cotação Ativo]],Table_Investimentos_Main[[#This Row],[Quantidade]]) -> 54110.797
B62: 45383 | C62: USDC | D62: USD | E62: Binance | G62: 3437.1 | H62: {=_xlfn.XLOOKUP(Table_Investimentos_Main[[#This Row],[Data]]&Table_Investimentos_Main[[#This Row],[Ticker]],Table_Cotacoes[Data]&Table_Cotacoes[Ticker],Table_Cotacoes[Valor],"")} -> 5.1163 | I62: =IF(Table_Investimentos_Main[[#This Row],[Ticker]]<>"",_xlfn.XLOOKUP(Table_Investimentos_Main[[#This Row],[Ticker]],Table_Cotacoes[Ticker],Table_Cotacoes[Moeda Base],""),"BRL") -> USD | J62: {=_xlfn.SINGLE(_xlfn.XLOOKUP(Table_Investimentos_Main[[#This Row],[Data]]&"USD",Table_Cotacoes[Data]&Table_Cotacoes[Ticker],Table_Cotacoes[Valor],""))} -> 5.1163 | K62: =IF(Table_Investimentos_Main[[#This Row],[Ticker]]<>"",Table_Investimentos_Main[[#This Row],[Quantidade]]*Table_Investimentos_Main[[#This Row],[Cotação Ativo]],Table_Investimentos_Main[[#This Row],[Quantidade]]) -> 17585.235
B63: 45383 | C63: Bitcoin 02 | D63: BTC | E63: Binance | G63: 0.04627105 | H63: {=_xlfn.XLOOKUP(Table_Investimentos_Main[[#This Row],[Data]]&Table_Investimentos_Main[[#This Row],[Ticker]],Table_Cotacoes[Data]&Table_Cotacoes[Ticker],Table_Cotacoes[Valor],"")} -> 301966 | I63: =IF(Table_Investimentos_Main[[#This Row],[Ticker]]<>"",_xlfn.XLOOKUP(Table_Investimentos_Main[[#This Row],[Ticker]],Table_Cotacoes[Ticker],Table_Cotacoes[Moeda Base],""),"BRL") -> BTC | J63: {=_xlfn.SINGLE(_xlfn.XLOOKUP(Table_Investimentos_Main[[#This Row],[Data]]&"USD",Table_Cotacoes[Data]&Table_Cotacoes[Ticker],Table_Cotacoes[Valor],""))} -> 5.1163 | K63: =IF(Table_Investimentos_Main[[#This Row],[Ticker]]<>"",Table_Investimentos_Main[[#This Row],[Quantidade]]*Table_Investimentos_Main[[#This Row],[Cotação Ativo]],Table_Investimentos_Main[[#This Row],[Quantidade]]) -> 13972.284
B64: 45413 | C64: CDB Itaú 100% | E64: Itaú | G64: 16611 | H64: {=_xlfn.XLOOKUP(Table_Investimentos_Main[[#This Row],[Data]]&Table_Investimentos_Main[[#This Row],[Ticker]],Table_Cotacoes[Data]&Table_Cotacoes[Ticker],Table_Cotacoes[Valor],"")} | I64: =IF(Table_Investimentos_Main[[#This Row],[Ticker]]<>"",_xlfn.XLOOKUP(Table_Investimentos_Main[[#This Row],[Ticker]],Table_Cotacoes[Ticker],Table_Cotacoes[Moeda Base],""),"BRL") -> BRL | J64: {=_xlfn.SINGLE(_xlfn.XLOOKUP(Table_Investimentos_Main[[#This Row],[Data]]&"USD",Table_Cotacoes[Data]&Table_Cotacoes[Ticker],Table_Cotacoes[Valor],""))} -> 5.155 | K64: =IF(Table_Investimentos_Main[[#This Row],[Ticker]]<>"",Table_Investimentos_Main[[#This Row],[Quantidade]]*Table_Investimentos_Main[[#This Row],[Cotação Ativo]],Table_Investimentos_Main[[#This Row],[Quantidade]]) -> 16611
B65: 45413 | C65: Bitcoin 01 | D65: BTC | E65: Carteira Cripto | G65: 0.179195 | H65: {=_xlfn.XLOOKUP(Table_Investimentos_Main[[#This Row],[Data]]&Table_Investimentos_Main[[#This Row],[Ticker]],Table_Cotacoes[Data]&Table_Cotacoes[Ticker],Table_Cotacoes[Valor],"")} -> 355704 | I65: =IF(Table_Investimentos_Main[[#This Row],[Ticker]]<>"",_xlfn.XLOOKUP(Table_Investimentos_Main[[#This Row],[Ticker]],Table_Cotacoes[Ticker],Table_Cotacoes[Moeda Base],""),"BRL") -> BTC | J65: {=_xlfn.SINGLE(_xlfn.XLOOKUP(Table_Investimentos_Main[[#This Row],[Data]]&"USD",Table_Cotacoes[Data]&Table_Cotacoes[Ticker],Table_Cotacoes[Valor],""))} -> 5.155 | K65: =IF(Table_Investimentos_Main[[#This Row],[Ticker]]<>"",Table_Investimentos_Main[[#This Row],[Quantidade]]*Table_Investimentos_Main[[#This Row],[Cotação Ativo]],Table_Investimentos_Main[[#This Row],[Quantidade]]) -> 63740.378
B66: 45413 | C66: USDC | D66: USD | E66: Binance | G66: 3444 | H66: {=_xlfn.XLOOKUP(Table_Investimentos_Main[[#This Row],[Data]]&Table_Investimentos_Main[[#This Row],[Ticker]],Table_Cotacoes[Data]&Table_Cotacoes[Ticker],Table_Cotacoes[Valor],"")} -> 5.155 | I66: =IF(Table_Investimentos_Main[[#This Row],[Ticker]]<>"",_xlfn.XLOOKUP(Table_Investimentos_Main[[#This Row],[Ticker]],Table_Cotacoes[Ticker],Table_Cotacoes[Moeda Base],""),"BRL") -> USD | J66: {=_xlfn.SINGLE(_xlfn.XLOOKUP(Table_Investimentos_Main[[#This Row],[Data]]&"USD",Table_Cotacoes[Data]&Table_Cotacoes[Ticker],Table_Cotacoes[Valor],""))} -> 5.155 | K66: =IF(Table_Investimentos_Main[[#This Row],[Ticker]]<>"",Table_Investimentos_Main[[#This Row],[Quantidade]]*Table_Investimentos_Main[[#This Row],[Cotação Ativo]],Table_Investimentos_Main[[#This Row],[Quantidade]]) -> 17753.82
B67: 45413 | C67: Bitcoin 02 | D67: BTC | E67: Binance | G67: 0.07912145 | H67: {=_xlfn.XLOOKUP(Table_Investimentos_Main[[#This Row],[Data]]&Table_Investimentos_Main[[#This Row],[Ticker]],Table_Cotacoes[Data]&Table_Cotacoes[Ticker],Table_Cotacoes[Valor],"")} -> 355704 | I67: =IF(Table_Investimentos_Main[[#This Row],[Ticker]]<>"",_xlfn.XLOOKUP(Table_Investimentos_Main[[#This Row],[Ticker]],Table_Cotacoes[Ticker],Table_Cotacoes[Moeda Base],""),"BRL") -> BTC | J67: {=_xlfn.SINGLE(_xlfn.XLOOKUP(Table_Investimentos_Main[[#This Row],[Data]]&"USD",Table_Cotacoes[Data]&Table_Cotacoes[Ticker],Table_Cotacoes[Valor],""))} -> 5.155 | K67: =IF(Table_Investimentos_Main[[#This Row],[Ticker]]<>"",Table_Investimentos_Main[[#This Row],[Quantidade]]*Table_Investimentos_Main[[#This Row],[Cotação Ativo]],Table_Investimentos_Main[[#This Row],[Quantidade]]) -> 28143.816
B68: 45444 | C68: Fundo Itaú | E68: Itaú | G68: 13103.07 | H68: {=_xlfn.XLOOKUP(Table_Investimentos_Main[[#This Row],[Data]]&Table_Investimentos_Main[[#This Row],[Ticker]],Table_Cotacoes[Data]&Table_Cotacoes[Ticker],Table_Cotacoes[Valor],"")} | I68: =IF(Table_Investimentos_Main[[#This Row],[Ticker]]<>"",_xlfn.XLOOKUP(Table_Investimentos_Main[[#This Row],[Ticker]],Table_Cotacoes[Ticker],Table_Cotacoes[Moeda Base],""),"BRL") -> BRL | J68: {=_xlfn.SINGLE(_xlfn.XLOOKUP(Table_Investimentos_Main[[#This Row],[Data]]&"USD",Table_Cotacoes[Data]&Table_Cotacoes[Ticker],Table_Cotacoes[Valor],""))} -> 5.43 | K68: =IF(Table_Investimentos_Main[[#This Row],[Ticker]]<>"",Table_Investimentos_Main[[#This Row],[Quantidade]]*Table_Investimentos_Main[[#This Row],[Cotação Ativo]],Table_Investimentos_Main[[#This Row],[Quantidade]]) -> 13103.07
B69: 45444 | C69: CDB Itaú 100% | E69: Itaú | G69: 5331.61 | H69: {=_xlfn.XLOOKUP(Table_Investimentos_Main[[#This Row],[Data]]&Table_Investimentos_Main[[#This Row],[Ticker]],Table_Cotacoes[Data]&Table_Cotacoes[Ticker],Table_Cotacoes[Valor],"")} | I69: =IF(Table_Investimentos_Main[[#This Row],[Ticker]]<>"",_xlfn.XLOOKUP(Table_Investimentos_Main[[#This Row],[Ticker]],Table_Cotacoes[Ticker],Table_Cotacoes[Moeda Base],""),"BRL") -> BRL | J69: {=_xlfn.SINGLE(_xlfn.XLOOKUP(Table_Investimentos_Main[[#This Row],[Data]]&"USD",Table_Cotacoes[Data]&Table_Cotacoes[Ticker],Table_Cotacoes[Valor],""))} -> 5.43 | K69: =IF(Table_Investimentos_Main[[#This Row],[Ticker]]<>"",Table_Investimentos_Main[[#This Row],[Quantidade]]*Table_Investimentos_Main[[#This Row],[Cotação Ativo]],Table_Investimentos_Main[[#This Row],[Quantidade]]) -> 5331.61
B70: 45444 | C70: Bitcoin 01 | D70: BTC | E70: Carteira Cripto | G70: 0.179195 | H70: {=_xlfn.XLOOKUP(Table_Investimentos_Main[[#This Row],[Data]]&Table_Investimentos_Main[[#This Row],[Ticker]],Table_Cotacoes[Data]&Table_Cotacoes[Ticker],Table_Cotacoes[Valor],"")} -> 346000 | I70: =IF(Table_Investimentos_Main[[#This Row],[Ticker]]<>"",_xlfn.XLOOKUP(Table_Investimentos_Main[[#This Row],[Ticker]],Table_Cotacoes[Ticker],Table_Cotacoes[Moeda Base],""),"BRL") -> BTC | J70: {=_xlfn.SINGLE(_xlfn.XLOOKUP(Table_Investimentos_Main[[#This Row],[Data]]&"USD",Table_Cotacoes[Data]&Table_Cotacoes[Ticker],Table_Cotacoes[Valor],""))} -> 5.43 | K70: =IF(Table_Investimentos_Main[[#This Row],[Ticker]]<>"",Table_Investimentos_Main[[#This Row],[Quantidade]]*Table_Investimentos_Main[[#This Row],[Cotação Ativo]],Table_Investimentos_Main[[#This Row],[Quantidade]]) -> 62001.47
B71: 45444 | C71: USDC | D71: USD | E71: Binance | G71: 3458 | H71: {=_xlfn.XLOOKUP(Table_Investimentos_Main[[#This Row],[Data]]&Table_Investimentos_Main[[#This Row],[Ticker]],Table_Cotacoes[Data]&Table_Cotacoes[Ticker],Table_Cotacoes[Valor],"")} -> 5.43 | I71: =IF(Table_Investimentos_Main[[#This Row],[Ticker]]<>"",_xlfn.XLOOKUP(Table_Investimentos_Main[[#This Row],[Ticker]],Table_Cotacoes[Ticker],Table_Cotacoes[Moeda Base],""),"BRL") -> USD | J71: {=_xlfn.SINGLE(_xlfn.XLOOKUP(Table_Investimentos_Main[[#This Row],[Data]]&"USD",Table_Cotacoes[Data]&Table_Cotacoes[Ticker],Table_Cotacoes[Valor],""))} -> 5.43 | K71: =IF(Table_Investimentos_Main[[#This Row],[Ticker]]<>"",Table_Investimentos_Main[[#This Row],[Quantidade]]*Table_Investimentos_Main[[#This Row],[Cotação Ativo]],Table_Investimentos_Main[[#This Row],[Quantidade]]) -> 18776.94
B72: 45444 | C72: Bitcoin 02 | D72: BTC | E72: Binance | G72: 0.07912145 | H72: {=_xlfn.XLOOKUP(Table_Investimentos_Main[[#This Row],[Data]]&Table_Investimentos_Main[[#This Row],[Ticker]],Table_Cotacoes[Data]&Table_Cotacoes[Ticker],Table_Cotacoes[Valor],"")} -> 346000 | I72: =IF(Table_Investimentos_Main[[#This Row],[Ticker]]<>"",_xlfn.XLOOKUP(Table_Investimentos_Main[[#This Row],[Ticker]],Table_Cotacoes[Ticker],Table_Cotacoes[Moeda Base],""),"BRL") -> BTC | J72: {=_xlfn.SINGLE(_xlfn.XLOOKUP(Table_Investimentos_Main[[#This Row],[Data]]&"USD",Table_Cotacoes[Data]&Table_Cotacoes[Ticker],Table_Cotacoes[Valor],""))} -> 5.43 | K72: =IF(Table_Investimentos_Main[[#This Row],[Ticker]]<>"",Table_Investimentos_Main[[#This Row],[Quantidade]]*Table_Investimentos_Main[[#This Row],[Cotação Ativo]],Table_Investimentos_Main[[#This Row],[Quantidade]]) -> 27376.022
B73: 45444 | C73: Etherium | D73: USD | E73: Binance | G73: 548 | H73: {=_xlfn.XLOOKUP(Table_Investimentos_Main[[#This Row],[Data]]&Table_Investimentos_Main[[#This Row],[Ticker]],Table_Cotacoes[Data]&Table_Cotacoes[Ticker],Table_Cotacoes[Valor],"")} -> 5.43 | I73: =IF(Table_Investimentos_Main[[#This Row],[Ticker]]<>"",_xlfn.XLOOKUP(Table_Investimentos_Main[[#This Row],[Ticker]],Table_Cotacoes[Ticker],Table_Cotacoes[Moeda Base],""),"BRL") -> USD | J73: {=_xlfn.SINGLE(_xlfn.XLOOKUP(Table_Investimentos_Main[[#This Row],[Data]]&"USD",Table_Cotacoes[Data]&Table_Cotacoes[Ticker],Table_Cotacoes[Valor],""))} -> 5.43 | K73: =IF(Table_Investimentos_Main[[#This Row],[Ticker]]<>"",Table_Investimentos_Main[[#This Row],[Quantidade]]*Table_Investimentos_Main[[#This Row],[Cotação Ativo]],Table_Investimentos_Main[[#This Row],[Quantidade]]) -> 2975.64
B74: 45444 | C74: Solana | D74: USD | E74: Binance | G74: 245 | H74: {=_xlfn.XLOOKUP(Table_Investimentos_Main[[#This Row],[Data]]&Table_Investimentos_Main[[#This Row],[Ticker]],Table_Cotacoes[Data]&Table_Cotacoes[Ticker],Table_Cotacoes[Valor],"")} -> 5.43 | I74: =IF(Table_Investimentos_Main[[#This Row],[Ticker]]<>"",_xlfn.XLOOKUP(Table_Investimentos_Main[[#This Row],[Ticker]],Table_Cotacoes[Ticker],Table_Cotacoes[Moeda Base],""),"BRL") -> USD | J74: {=_xlfn.SINGLE(_xlfn.XLOOKUP(Table_Investimentos_Main[[#This Row],[Data]]&"USD",Table_Cotacoes[Data]&Table_Cotacoes[Ticker],Table_Cotacoes[Valor],""))} -> 5.43 | K74: =IF(Table_Investimentos_Main[[#This Row],[Ticker]]<>"",Table_Investimentos_Main[[#This Row],[Quantidade]]*Table_Investimentos_Main[[#This Row],[Cotação Ativo]],Table_Investimentos_Main[[#This Row],[Quantidade]]) -> 1330.35
B75: 45505 | C75: Fundo Itaú | E75: Itaú | G75: 11305.1 | H75: {=_xlfn.XLOOKUP(Table_Investimentos_Main[[#This Row],[Data]]&Table_Investimentos_Main[[#This Row],[Ticker]],Table_Cotacoes[Data]&Table_Cotacoes[Ticker],Table_Cotacoes[Valor],"")} | I75: =IF(Table_Investimentos_Main[[#This Row],[Ticker]]<>"",_xlfn.XLOOKUP(Table_Investimentos_Main[[#This Row],[Ticker]],Table_Cotacoes[Ticker],Table_Cotacoes[Moeda Base],""),"BRL") -> BRL | J75: {=_xlfn.SINGLE(_xlfn.XLOOKUP(Table_Investimentos_Main[[#This Row],[Data]]&"USD",Table_Cotacoes[Data]&Table_Cotacoes[Ticker],Table_Cotacoes[Valor],""))} -> 5.5 | K75: =IF(Table_Investimentos_Main[[#This Row],[Ticker]]<>"",Table_Investimentos_Main[[#This Row],[Quantidade]]*Table_Investimentos_Main[[#This Row],[Cotação Ativo]],Table_Investimentos_Main[[#This Row],[Quantidade]]) -> 11305.1
B76: 45505 | C76: CDB Itaú 100% | E76: Itaú | G76: 3002.8 | H76: {=_xlfn.XLOOKUP(Table_Investimentos_Main[[#This Row],[Data]]&Table_Investimentos_Main[[#This Row],[Ticker]],Table_Cotacoes[Data]&Table_Cotacoes[Ticker],Table_Cotacoes[Valor],"")} | I76: =IF(Table_Investimentos_Main[[#This Row],[Ticker]]<>"",_xlfn.XLOOKUP(Table_Investimentos_Main[[#This Row],[Ticker]],Table_Cotacoes[Ticker],Table_Cotacoes[Moeda Base],""),"BRL") -> BRL | J76: {=_xlfn.SINGLE(_xlfn.XLOOKUP(Table_Investimentos_Main[[#This Row],[Data]]&"USD",Table_Cotacoes[Data]&Table_Cotacoes[Ticker],Table_Cotacoes[Valor],""))} -> 5.5 | K76: =IF(Table_Investimentos_Main[[#This Row],[Ticker]]<>"",Table_Investimentos_Main[[#This Row],[Quantidade]]*Table_Investimentos_Main[[#This Row],[Cotação Ativo]],Table_Investimentos_Main[[#This Row],[Quantidade]]) -> 3002.8
B77: 45505 | C77: Bitcoin 01 | D77: BTC | E77: Carteira Cripto | G77: 0.2582571 | H77: {=_xlfn.XLOOKUP(Table_Investimentos_Main[[#This Row],[Data]]&Table_Investimentos_Main[[#This Row],[Ticker]],Table_Cotacoes[Data]&Table_Cotacoes[Ticker],Table_Cotacoes[Valor],"")} -> 339653.67 | I77: =IF(Table_Investimentos_Main[[#This Row],[Ticker]]<>"",_xlfn.XLOOKUP(Table_Investimentos_Main[[#This Row],[Ticker]],Table_Cotacoes[Ticker],Table_Cotacoes[Moeda Base],""),"BRL") -> BTC | J77: {=_xlfn.SINGLE(_xlfn.XLOOKUP(Table_Investimentos_Main[[#This Row],[Data]]&"USD",Table_Cotacoes[Data]&Table_Cotacoes[Ticker],Table_Cotacoes[Valor],""))} -> 5.5 | K77: =IF(Table_Investimentos_Main[[#This Row],[Ticker]]<>"",Table_Investimentos_Main[[#This Row],[Quantidade]]*Table_Investimentos_Main[[#This Row],[Cotação Ativo]],Table_Investimentos_Main[[#This Row],[Quantidade]]) -> 87717.972
B78: 45505 | C78: USDC | D78: USD | E78: Binance | G78: 3412 | H78: {=_xlfn.XLOOKUP(Table_Investimentos_Main[[#This Row],[Data]]&Table_Investimentos_Main[[#This Row],[Ticker]],Table_Cotacoes[Data]&Table_Cotacoes[Ticker],Table_Cotacoes[Valor],"")} -> 5.5 | I78: =IF(Table_Investimentos_Main[[#This Row],[Ticker]]<>"",_xlfn.XLOOKUP(Table_Investimentos_Main[[#This Row],[Ticker]],Table_Cotacoes[Ticker],Table_Cotacoes[Moeda Base],""),"BRL") -> USD | J78: {=_xlfn.SINGLE(_xlfn.XLOOKUP(Table_Investimentos_Main[[#This Row],[Data]]&"USD",Table_Cotacoes[Data]&Table_Cotacoes[Ticker],Table_Cotacoes[Valor],""))} -> 5.5 | K78: =IF(Table_Investimentos_Main[[#This Row],[Ticker]]<>"",Table_Investimentos_Main[[#This Row],[Quantidade]]*Table_Investimentos_Main[[#This Row],[Cotação Ativo]],Table_Investimentos_Main[[#This Row],[Quantidade]]) -> 18766
B79: 45505 | C79: Bitcoin 02 | D79: BTC | E79: Binance | G79: 0.01584414 | H79: {=_xlfn.XLOOKUP(Table_Investimentos_Main[[#This Row],[Data]]&Table_Investimentos_Main[[#This Row],[Ticker]],Table_Cotacoes[Data]&Table_Cotacoes[Ticker],Table_Cotacoes[Valor],"")} -> 339653.67 | I79: =IF(Table_Investimentos_Main[[#This Row],[Ticker]]<>"",_xlfn.XLOOKUP(Table_Investimentos_Main[[#This Row],[Ticker]],Table_Cotacoes[Ticker],Table_Cotacoes[Moeda Base],""),"BRL") -> BTC | J79: {=_xlfn.SINGLE(_xlfn.XLOOKUP(Table_Investimentos_Main[[#This Row],[Data]]&"USD",Table_Cotacoes[Data]&Table_Cotacoes[Ticker],Table_Cotacoes[Valor],""))} -> 5.5 | K79: =IF(Table_Investimentos_Main[[#This Row],[Ticker]]<>"",Table_Investimentos_Main[[#This Row],[Quantidade]]*Table_Investimentos_Main[[#This Row],[Cotação Ativo]],Table_Investimentos_Main[[#This Row],[Quantidade]]) -> 5381.5203
B80: 45505 | C80: Etherium | D80: USD | E80: Binance | G80: 413.9 | H80: {=_xlfn.XLOOKUP(Table_Investimentos_Main[[#This Row],[Data]]&Table_Investimentos_Main[[#This Row],[Ticker]],Table_Cotacoes[Data]&Table_Cotacoes[Ticker],Table_Cotacoes[Valor],"")} -> 5.5 | I80: =IF(Table_Investimentos_Main[[#This Row],[Ticker]]<>"",_xlfn.XLOOKUP(Table_Investimentos_Main[[#This Row],[Ticker]],Table_Cotacoes[Ticker],Table_Cotacoes[Moeda Base],""),"BRL") -> USD | J80: {=_xlfn.SINGLE(_xlfn.XLOOKUP(Table_Investimentos_Main[[#This Row],[Data]]&"USD",Table_Cotacoes[Data]&Table_Cotacoes[Ticker],Table_Cotacoes[Valor],""))} -> 5.5 | K80: =IF(Table_Investimentos_Main[[#This Row],[Ticker]]<>"",Table_Investimentos_Main[[#This Row],[Quantidade]]*Table_Investimentos_Main[[#This Row],[Cotação Ativo]],Table_Investimentos_Main[[#This Row],[Quantidade]]) -> 2276.45
B81: 45505 | C81: Solana | D81: USD | E81: Binance | G81: 718.98 | H81: {=_xlfn.XLOOKUP(Table_Investimentos_Main[[#This Row],[Data]]&Table_Investimentos_Main[[#This Row],[Ticker]],Table_Cotacoes[Data]&Table_Cotacoes[Ticker],Table_Cotacoes[Valor],"")} -> 5.5 | I81: =IF(Table_Investimentos_Main[[#This Row],[Ticker]]<>"",_xlfn.XLOOKUP(Table_Investimentos_Main[[#This Row],[Ticker]],Table_Cotacoes[Ticker],Table_Cotacoes[Moeda Base],""),"BRL") -> USD | J81: {=_xlfn.SINGLE(_xlfn.XLOOKUP(Table_Investimentos_Main[[#This Row],[Data]]&"USD",Table_Cotacoes[Data]&Table_Cotacoes[Ticker],Table_Cotacoes[Valor],""))} -> 5.5 | K81: =IF(Table_Investimentos_Main[[#This Row],[Ticker]]<>"",Table_Investimentos_Main[[#This Row],[Quantidade]]*Table_Investimentos_Main[[#This Row],[Cotação Ativo]],Table_Investimentos_Main[[#This Row],[Quantidade]]) -> 3954.39
B82: 45536 | C82: Fundo Itaú | E82: Itaú | G82: 2355.31 | H82: {=_xlfn.XLOOKUP(Table_Investimentos_Main[[#This Row],[Data]]&Table_Investimentos_Main[[#This Row],[Ticker]],Table_Cotacoes[Data]&Table_Cotacoes[Ticker],Table_Cotacoes[Valor],"")} | I82: =IF(Table_Investimentos_Main[[#This Row],[Ticker]]<>"",_xlfn.XLOOKUP(Table_Investimentos_Main[[#This Row],[Ticker]],Table_Cotacoes[Ticker],Table_Cotacoes[Moeda Base],""),"BRL") -> BRL | J82: {=_xlfn.SINGLE(_xlfn.XLOOKUP(Table_Investimentos_Main[[#This Row],[Data]]&"USD",Table_Cotacoes[Data]&Table_Cotacoes[Ticker],Table_Cotacoes[Valor],""))} -> 5.52 | K82: =IF(Table_Investimentos_Main[[#This Row],[Ticker]]<>"",Table_Investimentos_Main[[#This Row],[Quantidade]]*Table_Investimentos_Main[[#This Row],[Cotação Ativo]],Table_Investimentos_Main[[#This Row],[Quantidade]]) -> 2355.31
B83: 45536 | C83: CDB Itaú 100% | E83: Itaú | G83: 950 | H83: {=_xlfn.XLOOKUP(Table_Investimentos_Main[[#This Row],[Data]]&Table_Investimentos_Main[[#This Row],[Ticker]],Table_Cotacoes[Data]&Table_Cotacoes[Ticker],Table_Cotacoes[Valor],"")} | I83: =IF(Table_Investimentos_Main[[#This Row],[Ticker]]<>"",_xlfn.XLOOKUP(Table_Investimentos_Main[[#This Row],[Ticker]],Table_Cotacoes[Ticker],Table_Cotacoes[Moeda Base],""),"BRL") -> BRL | J83: {=_xlfn.SINGLE(_xlfn.XLOOKUP(Table_Investimentos_Main[[#This Row],[Data]]&"USD",Table_Cotacoes[Data]&Table_Cotacoes[Ticker],Table_Cotacoes[Valor],""))} -> 5.52 | K83: =IF(Table_Investimentos_Main[[#This Row],[Ticker]]<>"",Table_Investimentos_Main[[#This Row],[Quantidade]]*Table_Investimentos_Main[[#This Row],[Cotação Ativo]],Table_Investimentos_Main[[#This Row],[Quantidade]]) -> 950
B84: 45536 | C84: Bitcoin 01 | D84: BTC | E84: Carteira Cripto | G84: 0.2582571 | H84: {=_xlfn.XLOOKUP(Table_Investimentos_Main[[#This Row],[Data]]&Table_Investimentos_Main[[#This Row],[Ticker]],Table_Cotacoes[Data]&Table_Cotacoes[Ticker],Table_Cotacoes[Valor],"")} -> 348333.72 | I84: =IF(Table_Investimentos_Main[[#This Row],[Ticker]]<>"",_xlfn.XLOOKUP(Table_Investimentos_Main[[#This Row],[Ticker]],Table_Cotacoes[Ticker],Table_Cotacoes[Moeda Base],""),"BRL") -> BTC | J84: {=_xlfn.SINGLE(_xlfn.XLOOKUP(Table_Investimentos_Main[[#This Row],[Data]]&"USD",Table_Cotacoes[Data]&Table_Cotacoes[Ticker],Table_Cotacoes[Valor],""))} -> 5.52 | K84: =IF(Table_Investimentos_Main[[#This Row],[Ticker]]<>"",Table_Investimentos_Main[[#This Row],[Quantidade]]*Table_Investimentos_Main[[#This Row],[Cotação Ativo]],Table_Investimentos_Main[[#This Row],[Quantidade]]) -> 89959.656
B85: 45536 | C85: Bitcoin 02 | D85: BTC | E85: Binance | G85: 0.01584414 | H85: {=_xlfn.XLOOKUP(Table_Investimentos_Main[[#This Row],[Data]]&Table_Investimentos_Main[[#This Row],[Ticker]],Table_Cotacoes[Data]&Table_Cotacoes[Ticker],Table_Cotacoes[Valor],"")} -> 348333.72 | I85: =IF(Table_Investimentos_Main[[#This Row],[Ticker]]<>"",_xlfn.XLOOKUP(Table_Investimentos_Main[[#This Row],[Ticker]],Table_Cotacoes[Ticker],Table_Cotacoes[Moeda Base],""),"BRL") -> BTC | J85: {=_xlfn.SINGLE(_xlfn.XLOOKUP(Table_Investimentos_Main[[#This Row],[Data]]&"USD",Table_Cotacoes[Data]&Table_Cotacoes[Ticker],Table_Cotacoes[Valor],""))} -> 5.52 | K85: =IF(Table_Investimentos_Main[[#This Row],[Ticker]]<>"",Table_Investimentos_Main[[#This Row],[Quantidade]]*Table_Investimentos_Main[[#This Row],[Cotação Ativo]],Table_Investimentos_Main[[#This Row],[Quantidade]]) -> 5519.0482
B86: 45536 | C86: Bitcoin 03 - Viagem | D86: BTC | E86: Binance | G86: 0.01963 | H86: {=_xlfn.XLOOKUP(Table_Investimentos_Main[[#This Row],[Data]]&Table_Investimentos_Main[[#This Row],[Ticker]],Table_Cotacoes[Data]&Table_Cotacoes[Ticker],Table_Cotacoes[Valor],"")} -> 348333.72 | I86: =IF(Table_Investimentos_Main[[#This Row],[Ticker]]<>"",_xlfn.XLOOKUP(Table_Investimentos_Main[[#This Row],[Ticker]],Table_Cotacoes[Ticker],Table_Cotacoes[Moeda Base],""),"BRL") -> BTC | J86: {=_xlfn.SINGLE(_xlfn.XLOOKUP(Table_Investimentos_Main[[#This Row],[Data]]&"USD",Table_Cotacoes[Data]&Table_Cotacoes[Ticker],Table_Cotacoes[Valor],""))} -> 5.52 | K86: =IF(Table_Investimentos_Main[[#This Row],[Ticker]]<>"",Table_Investimentos_Main[[#This Row],[Quantidade]]*Table_Investimentos_Main[[#This Row],[Cotação Ativo]],Table_Investimentos_Main[[#This Row],[Quantidade]]) -> 6837.7909
B87: 45536 | C87: USDC | D87: USD | E87: Binance | G87: 3418.33 | H87: {=_xlfn.XLOOKUP(Table_Investimentos_Main[[#This Row],[Data]]&Table_Investimentos_Main[[#This Row],[Ticker]],Table_Cotacoes[Data]&Table_Cotacoes[Ticker],Table_Cotacoes[Valor],"")} -> 5.52 | I87: =IF(Table_Investimentos_Main[[#This Row],[Ticker]]<>"",_xlfn.XLOOKUP(Table_Investimentos_Main[[#This Row],[Ticker]],Table_Cotacoes[Ticker],Table_Cotacoes[Moeda Base],""),"BRL") -> USD | J87: {=_xlfn.SINGLE(_xlfn.XLOOKUP(Table_Investimentos_Main[[#This Row],[Data]]&"USD",Table_Cotacoes[Data]&Table_Cotacoes[Ticker],Table_Cotacoes[Valor],""))} -> 5.52 | K87: =IF(Table_Investimentos_Main[[#This Row],[Ticker]]<>"",Table_Investimentos_Main[[#This Row],[Quantidade]]*Table_Investimentos_Main[[#This Row],[Cotação Ativo]],Table_Investimentos_Main[[#This Row],[Quantidade]]) -> 18869.182
B88: 45536 | C88: Etherium | D88: USD | E88: Binance | G88: 413.59 | H88: {=_xlfn.XLOOKUP(Table_Investimentos_Main[[#This Row],[Data]]&Table_Investimentos_Main[[#This Row],[Ticker]],Table_Cotacoes[Data]&Table_Cotacoes[Ticker],Table_Cotacoes[Valor],"")} -> 5.52 | I88: =IF(Table_Investimentos_Main[[#This Row],[Ticker]]<>"",_xlfn.XLOOKUP(Table_Investimentos_Main[[#This Row],[Ticker]],Table_Cotacoes[Ticker],Table_Cotacoes[Moeda Base],""),"BRL") -> USD | J88: {=_xlfn.SINGLE(_xlfn.XLOOKUP(Table_Investimentos_Main[[#This Row],[Data]]&"USD",Table_Cotacoes[Data]&Table_Cotacoes[Ticker],Table_Cotacoes[Valor],""))} -> 5.52 | K88: =IF(Table_Investimentos_Main[[#This Row],[Ticker]]<>"",Table_Investimentos_Main[[#This Row],[Quantidade]]*Table_Investimentos_Main[[#This Row],[Cotação Ativo]],Table_Investimentos_Main[[#This Row],[Quantidade]]) -> 2283.0168
B89: 45536 | C89: Solana | D89: USD | E89: Binance | G89: 676.47 | H89: {=_xlfn.XLOOKUP(Table_Investimentos_Main[[#This Row],[Data]]&Table_Investimentos_Main[[#This Row],[Ticker]],Table_Cotacoes[Data]&Table_Cotacoes[Ticker],Table_Cotacoes[Valor],"")} -> 5.52 | I89: =IF(Table_Investimentos_Main[[#This Row],[Ticker]]<>"",_xlfn.XLOOKUP(Table_Investimentos_Main[[#This Row],[Ticker]],Table_Cotacoes[Ticker],Table_Cotacoes[Moeda Base],""),"BRL") -> USD | J89: {=_xlfn.SINGLE(_xlfn.XLOOKUP(Table_Investimentos_Main[[#This Row],[Data]]&"USD",Table_Cotacoes[Data]&Table_Cotacoes[Ticker],Table_Cotacoes[Valor],""))} -> 5.52 | K89: =IF(Table_Investimentos_Main[[#This Row],[Ticker]]<>"",Table_Investimentos_Main[[#This Row],[Quantidade]]*Table_Investimentos_Main[[#This Row],[Cotação Ativo]],Table_Investimentos_Main[[#This Row],[Quantidade]]) -> 3734.1144
B90: 45536 | C90: ETF - VOO | D90: USD | E90: Banco Inter | G90: 912.37 | H90: {=_xlfn.XLOOKUP(Table_Investimentos_Main[[#This Row],[Data]]&Table_Investimentos_Main[[#This Row],[Ticker]],Table_Cotacoes[Data]&Table_Cotacoes[Ticker],Table_Cotacoes[Valor],"")} -> 5.52 | I90: =IF(Table_Investimentos_Main[[#This Row],[Ticker]]<>"",_xlfn.XLOOKUP(Table_Investimentos_Main[[#This Row],[Ticker]],Table_Cotacoes[Ticker],Table_Cotacoes[Moeda Base],""),"BRL") -> USD | J90: {=_xlfn.SINGLE(_xlfn.XLOOKUP(Table_Investimentos_Main[[#This Row],[Data]]&"USD",Table_Cotacoes[Data]&Table_Cotacoes[Ticker],Table_Cotacoes[Valor],""))} -> 5.52 | K90: =IF(Table_Investimentos_Main[[#This Row],[Ticker]]<>"",Table_Investimentos_Main[[#This Row],[Quantidade]]*Table_Investimentos_Main[[#This Row],[Cotação Ativo]],Table_Investimentos_Main[[#This Row],[Quantidade]]) -> 5036.2824
B91: 45566 | C91: Fundo Itaú | E91: Itaú | G91: 1769.97 | H91: {=_xlfn.XLOOKUP(Table_Investimentos_Main[[#This Row],[Data]]&Table_Investimentos_Main[[#This Row],[Ticker]],Table_Cotacoes[Data]&Table_Cotacoes[Ticker],Table_Cotacoes[Valor],"")} | I91: =IF(Table_Investimentos_Main[[#This Row],[Ticker]]<>"",_xlfn.XLOOKUP(Table_Investimentos_Main[[#This Row],[Ticker]],Table_Cotacoes[Ticker],Table_Cotacoes[Moeda Base],""),"BRL") -> BRL | J91: {=_xlfn.SINGLE(_xlfn.XLOOKUP(Table_Investimentos_Main[[#This Row],[Data]]&"USD",Table_Cotacoes[Data]&Table_Cotacoes[Ticker],Table_Cotacoes[Valor],""))} -> 5.76 | K91: =IF(Table_Investimentos_Main[[#This Row],[Ticker]]<>"",Table_Investimentos_Main[[#This Row],[Quantidade]]*Table_Investimentos_Main[[#This Row],[Cotação Ativo]],Table_Investimentos_Main[[#This Row],[Quantidade]]) -> 1769.97
B92: 45566 | C92: CDB Itaú 100% | E92: Itaú | G92: 2003.1 | H92: {=_xlfn.XLOOKUP(Table_Investimentos_Main[[#This Row],[Data]]&Table_Investimentos_Main[[#This Row],[Ticker]],Table_Cotacoes[Data]&Table_Cotacoes[Ticker],Table_Cotacoes[Valor],"")} | I92: =IF(Table_Investimentos_Main[[#This Row],[Ticker]]<>"",_xlfn.XLOOKUP(Table_Investimentos_Main[[#This Row],[Ticker]],Table_Cotacoes[Ticker],Table_Cotacoes[Moeda Base],""),"BRL") -> BRL | J92: {=_xlfn.SINGLE(_xlfn.XLOOKUP(Table_Investimentos_Main[[#This Row],[Data]]&"USD",Table_Cotacoes[Data]&Table_Cotacoes[Ticker],Table_Cotacoes[Valor],""))} -> 5.76 | K92: =IF(Table_Investimentos_Main[[#This Row],[Ticker]]<>"",Table_Investimentos_Main[[#This Row],[Quantidade]]*Table_Investimentos_Main[[#This Row],[Cotação Ativo]],Table_Investimentos_Main[[#This Row],[Quantidade]]) -> 2003.1
B93: 45566 | C93: Bitcoin 01 | D93: BTC | E93: Carteira Cripto | G93: 0.2582571 | H93: {=_xlfn.XLOOKUP(Table_Investimentos_Main[[#This Row],[Data]]&Table_Investimentos_Main[[#This Row],[Ticker]],Table_Cotacoes[Data]&Table_Cotacoes[Ticker],Table_Cotacoes[Valor],"")} -> 418028.58 | I93: =IF(Table_Investimentos_Main[[#This Row],[Ticker]]<>"",_xlfn.XLOOKUP(Table_Investimentos_Main[[#This Row],[Ticker]],Table_Cotacoes[Ticker],Table_Cotacoes[Moeda Base],""),"BRL") -> BTC | J93: {=_xlfn.SINGLE(_xlfn.XLOOKUP(Table_Investimentos_Main[[#This Row],[Data]]&"USD",Table_Cotacoes[Data]&Table_Cotacoes[Ticker],Table_Cotacoes[Valor],""))} -> 5.76 | K93: =IF(Table_Investimentos_Main[[#This Row],[Ticker]]<>"",Table_Investimentos_Main[[#This Row],[Quantidade]]*Table_Investimentos_Main[[#This Row],[Cotação Ativo]],Table_Investimentos_Main[[#This Row],[Quantidade]]) -> 107958.85
B94: 45566 | C94: Bitcoin 02 | D94: BTC | E94: Binance | G94: 0.01584414 | H94: {=_xlfn.XLOOKUP(Table_Investimentos_Main[[#This Row],[Data]]&Table_Investimentos_Main[[#This Row],[Ticker]],Table_Cotacoes[Data]&Table_Cotacoes[Ticker],Table_Cotacoes[Valor],"")} -> 418028.58 | I94: =IF(Table_Investimentos_Main[[#This Row],[Ticker]]<>"",_xlfn.XLOOKUP(Table_Investimentos_Main[[#This Row],[Ticker]],Table_Cotacoes[Ticker],Table_Cotacoes[Moeda Base],""),"BRL") -> BTC | J94: {=_xlfn.SINGLE(_xlfn.XLOOKUP(Table_Investimentos_Main[[#This Row],[Data]]&"USD",Table_Cotacoes[Data]&Table_Cotacoes[Ticker],Table_Cotacoes[Valor],""))} -> 5.76 | K94: =IF(Table_Investimentos_Main[[#This Row],[Ticker]]<>"",Table_Investimentos_Main[[#This Row],[Quantidade]]*Table_Investimentos_Main[[#This Row],[Cotação Ativo]],Table_Investimentos_Main[[#This Row],[Quantidade]]) -> 6623.3033
B95: 45566 | C95: Bitcoin 03 - Viagem | D95: BTC | E95: Binance | G95: 0.01963 | H95: {=_xlfn.XLOOKUP(Table_Investimentos_Main[[#This Row],[Data]]&Table_Investimentos_Main[[#This Row],[Ticker]],Table_Cotacoes[Data]&Table_Cotacoes[Ticker],Table_Cotacoes[Valor],"")} -> 418028.58 | I95: =IF(Table_Investimentos_Main[[#This Row],[Ticker]]<>"",_xlfn.XLOOKUP(Table_Investimentos_Main[[#This Row],[Ticker]],Table_Cotacoes[Ticker],Table_Cotacoes[Moeda Base],""),"BRL") -> BTC | J95: {=_xlfn.SINGLE(_xlfn.XLOOKUP(Table_Investimentos_Main[[#This Row],[Data]]&"USD",Table_Cotacoes[Data]&Table_Cotacoes[Ticker],Table_Cotacoes[Valor],""))} -> 5.76 | K95: =IF(Table_Investimentos_Main[[#This Row],[Ticker]]<>"",Table_Investimentos_Main[[#This Row],[Quantidade]]*Table_Investimentos_Main[[#This Row],[Cotação Ativo]],Table_Investimentos_Main[[#This Row],[Quantidade]]) -> 8205.901
B96: 45566 | C96: USDC | D96: USD | E96: Binance | G96: 3432 | H96: {=_xlfn.XLOOKUP(Table_Investimentos_Main[[#This Row],[Data]]&Table_Investimentos_Main[[#This Row],[Ticker]],Table_Cotacoes[Data]&Table_Cotacoes[Ticker],Table_Cotacoes[Valor],"")} -> 5.76 | I96: =IF(Table_Investimentos_Main[[#This Row],[Ticker]]<>"",_xlfn.XLOOKUP(Table_Investimentos_Main[[#This Row],[Ticker]],Table_Cotacoes[Ticker],Table_Cotacoes[Moeda Base],""),"BRL") -> USD | J96: {=_xlfn.SINGLE(_xlfn.XLOOKUP(Table_Investimentos_Main[[#This Row],[Data]]&"USD",Table_Cotacoes[Data]&Table_Cotacoes[Ticker],Table_Cotacoes[Valor],""))} -> 5.76 | K96: =IF(Table_Investimentos_Main[[#This Row],[Ticker]]<>"",Table_Investimentos_Main[[#This Row],[Quantidade]]*Table_Investimentos_Main[[#This Row],[Cotação Ativo]],Table_Investimentos_Main[[#This Row],[Quantidade]]) -> 19768.32
B97: 45566 | C97: Etherium | D97: USD | E97: Binance | G97: 422.39 | H97: {=_xlfn.XLOOKUP(Table_Investimentos_Main[[#This Row],[Data]]&Table_Investimentos_Main[[#This Row],[Ticker]],Table_Cotacoes[Data]&Table_Cotacoes[Ticker],Table_Cotacoes[Valor],"")} -> 5.76 | I97: =IF(Table_Investimentos_Main[[#This Row],[Ticker]]<>"",_xlfn.XLOOKUP(Table_Investimentos_Main[[#This Row],[Ticker]],Table_Cotacoes[Ticker],Table_Cotacoes[Moeda Base],""),"BRL") -> USD | J97: {=_xlfn.SINGLE(_xlfn.XLOOKUP(Table_Investimentos_Main[[#This Row],[Data]]&"USD",Table_Cotacoes[Data]&Table_Cotacoes[Ticker],Table_Cotacoes[Valor],""))} -> 5.76 | K97: =IF(Table_Investimentos_Main[[#This Row],[Ticker]]<>"",Table_Investimentos_Main[[#This Row],[Quantidade]]*Table_Investimentos_Main[[#This Row],[Cotação Ativo]],Table_Investimentos_Main[[#This Row],[Quantidade]]) -> 2432.9664
B98: 45566 | C98: Solana | D98: USD | E98: Binance | G98: 836.11 | H98: {=_xlfn.XLOOKUP(Table_Investimentos_Main[[#This Row],[Data]]&Table_Investimentos_Main[[#This Row],[Ticker]],Table_Cotacoes[Data]&Table_Cotacoes[Ticker],Table_Cotacoes[Valor],"")} -> 5.76 | I98: =IF(Table_Investimentos_Main[[#This Row],[Ticker]]<>"",_xlfn.XLOOKUP(Table_Investimentos_Main[[#This Row],[Ticker]],Table_Cotacoes[Ticker],Table_Cotacoes[Moeda Base],""),"BRL") -> USD | J98: {=_xlfn.SINGLE(_xlfn.XLOOKUP(Table_Investimentos_Main[[#This Row],[Data]]&"USD",Table_Cotacoes[Data]&Table_Cotacoes[Ticker],Table_Cotacoes[Valor],""))} -> 5.76 | K98: =IF(Table_Investimentos_Main[[#This Row],[Ticker]]<>"",Table_Investimentos_Main[[#This Row],[Quantidade]]*Table_Investimentos_Main[[#This Row],[Cotação Ativo]],Table_Investimentos_Main[[#This Row],[Quantidade]]) -> 4815.9936
B99: 45566 | C99: ETF - VOO | D99: USD | E99: Banco Inter | G99: 931.33 | H99: {=_xlfn.XLOOKUP(Table_Investimentos_Main[[#This Row],[Data]]&Table_Investimentos_Main[[#This Row],[Ticker]],Table_Cotacoes[Data]&Table_Cotacoes[Ticker],Table_Cotacoes[Valor],"")} -> 5.76 | I99: =IF(Table_Investimentos_Main[[#This Row],[Ticker]]<>"",_xlfn.XLOOKUP(Table_Investimentos_Main[[#This Row],[Ticker]],Table_Cotacoes[Ticker],Table_Cotacoes[Moeda Base],""),"BRL") -> USD | J99: {=_xlfn.SINGLE(_xlfn.XLOOKUP(Table_Investimentos_Main[[#This Row],[Data]]&"USD",Table_Cotacoes[Data]&Table_Cotacoes[Ticker],Table_Cotacoes[Valor],""))} -> 5.76 | K99: =IF(Table_Investimentos_Main[[#This Row],[Ticker]]<>"",Table_Investimentos_Main[[#This Row],[Quantidade]]*Table_Investimentos_Main[[#This Row],[Cotação Ativo]],Table_Investimentos_Main[[#This Row],[Quantidade]]) -> 5364.4608
B100: 45597 | C100: Fundo Itaú | E100: Itaú | G100: 1774.82 | H100: {=_xlfn.XLOOKUP(Table_Investimentos_Main[[#This Row],[Data]]&Table_Investimentos_Main[[#This Row],[Ticker]],Table_Cotacoes[Data]&Table_Cotacoes[Ticker],Table_Cotacoes[Valor],"")} | I100: =IF(Table_Investimentos_Main[[#This Row],[Ticker]]<>"",_xlfn.XLOOKUP(Table_Investimentos_Main[[#This Row],[Ticker]],Table_Cotacoes[Ticker],Table_Cotacoes[Moeda Base],""),"BRL") -> BRL | J100: {=_xlfn.SINGLE(_xlfn.XLOOKUP(Table_Investimentos_Main[[#This Row],[Data]]&"USD",Table_Cotacoes[Data]&Table_Cotacoes[Ticker],Table_Cotacoes[Valor],""))} -> 5.81 | K100: =IF(Table_Investimentos_Main[[#This Row],[Ticker]]<>"",Table_Investimentos_Main[[#This Row],[Quantidade]]*Table_Investimentos_Main[[#This Row],[Cotação Ativo]],Table_Investimentos_Main[[#This Row],[Quantidade]]) -> 1774.82
B101: 45597 | C101: CDB Itaú 100% | E101: Itaú | G101: 7107.21 | H101: {=_xlfn.XLOOKUP(Table_Investimentos_Main[[#This Row],[Data]]&Table_Investimentos_Main[[#This Row],[Ticker]],Table_Cotacoes[Data]&Table_Cotacoes[Ticker],Table_Cotacoes[Valor],"")} | I101: =IF(Table_Investimentos_Main[[#This Row],[Ticker]]<>"",_xlfn.XLOOKUP(Table_Investimentos_Main[[#This Row],[Ticker]],Table_Cotacoes[Ticker],Table_Cotacoes[Moeda Base],""),"BRL") -> BRL | J101: {=_xlfn.SINGLE(_xlfn.XLOOKUP(Table_Investimentos_Main[[#This Row],[Data]]&"USD",Table_Cotacoes[Data]&Table_Cotacoes[Ticker],Table_Cotacoes[Valor],""))} -> 5.81 | K101: =IF(Table_Investimentos_Main[[#This Row],[Ticker]]<>"",Table_Investimentos_Main[[#This Row],[Quantidade]]*Table_Investimentos_Main[[#This Row],[Cotação Ativo]],Table_Investimentos_Main[[#This Row],[Quantidade]]) -> 7107.21
B102: 45597 | C102: Bitcoin 01 | D102: BTC | E102: Carteira Cripto | G102: 0.2582571 | H102: {=_xlfn.XLOOKUP(Table_Investimentos_Main[[#This Row],[Data]]&Table_Investimentos_Main[[#This Row],[Ticker]],Table_Cotacoes[Data]&Table_Cotacoes[Ticker],Table_Cotacoes[Valor],"")} -> 569958.14 | I102: =IF(Table_Investimentos_Main[[#This Row],[Ticker]]<>"",_xlfn.XLOOKUP(Table_Investimentos_Main[[#This Row],[Ticker]],Table_Cotacoes[Ticker],Table_Cotacoes[Moeda Base],""),"BRL") -> BTC | J102: {=_xlfn.SINGLE(_xlfn.XLOOKUP(Table_Investimentos_Main[[#This Row],[Data]]&"USD",Table_Cotacoes[Data]&Table_Cotacoes[Ticker],Table_Cotacoes[Valor],""))} -> 5.81 | K102: =IF(Table_Investimentos_Main[[#This Row],[Ticker]]<>"",Table_Investimentos_Main[[#This Row],[Quantidade]]*Table_Investimentos_Main[[#This Row],[Cotação Ativo]],Table_Investimentos_Main[[#This Row],[Quantidade]]) -> 147195.74
...

Sheet Investimentos_Porcent
B4: Data | C4: Nome | D4: Classe | E4: Subclasse | F4: Duração | G4: Estratégia | H4: Moeda Base | I4: Porcentagem | J4: Total (R$) | K4: Total ($)
B5: 46204 | C5: USDC | D5: Caixa | E5: Stablecoin | F5: D+0 | G5: {=_xlfn.XLOOKUP(Table_Investimentos_Porcent[[#This Row],[Data]]&Table_Investimentos_Porcent[[#This Row],[Nome]],Table_Investimentos_Main[Data]&Table_Investimentos_Main[Nome],Table_Investimentos_Main[Estratégia],"NOT FOUND")} -> Core | H5: {=_xlfn.XLOOKUP(Table_Investimentos_Porcent[[#This Row],[Data]]&Table_Investimentos_Porcent[[#This Row],[Nome]],Table_Investimentos_Main[Data]&Table_Investimentos_Main[Nome],Table_Investimentos_Main[Moeda Base],"NOT FOUND")} -> USD | I5: 1 | J5: {=Table_Investimentos_Porcent[[#This Row],[Porcentagem]]*_xlfn.XLOOKUP(Table_Investimentos_Porcent[[#This Row],[Data]]&Table_Investimentos_Porcent[[#This Row],[Nome]],Table_Investimentos_Main[Data]&Table_Investimentos_Main[Nome],Table_Investimentos_Main[Total (R$)],"NOT FOUND")} -> 8807.1311 | K5: {=Table_Investimentos_Porcent[[#This Row],[Total (R$)]]/_xlfn.XLOOKUP(Table_Investimentos_Porcent[[#This Row],[Data]]&Table_Investimentos_Porcent[[#This Row],[Nome]],Table_Investimentos_Main[Data]&Table_Investimentos_Main[Nome],Table_Investimentos_Main[Cotação Dolar],"NOT FOUND")} -> 1704.76
B6: 46204 | C6: Bitcoin 02 | D6: Cripto | E6: BTC | F6: - | G6: {=_xlfn.XLOOKUP(Table_Investimentos_Porcent[[#This Row],[Data]]&Table_Investimentos_Porcent[[#This Row],[Nome]],Table_Investimentos_Main[Data]&Table_Investimentos_Main[Nome],Table_Investimentos_Main[Estratégia],"NOT FOUND")} -> Core-Satellite | H6: {=_xlfn.XLOOKUP(Table_Investimentos_Porcent[[#This Row],[Data]]&Table_Investimentos_Porcent[[#This Row],[Nome]],Table_Investimentos_Main[Data]&Table_Investimentos_Main[Nome],Table_Investimentos_Main[Moeda Base],"NOT FOUND")} -> BTC | I6: 1 | J6: {=Table_Investimentos_Porcent[[#This Row],[Porcentagem]]*_xlfn.XLOOKUP(Table_Investimentos_Porcent[[#This Row],[Data]]&Table_Investimentos_Porcent[[#This Row],[Nome]],Table_Investimentos_Main[Data]&Table_Investimentos_Main[Nome],Table_Investimentos_Main[Total (R$)],"NOT FOUND")} -> 1957.8315 | K6: {=Table_Investimentos_Porcent[[#This Row],[Total (R$)]]/_xlfn.XLOOKUP(Table_Investimentos_Porcent[[#This Row],[Data]]&Table_Investimentos_Porcent[[#This Row],[Nome]],Table_Investimentos_Main[Data]&Table_Investimentos_Main[Nome],Table_Investimentos_Main[Cotação Dolar],"NOT FOUND")} -> 378.96936
B7: 46204 | C7: Solana | D7: Cripto | E7: Altcoin | F7: - | G7: {=_xlfn.XLOOKUP(Table_Investimentos_Porcent[[#This Row],[Data]]&Table_Investimentos_Porcent[[#This Row],[Nome]],Table_Investimentos_Main[Data]&Table_Investimentos_Main[Nome],Table_Investimentos_Main[Estratégia],"NOT FOUND")} -> Satellite | H7: {=_xlfn.XLOOKUP(Table_Investimentos_Porcent[[#This Row],[Data]]&Table_Investimentos_Porcent[[#This Row],[Nome]],Table_Investimentos_Main[Data]&Table_Investimentos_Main[Nome],Table_Investimentos_Main[Moeda Base],"NOT FOUND")} -> USD | I7: 1 | J7: {=Table_Investimentos_Porcent[[#This Row],[Porcentagem]]*_xlfn.XLOOKUP(Table_Investimentos_Porcent[[#This Row],[Data]]&Table_Investimentos_Porcent[[#This Row],[Nome]],Table_Investimentos_Main[Data]&Table_Investimentos_Main[Nome],Table_Investimentos_Main[Total (R$)],"NOT FOUND")} -> 2435.167 | K7: {=Table_Investimentos_Porcent[[#This Row],[Total (R$)]]/_xlfn.XLOOKUP(Table_Investimentos_Porcent[[#This Row],[Data]]&Table_Investimentos_Porcent[[#This Row],[Nome]],Table_Investimentos_Main[Data]&Table_Investimentos_Main[Nome],Table_Investimentos_Main[Cotação Dolar],"NOT FOUND")} -> 471.36522
B8: 46204 | C8: Time Deposit | D8: Caixa | E8: Pós-fixado | F8: Curto | G8: {=_xlfn.XLOOKUP(Table_Investimentos_Porcent[[#This Row],[Data]]&Table_Investimentos_Porcent[[#This Row],[Nome]],Table_Investimentos_Main[Data]&Table_Investimentos_Main[Nome],Table_Investimentos_Main[Estratégia],"NOT FOUND")} -> Core | H8: {=_xlfn.XLOOKUP(Table_Investimentos_Porcent[[#This Row],[Data]]&Table_Investimentos_Porcent[[#This Row],[Nome]],Table_Investimentos_Main[Data]&Table_Investimentos_Main[Nome],Table_Investimentos_Main[Moeda Base],"NOT FOUND")} -> USD | I8: 1 | J8: {=Table_Investimentos_Porcent[[#This Row],[Porcentagem]]*_xlfn.XLOOKUP(Table_Investimentos_Porcent[[#This Row],[Data]]&Table_Investimentos_Porcent[[#This Row],[Nome]],Table_Investimentos_Main[Data]&Table_Investimentos_Main[Nome],Table_Investimentos_Main[Total (R$)],"NOT FOUND")} -> 1331.1748 | K8: {=Table_Investimentos_Porcent[[#This Row],[Total (R$)]]/_xlfn.XLOOKUP(Table_Investimentos_Porcent[[#This Row],[Data]]&Table_Investimentos_Porcent[[#This Row],[Nome]],Table_Investimentos_Main[Data]&Table_Investimentos_Main[Nome],Table_Investimentos_Main[Cotação Dolar],"NOT FOUND")} -> 257.67
B9: 46204 | C9: Flexible Account | D9: Caixa | E9: Curto | F9: D+0 | G9: {=_xlfn.XLOOKUP(Table_Investimentos_Porcent[[#This Row],[Data]]&Table_Investimentos_Porcent[[#This Row],[Nome]],Table_Investimentos_Main[Data]&Table_Investimentos_Main[Nome],Table_Investimentos_Main[Estratégia],"NOT FOUND")} -> Core | H9: {=_xlfn.XLOOKUP(Table_Investimentos_Porcent[[#This Row],[Data]]&Table_Investimentos_Porcent[[#This Row],[Nome]],Table_Investimentos_Main[Data]&Table_Investimentos_Main[Nome],Table_Investimentos_Main[Moeda Base],"NOT FOUND")} -> USD | I9: 1 | J9: {=Table_Investimentos_Porcent[[#This Row],[Porcentagem]]*_xlfn.XLOOKUP(Table_Investimentos_Porcent[[#This Row],[Data]]&Table_Investimentos_Porcent[[#This Row],[Nome]],Table_Investimentos_Main[Data]&Table_Investimentos_Main[Nome],Table_Investimentos_Main[Total (R$)],"NOT FOUND")} -> 2991.2815 | K9: {=Table_Investimentos_Porcent[[#This Row],[Total (R$)]]/_xlfn.XLOOKUP(Table_Investimentos_Porcent[[#This Row],[Data]]&Table_Investimentos_Porcent[[#This Row],[Nome]],Table_Investimentos_Main[Data]&Table_Investimentos_Main[Nome],Table_Investimentos_Main[Cotação Dolar],"NOT FOUND")} -> 579.01
B10: 46204 | C10: ETF - GLDM | D10: Reserva | E10: Commoditie | F10: - | G10: {=_xlfn.XLOOKUP(Table_Investimentos_Porcent[[#This Row],[Data]]&Table_Investimentos_Porcent[[#This Row],[Nome]],Table_Investimentos_Main[Data]&Table_Investimentos_Main[Nome],Table_Investimentos_Main[Estratégia],"NOT FOUND")} -> Hedge | H10: {=_xlfn.XLOOKUP(Table_Investimentos_Porcent[[#This Row],[Data]]&Table_Investimentos_Porcent[[#This Row],[Nome]],Table_Investimentos_Main[Data]&Table_Investimentos_Main[Nome],Table_Investimentos_Main[Moeda Base],"NOT FOUND")} -> USD | I10: 1 | J10: {=Table_Investimentos_Porcent[[#This Row],[Porcentagem]]*_xlfn.XLOOKUP(Table_Investimentos_Porcent[[#This Row],[Data]]&Table_Investimentos_Porcent[[#This Row],[Nome]],Table_Investimentos_Main[Data]&Table_Investimentos_Main[Nome],Table_Investimentos_Main[Total (R$)],"NOT FOUND")} -> 5764.7618 | K10: {=Table_Investimentos_Porcent[[#This Row],[Total (R$)]]/_xlfn.XLOOKUP(Table_Investimentos_Porcent[[#This Row],[Data]]&Table_Investimentos_Porcent[[#This Row],[Nome]],Table_Investimentos_Main[Data]&Table_Investimentos_Main[Nome],Table_Investimentos_Main[Cotação Dolar],"NOT FOUND")} -> 1115.8611
B11: 46204 | C11: ETF - GPCA11 | D11: Renda Fixa | E11: IPCA | F11: Curto | G11: {=_xlfn.XLOOKUP(Table_Investimentos_Porcent[[#This Row],[Data]]&Table_Investimentos_Porcent[[#This Row],[Nome]],Table_Investimentos_Main[Data]&Table_Investimentos_Main[Nome],Table_Investimentos_Main[Estratégia],"NOT FOUND")} -> Core | H11: {=_xlfn.XLOOKUP(Table_Investimentos_Porcent[[#This Row],[Data]]&Table_Investimentos_Porcent[[#This Row],[Nome]],Table_Investimentos_Main[Data]&Table_Investimentos_Main[Nome],Table_Investimentos_Main[Moeda Base],"NOT FOUND")} -> BRL | I11: 0.6 | J11: {=Table_Investimentos_Porcent[[#This Row],[Porcentagem]]*_xlfn.XLOOKUP(Table_Investimentos_Porcent[[#This Row],[Data]]&Table_Investimentos_Porcent[[#This Row],[Nome]],Table_Investimentos_Main[Data]&Table_Investimentos_Main[Nome],Table_Investimentos_Main[Total (R$)],"NOT FOUND")} -> 3002.076 | K11: {=Table_Investimentos_Porcent[[#This Row],[Total (R$)]]/_xlfn.XLOOKUP(Table_Investimentos_Porcent[[#This Row],[Data]]&Table_Investimentos_Porcent[[#This Row],[Nome]],Table_Investimentos_Main[Data]&Table_Investimentos_Main[Nome],Table_Investimentos_Main[Cotação Dolar],"NOT FOUND")} -> 581.09945
B12: 46204 | C12: Tesouro IPCA+ 2032 | D12: Renda Fixa | E12: IPCA | F12: Médio | G12: {=_xlfn.XLOOKUP(Table_Investimentos_Porcent[[#This Row],[Data]]&Table_Investimentos_Porcent[[#This Row],[Nome]],Table_Investimentos_Main[Data]&Table_Investimentos_Main[Nome],Table_Investimentos_Main[Estratégia],"NOT FOUND")} -> Core | H12: {=_xlfn.XLOOKUP(Table_Investimentos_Porcent[[#This Row],[Data]]&Table_Investimentos_Porcent[[#This Row],[Nome]],Table_Investimentos_Main[Data]&Table_Investimentos_Main[Nome],Table_Investimentos_Main[Moeda Base],"NOT FOUND")} -> BRL | I12: 1 | J12: {=Table_Investimentos_Porcent[[#This Row],[Porcentagem]]*_xlfn.XLOOKUP(Table_Investimentos_Porcent[[#This Row],[Data]]&Table_Investimentos_Porcent[[#This Row],[Nome]],Table_Investimentos_Main[Data]&Table_Investimentos_Main[Nome],Table_Investimentos_Main[Total (R$)],"NOT FOUND")} -> 2986.86 | K12: {=Table_Investimentos_Porcent[[#This Row],[Total (R$)]]/_xlfn.XLOOKUP(Table_Investimentos_Porcent[[#This Row],[Data]]&Table_Investimentos_Porcent[[#This Row],[Nome]],Table_Investimentos_Main[Data]&Table_Investimentos_Main[Nome],Table_Investimentos_Main[Cotação Dolar],"NOT FOUND")} -> 578.15416
B13: 46204 | C13: ETF - GPCA11 | D13: Renda Fixa | E13: IPCA | F13: Médio | G13: {=_xlfn.XLOOKUP(Table_Investimentos_Porcent[[#This Row],[Data]]&Table_Investimentos_Porcent[[#This Row],[Nome]],Table_Investimentos_Main[Data]&Table_Investimentos_Main[Nome],Table_Investimentos_Main[Estratégia],"NOT FOUND")} -> Core | H13: {=_xlfn.XLOOKUP(Table_Investimentos_Porcent[[#This Row],[Data]]&Table_Investimentos_Porcent[[#This Row],[Nome]],Table_Investimentos_Main[Data]&Table_Investimentos_Main[Nome],Table_Investimentos_Main[Moeda Base],"NOT FOUND")} -> BRL | I13: 0.4 | J13: {=Table_Investimentos_Porcent[[#This Row],[Porcentagem]]*_xlfn.XLOOKUP(Table_Investimentos_Porcent[[#This Row],[Data]]&Table_Investimentos_Porcent[[#This Row],[Nome]],Table_Investimentos_Main[Data]&Table_Investimentos_Main[Nome],Table_Investimentos_Main[Total (R$)],"NOT FOUND")} -> 2001.384 | K13: {=Table_Investimentos_Porcent[[#This Row],[Total (R$)]]/_xlfn.XLOOKUP(Table_Investimentos_Porcent[[#This Row],[Data]]&Table_Investimentos_Porcent[[#This Row],[Nome]],Table_Investimentos_Main[Data]&Table_Investimentos_Main[Nome],Table_Investimentos_Main[Cotação Dolar],"NOT FOUND")} -> 387.39964
B14: 46204 | C14: ETF - IAUM | D14: Reserva | E14: Commoditie | F14: - | G14: {=_xlfn.XLOOKUP(Table_Investimentos_Porcent[[#This Row],[Data]]&Table_Investimentos_Porcent[[#This Row],[Nome]],Table_Investimentos_Main[Data]&Table_Investimentos_Main[Nome],Table_Investimentos_Main[Estratégia],"NOT FOUND")} -> Hedge | H14: {=_xlfn.XLOOKUP(Table_Investimentos_Porcent[[#This Row],[Data]]&Table_Investimentos_Porcent[[#This Row],[Nome]],Table_Investimentos_Main[Data]&Table_Investimentos_Main[Nome],Table_Investimentos_Main[Moeda Base],"NOT FOUND")} -> USD | I14: 1 | J14: {=Table_Investimentos_Porcent[[#This Row],[Porcentagem]]*_xlfn.XLOOKUP(Table_Investimentos_Porcent[[#This Row],[Data]]&Table_Investimentos_Porcent[[#This Row],[Nome]],Table_Investimentos_Main[Data]&Table_Investimentos_Main[Nome],Table_Investimentos_Main[Total (R$)],"NOT FOUND")} -> 4695.6773 | K14: {=Table_Investimentos_Porcent[[#This Row],[Total (R$)]]/_xlfn.XLOOKUP(Table_Investimentos_Porcent[[#This Row],[Data]]&Table_Investimentos_Porcent[[#This Row],[Nome]],Table_Investimentos_Main[Data]&Table_Investimentos_Main[Nome],Table_Investimentos_Main[Cotação Dolar],"NOT FOUND")} -> 908.92287
B15: 46204 | C15: ETF - SIVR | D15: Renda Variável | E15: Commoditie | F15: - | G15: {=_xlfn.XLOOKUP(Table_Investimentos_Porcent[[#This Row],[Data]]&Table_Investimentos_Porcent[[#This Row],[Nome]],Table_Investimentos_Main[Data]&Table_Investimentos_Main[Nome],Table_Investimentos_Main[Estratégia],"NOT FOUND")} -> Satellite | H15: {=_xlfn.XLOOKUP(Table_Investimentos_Porcent[[#This Row],[Data]]&Table_Investimentos_Porcent[[#This Row],[Nome]],Table_Investimentos_Main[Data]&Table_Investimentos_Main[Nome],Table_Investimentos_Main[Moeda Base],"NOT FOUND")} -> USD | I15: 1 | J15: {=Table_Investimentos_Porcent[[#This Row],[Porcentagem]]*_xlfn.XLOOKUP(Table_Investimentos_Porcent[[#This Row],[Data]]&Table_Investimentos_Porcent[[#This Row],[Nome]],Table_Investimentos_Main[Data]&Table_Investimentos_Main[Nome],Table_Investimentos_Main[Total (R$)],"NOT FOUND")} -> 908.10688 | K15: {=Table_Investimentos_Porcent[[#This Row],[Total (R$)]]/_xlfn.XLOOKUP(Table_Investimentos_Porcent[[#This Row],[Data]]&Table_Investimentos_Porcent[[#This Row],[Nome]],Table_Investimentos_Main[Data]&Table_Investimentos_Main[Nome],Table_Investimentos_Main[Cotação Dolar],"NOT FOUND")} -> 175.7785
B16: 46204 | C16: ETF - VOO | D16: Renda Variável | E16: Ações EUA | F16: - | G16: {=_xlfn.XLOOKUP(Table_Investimentos_Porcent[[#This Row],[Data]]&Table_Investimentos_Porcent[[#This Row],[Nome]],Table_Investimentos_Main[Data]&Table_Investimentos_Main[Nome],Table_Investimentos_Main[Estratégia],"NOT FOUND")} -> Core | H16: {=_xlfn.XLOOKUP(Table_Investimentos_Porcent[[#This Row],[Data]]&Table_Investimentos_Porcent[[#This Row],[Nome]],Table_Investimentos_Main[Data]&Table_Investimentos_Main[Nome],Table_Investimentos_Main[Moeda Base],"NOT FOUND")} -> USD | I16: 1 | J16: {=Table_Investimentos_Porcent[[#This Row],[Porcentagem]]*_xlfn.XLOOKUP(Table_Investimentos_Porcent[[#This Row],[Data]]&Table_Investimentos_Porcent[[#This Row],[Nome]],Table_Investimentos_Main[Data]&Table_Investimentos_Main[Nome],Table_Investimentos_Main[Total (R$)],"NOT FOUND")} -> 9918.2626 | K16: {=Table_Investimentos_Porcent[[#This Row],[Total (R$)]]/_xlfn.XLOOKUP(Table_Investimentos_Porcent[[#This Row],[Data]]&Table_Investimentos_Porcent[[#This Row],[Nome]],Table_Investimentos_Main[Data]&Table_Investimentos_Main[Nome],Table_Investimentos_Main[Cotação Dolar],"NOT FOUND")} -> 1919.8371
... B30: 46204 | C30: Tesouro IPCA Renda+ 2065 | D30: Renda Fixa | E30: IPCA | F30: Longo | G30: {=_xlfn.XLOOKUP(Table_Investimentos_Porcent[[#This Row],[Data]]&Table_Investimentos_Porcent[[#This Row],[Nome]],Table_Investimentos_Main[Data]&Table_Investimentos_Main[Nome],Table_Investimentos_Main[Estratégia],"NOT FOUND")} -> Core | H30: {=_xlfn.XLOOKUP(Table_Investimentos_Porcent[[#This Row],[Data]]&Table_Investimentos_Porcent[[#This Row],[Nome]],Table_Investimentos_Main[Data]&Table_Investimentos_Main[Nome],Table_Investimentos_Main[Moeda Base],"NOT FOUND")} -> BRL | I30: 1 | J30: {=Table_Investimentos_Porcent[[#This Row],[Porcentagem]]*_xlfn.XLOOKUP(Table_Investimentos_Porcent[[#This Row],[Data]]&Table_Investimentos_Porcent[[#This Row],[Nome]],Table_Investimentos_Main[Data]&Table_Investimentos_Main[Nome],Table_Investimentos_Main[Total (R$)],"NOT FOUND")} -> 11955.66 | K30: {=Table_Investimentos_Porcent[[#This Row],[Total (R$)]]/_xlfn.XLOOKUP(Table_Investimentos_Porcent[[#This Row],[Data]]&Table_Investimentos_Porcent[[#This Row],[Nome]],Table_Investimentos_Main[Data]&Table_Investimentos_Main[Nome],Table_Investimentos_Main[Cotação Dolar],"NOT FOUND")} -> 2314.2077
B31: 45078 | C31: Bitcoin | D31: Cripto | G31: {=_xlfn.XLOOKUP(Table_Investimentos_Porcent[[#This Row],[Data]]&Table_Investimentos_Porcent[[#This Row],[Nome]],Table_Investimentos_Main[Data]&Table_Investimentos_Main[Nome],Table_Investimentos_Main[Estratégia],"NOT FOUND")} -> 0 | H31: {=_xlfn.XLOOKUP(Table_Investimentos_Porcent[[#This Row],[Data]]&Table_Investimentos_Porcent[[#This Row],[Nome]],Table_Investimentos_Main[Data]&Table_Investimentos_Main[Nome],Table_Investimentos_Main[Moeda Base],"NOT FOUND")} -> BTC | I31: 1 | J31: {=Table_Investimentos_Porcent[[#This Row],[Porcentagem]]*_xlfn.XLOOKUP(Table_Investimentos_Porcent[[#This Row],[Data]]&Table_Investimentos_Porcent[[#This Row],[Nome]],Table_Investimentos_Main[Data]&Table_Investimentos_Main[Nome],Table_Investimentos_Main[Total (R$)],"NOT FOUND")} -> 24200.643 | K31: {=Table_Investimentos_Porcent[[#This Row],[Total (R$)]]/_xlfn.XLOOKUP(Table_Investimentos_Porcent[[#This Row],[Data]]&Table_Investimentos_Porcent[[#This Row],[Nome]],Table_Investimentos_Main[Data]&Table_Investimentos_Main[Nome],Table_Investimentos_Main[Cotação Dolar],"NOT FOUND")} -> 4833.3619
B32: 45078 | C32: Liquidez Diaria | D32: Caixa | G32: {=_xlfn.XLOOKUP(Table_Investimentos_Porcent[[#This Row],[Data]]&Table_Investimentos_Porcent[[#This Row],[Nome]],Table_Investimentos_Main[Data]&Table_Investimentos_Main[Nome],Table_Investimentos_Main[Estratégia],"NOT FOUND")} -> 0 | H32: {=_xlfn.XLOOKUP(Table_Investimentos_Porcent[[#This Row],[Data]]&Table_Investimentos_Porcent[[#This Row],[Nome]],Table_Investimentos_Main[Data]&Table_Investimentos_Main[Nome],Table_Investimentos_Main[Moeda Base],"NOT FOUND")} -> BRL | I32: 1 | J32: {=Table_Investimentos_Porcent[[#This Row],[Porcentagem]]*_xlfn.XLOOKUP(Table_Investimentos_Porcent[[#This Row],[Data]]&Table_Investimentos_Porcent[[#This Row],[Nome]],Table_Investimentos_Main[Data]&Table_Investimentos_Main[Nome],Table_Investimentos_Main[Total (R$)],"NOT FOUND")} -> 3698.14 | K32: {=Table_Investimentos_Porcent[[#This Row],[Total (R$)]]/_xlfn.XLOOKUP(Table_Investimentos_Porcent[[#This Row],[Data]]&Table_Investimentos_Porcent[[#This Row],[Nome]],Table_Investimentos_Main[Data]&Table_Investimentos_Main[Nome],Table_Investimentos_Main[Cotação Dolar],"NOT FOUND")} -> 738.59397
B33: 45078 | C33: CDB - 110% | D33: Renda Fixa | G33: {=_xlfn.XLOOKUP(Table_Investimentos_Porcent[[#This Row],[Data]]&Table_Investimentos_Porcent[[#This Row],[Nome]],Table_Investimentos_Main[Data]&Table_Investimentos_Main[Nome],Table_Investimentos_Main[Estratégia],"NOT FOUND")} -> 0 | H33: {=_xlfn.XLOOKUP(Table_Investimentos_Porcent[[#This Row],[Data]]&Table_Investimentos_Porcent[[#This Row],[Nome]],Table_Investimentos_Main[Data]&Table_Investimentos_Main[Nome],Table_Investimentos_Main[Moeda Base],"NOT FOUND")} -> BRL | I33: 1 | J33: {=Table_Investimentos_Porcent[[#This Row],[Porcentagem]]*_xlfn.XLOOKUP(Table_Investimentos_Porcent[[#This Row],[Data]]&Table_Investimentos_Porcent[[#This Row],[Nome]],Table_Investimentos_Main[Data]&Table_Investimentos_Main[Nome],Table_Investimentos_Main[Total (R$)],"NOT FOUND")} -> 20017.71 | K33: {=Table_Investimentos_Porcent[[#This Row],[Total (R$)]]/_xlfn.XLOOKUP(Table_Investimentos_Porcent[[#This Row],[Data]]&Table_Investimentos_Porcent[[#This Row],[Nome]],Table_Investimentos_Main[Data]&Table_Investimentos_Main[Nome],Table_Investimentos_Main[Cotação Dolar],"NOT FOUND")} -> 3997.9449
B34: 45078 | C34: USDT | D34: Reserva | G34: {=_xlfn.XLOOKUP(Table_Investimentos_Porcent[[#This Row],[Data]]&Table_Investimentos_Porcent[[#This Row],[Nome]],Table_Investimentos_Main[Data]&Table_Investimentos_Main[Nome],Table_Investimentos_Main[Estratégia],"NOT FOUND")} -> 0 | H34: {=_xlfn.XLOOKUP(Table_Investimentos_Porcent[[#This Row],[Data]]&Table_Investimentos_Porcent[[#This Row],[Nome]],Table_Investimentos_Main[Data]&Table_Investimentos_Main[Nome],Table_Investimentos_Main[Moeda Base],"NOT FOUND")} -> USD | I34: 1 | J34: {=Table_Investimentos_Porcent[[#This Row],[Porcentagem]]*_xlfn.XLOOKUP(Table_Investimentos_Porcent[[#This Row],[Data]]&Table_Investimentos_Porcent[[#This Row],[Nome]],Table_Investimentos_Main[Data]&Table_Investimentos_Main[Nome],Table_Investimentos_Main[Total (R$)],"NOT FOUND")} -> 5017.014 | K34: {=Table_Investimentos_Porcent[[#This Row],[Total (R$)]]/_xlfn.XLOOKUP(Table_Investimentos_Porcent[[#This Row],[Data]]&Table_Investimentos_Porcent[[#This Row],[Nome]],Table_Investimentos_Main[Data]&Table_Investimentos_Main[Nome],Table_Investimentos_Main[Cotação Dolar],"NOT FOUND")} -> 1002
B35: 45078 | C35: BUSD | D35: Reserva | G35: {=_xlfn.XLOOKUP(Table_Investimentos_Porcent[[#This Row],[Data]]&Table_Investimentos_Porcent[[#This Row],[Nome]],Table_Investimentos_Main[Data]&Table_Investimentos_Main[Nome],Table_Investimentos_Main[Estratégia],"NOT FOUND")} -> 0 | H35: {=_xlfn.XLOOKUP(Table_Investimentos_Porcent[[#This Row],[Data]]&Table_Investimentos_Porcent[[#This Row],[Nome]],Table_Investimentos_Main[Data]&Table_Investimentos_Main[Nome],Table_Investimentos_Main[Moeda Base],"NOT FOUND")} -> USD | I35: 1 | J35: {=Table_Investimentos_Porcent[[#This Row],[Porcentagem]]*_xlfn.XLOOKUP(Table_Investimentos_Porcent[[#This Row],[Data]]&Table_Investimentos_Porcent[[#This Row],[Nome]],Table_Investimentos_Main[Data]&Table_Investimentos_Main[Nome],Table_Investimentos_Main[Total (R$)],"NOT FOUND")} -> 12652.689 | K35: {=Table_Investimentos_Porcent[[#This Row],[Total (R$)]]/_xlfn.XLOOKUP(Table_Investimentos_Porcent[[#This Row],[Data]]&Table_Investimentos_Porcent[[#This Row],[Nome]],Table_Investimentos_Main[Data]&Table_Investimentos_Main[Nome],Table_Investimentos_Main[Cotação Dolar],"NOT FOUND")} -> 2527
B36: 45078 | C36: Dolar | D36: Reserva | G36: {=_xlfn.XLOOKUP(Table_Investimentos_Porcent[[#This Row],[Data]]&Table_Investimentos_Porcent[[#This Row],[Nome]],Table_Investimentos_Main[Data]&Table_Investimentos_Main[Nome],Table_Investimentos_Main[Estratégia],"NOT FOUND")} -> 0 | H36: {=_xlfn.XLOOKUP(Table_Investimentos_Porcent[[#This Row],[Data]]&Table_Investimentos_Porcent[[#This Row],[Nome]],Table_Investimentos_Main[Data]&Table_Investimentos_Main[Nome],Table_Investimentos_Main[Moeda Base],"NOT FOUND")} -> USD | I36: 1 | J36: {=Table_Investimentos_Porcent[[#This Row],[Porcentagem]]*_xlfn.XLOOKUP(Table_Investimentos_Porcent[[#This Row],[Data]]&Table_Investimentos_Porcent[[#This Row],[Nome]],Table_Investimentos_Main[Data]&Table_Investimentos_Main[Nome],Table_Investimentos_Main[Total (R$)],"NOT FOUND")} -> 499.64853 | K36: {=Table_Investimentos_Porcent[[#This Row],[Total (R$)]]/_xlfn.XLOOKUP(Table_Investimentos_Porcent[[#This Row],[Data]]&Table_Investimentos_Porcent[[#This Row],[Nome]],Table_Investimentos_Main[Data]&Table_Investimentos_Main[Nome],Table_Investimentos_Main[Cotação Dolar],"NOT FOUND")} -> 99.79
B37: 45108 | C37: Bitcoin | D37: Cripto | G37: {=_xlfn.XLOOKUP(Table_Investimentos_Porcent[[#This Row],[Data]]&Table_Investimentos_Porcent[[#This Row],[Nome]],Table_Investimentos_Main[Data]&Table_Investimentos_Main[Nome],Table_Investimentos_Main[Estratégia],"NOT FOUND")} -> 0 | H37: {=_xlfn.XLOOKUP(Table_Investimentos_Porcent[[#This Row],[Data]]&Table_Investimentos_Porcent[[#This Row],[Nome]],Table_Investimentos_Main[Data]&Table_Investimentos_Main[Nome],Table_Investimentos_Main[Moeda Base],"NOT FOUND")} -> BTC | I37: 1 | J37: {=Table_Investimentos_Porcent[[#This Row],[Porcentagem]]*_xlfn.XLOOKUP(Table_Investimentos_Porcent[[#This Row],[Data]]&Table_Investimentos_Porcent[[#This Row],[Nome]],Table_Investimentos_Main[Data]&Table_Investimentos_Main[Nome],Table_Investimentos_Main[Total (R$)],"NOT FOUND")} -> 27125.324 | K37: {=Table_Investimentos_Porcent[[#This Row],[Total (R$)]]/_xlfn.XLOOKUP(Table_Investimentos_Porcent[[#This Row],[Data]]&Table_Investimentos_Porcent[[#This Row],[Nome]],Table_Investimentos_Main[Data]&Table_Investimentos_Main[Nome],Table_Investimentos_Main[Cotação Dolar],"NOT FOUND")} -> 5547.1011
B38: 45108 | C38: Liquidez Diaria | D38: Caixa | G38: {=_xlfn.XLOOKUP(Table_Investimentos_Porcent[[#This Row],[Data]]&Table_Investimentos_Porcent[[#This Row],[Nome]],Table_Investimentos_Main[Data]&Table_Investimentos_Main[Nome],Table_Investimentos_Main[Estratégia],"NOT FOUND")} -> 0 | H38: {=_xlfn.XLOOKUP(Table_Investimentos_Porcent[[#This Row],[Data]]&Table_Investimentos_Porcent[[#This Row],[Nome]],Table_Investimentos_Main[Data]&Table_Investimentos_Main[Nome],Table_Investimentos_Main[Moeda Base],"NOT FOUND")} -> BRL | I38: 1 | J38: {=Table_Investimentos_Porcent[[#This Row],[Porcentagem]]*_xlfn.XLOOKUP(Table_Investimentos_Porcent[[#This Row],[Data]]&Table_Investimentos_Porcent[[#This Row],[Nome]],Table_Investimentos_Main[Data]&Table_Investimentos_Main[Nome],Table_Investimentos_Main[Total (R$)],"NOT FOUND")} -> 4238.83 | K38: {=Table_Investimentos_Porcent[[#This Row],[Total (R$)]]/_xlfn.XLOOKUP(Table_Investimentos_Porcent[[#This Row],[Data]]&Table_Investimentos_Porcent[[#This Row],[Nome]],Table_Investimentos_Main[Data]&Table_Investimentos_Main[Nome],Table_Investimentos_Main[Cotação Dolar],"NOT FOUND")} -> 866.8364
B39: 45108 | C39: CDB - 110% | D39: Renda Fixa | G39: {=_xlfn.XLOOKUP(Table_Investimentos_Porcent[[#This Row],[Data]]&Table_Investimentos_Porcent[[#This Row],[Nome]],Table_Investimentos_Main[Data]&Table_Investimentos_Main[Nome],Table_Investimentos_Main[Estratégia],"NOT FOUND")} -> 0 | H39: {=_xlfn.XLOOKUP(Table_Investimentos_Porcent[[#This Row],[Data]]&Table_Investimentos_Porcent[[#This Row],[Nome]],Table_Investimentos_Main[Data]&Table_Investimentos_Main[Nome],Table_Investimentos_Main[Moeda Base],"NOT FOUND")} -> BRL | I39: 1 | J39: {=Table_Investimentos_Porcent[[#This Row],[Porcentagem]]*_xlfn.XLOOKUP(Table_Investimentos_Porcent[[#This Row],[Data]]&Table_Investimentos_Porcent[[#This Row],[Nome]],Table_Investimentos_Main[Data]&Table_Investimentos_Main[Nome],Table_Investimentos_Main[Total (R$)],"NOT FOUND")} -> 20277.35 | K39: {=Table_Investimentos_Porcent[[#This Row],[Total (R$)]]/_xlfn.XLOOKUP(Table_Investimentos_Porcent[[#This Row],[Data]]&Table_Investimentos_Porcent[[#This Row],[Nome]],Table_Investimentos_Main[Data]&Table_Investimentos_Main[Nome],Table_Investimentos_Main[Cotação Dolar],"NOT FOUND")} -> 4146.6973
B40: 45108 | C40: USDT | D40: Caixa | G40: {=_xlfn.XLOOKUP(Table_Investimentos_Porcent[[#This Row],[Data]]&Table_Investimentos_Porcent[[#This Row],[Nome]],Table_Investimentos_Main[Data]&Table_Investimentos_Main[Nome],Table_Investimentos_Main[Estratégia],"NOT FOUND")} -> 0 | H40: {=_xlfn.XLOOKUP(Table_Investimentos_Porcent[[#This Row],[Data]]&Table_Investimentos_Porcent[[#This Row],[Nome]],Table_Investimentos_Main[Data]&Table_Investimentos_Main[Nome],Table_Investimentos_Main[Moeda Base],"NOT FOUND")} -> USD | I40: 1 | J40: {=Table_Investimentos_Porcent[[#This Row],[Porcentagem]]*_xlfn.XLOOKUP(Table_Investimentos_Porcent[[#This Row],[Data]]&Table_Investimentos_Porcent[[#This Row],[Nome]],Table_Investimentos_Main[Data]&Table_Investimentos_Main[Nome],Table_Investimentos_Main[Total (R$)],"NOT FOUND")} -> 4934.01 | K40: {=Table_Investimentos_Porcent[[#This Row],[Total (R$)]]/_xlfn.XLOOKUP(Table_Investimentos_Porcent[[#This Row],[Data]]&Table_Investimentos_Porcent[[#This Row],[Nome]],Table_Investimentos_Main[Data]&Table_Investimentos_Main[Nome],Table_Investimentos_Main[Cotação Dolar],"NOT FOUND")} -> 1009
B41: 45108 | C41: BUSD | D41: Caixa | G41: {=_xlfn.XLOOKUP(Table_Investimentos_Porcent[[#This Row],[Data]]&Table_Investimentos_Porcent[[#This Row],[Nome]],Table_Investimentos_Main[Data]&Table_Investimentos_Main[Nome],Table_Investimentos_Main[Estratégia],"NOT FOUND")} -> 0 | H41: {=_xlfn.XLOOKUP(Table_Investimentos_Porcent[[#This Row],[Data]]&Table_Investimentos_Porcent[[#This Row],[Nome]],Table_Investimentos_Main[Data]&Table_Investimentos_Main[Nome],Table_Investimentos_Main[Moeda Base],"NOT FOUND")} -> USD | I41: 1 | J41: {=Table_Investimentos_Porcent[[#This Row],[Porcentagem]]*_xlfn.XLOOKUP(Table_Investimentos_Porcent[[#This Row],[Data]]&Table_Investimentos_Porcent[[#This Row],[Nome]],Table_Investimentos_Main[Data]&Table_Investimentos_Main[Nome],Table_Investimentos_Main[Total (R$)],"NOT FOUND")} -> 12366.81 | K41: {=Table_Investimentos_Porcent[[#This Row],[Total (R$)]]/_xlfn.XLOOKUP(Table_Investimentos_Porcent[[#This Row],[Data]]&Table_Investimentos_Porcent[[#This Row],[Nome]],Table_Investimentos_Main[Data]&Table_Investimentos_Main[Nome],Table_Investimentos_Main[Cotação Dolar],"NOT FOUND")} -> 2529
B42: 45108 | C42: Dolar | D42: Caixa | G42: {=_xlfn.XLOOKUP(Table_Investimentos_Porcent[[#This Row],[Data]]&Table_Investimentos_Porcent[[#This Row],[Nome]],Table_Investimentos_Main[Data]&Table_Investimentos_Main[Nome],Table_Investimentos_Main[Estratégia],"NOT FOUND")} -> 0 | H42: {=_xlfn.XLOOKUP(Table_Investimentos_Porcent[[#This Row],[Data]]&Table_Investimentos_Porcent[[#This Row],[Nome]],Table_Investimentos_Main[Data]&Table_Investimentos_Main[Nome],Table_Investimentos_Main[Moeda Base],"NOT FOUND")} -> USD | I42: 1 | J42: {=Table_Investimentos_Porcent[[#This Row],[Porcentagem]]*_xlfn.XLOOKUP(Table_Investimentos_Porcent[[#This Row],[Data]]&Table_Investimentos_Porcent[[#This Row],[Nome]],Table_Investimentos_Main[Data]&Table_Investimentos_Main[Nome],Table_Investimentos_Main[Total (R$)],"NOT FOUND")} -> 487.9731 | K42: {=Table_Investimentos_Porcent[[#This Row],[Total (R$)]]/_xlfn.XLOOKUP(Table_Investimentos_Porcent[[#This Row],[Data]]&Table_Investimentos_Porcent[[#This Row],[Nome]],Table_Investimentos_Main[Data]&Table_Investimentos_Main[Nome],Table_Investimentos_Main[Cotação Dolar],"NOT FOUND")} -> 99.79
... B333: 46174 | C333: LCI BRB - Jun/27 | D333: Renda Fixa | G333: {=_xlfn.XLOOKUP(Table_Investimentos_Porcent[[#This Row],[Data]]&Table_Investimentos_Porcent[[#This Row],[Nome]],Table_Investimentos_Main[Data]&Table_Investimentos_Main[Nome],Table_Investimentos_Main[Estratégia],"NOT FOUND")} -> 0 | H333: {=_xlfn.XLOOKUP(Table_Investimentos_Porcent[[#This Row],[Data]]&Table_Investimentos_Porcent[[#This Row],[Nome]],Table_Investimentos_Main[Data]&Table_Investimentos_Main[Nome],Table_Investimentos_Main[Moeda Base],"NOT FOUND")} -> BRL | I333: 1 | J333: {=Table_Investimentos_Porcent[[#This Row],[Porcentagem]]*_xlfn.XLOOKUP(Table_Investimentos_Porcent[[#This Row],[Data]]&Table_Investimentos_Porcent[[#This Row],[Nome]],Table_Investimentos_Main[Data]&Table_Investimentos_Main[Nome],Table_Investimentos_Main[Total (R$)],"NOT FOUND")} -> 6000 | K333: {=Table_Investimentos_Porcent[[#This Row],[Total (R$)]]/_xlfn.XLOOKUP(Table_Investimentos_Porcent[[#This Row],[Data]]&Table_Investimentos_Porcent[[#This Row],[Nome]],Table_Investimentos_Main[Data]&Table_Investimentos_Main[Nome],Table_Investimentos_Main[Cotação Dolar],"NOT FOUND")} -> 1157.7647
B334: 46235 | C334: USDC | D334: Caixa | E334: Stablecoin | F334: D+0 | G334: Core | H334: USD | I334: 1 | J334: 8807.1311 | K334: 1704.76
B335: 46235 | C335: Bitcoin 02 | D335: Cripto | E335: BTC | F335: - | G335: Core-Satellite | H335: BTC | I335: 1 | J335: 1957.8315 | K335: 378.96936
B336: 46235 | C336: Solana | D336: Cripto | E336: Altcoin | F336: - | G336: Satellite | H336: USD | I336: 1 | J336: 2435.167 | K336: 471.36522
B337: 46235 | C337: Time Deposit | D337: Caixa | E337: Pós-fixado | F337: Curto | G337: Core | H337: USD | I337: 1 | J337: 1331.1748 | K337: 257.67
B338: 46235 | C338: Flexible Account | D338: Caixa | E338: Curto | F338: D+0 | G338: Core | H338: USD | I338: 1 | J338: 2991.2815 | K338: 579.01
B339: 46235 | C339: ETF - GLDM | D339: Reserva | E339: Commoditie | F339: - | G339: Hedge | H339: USD | I339: 1 | J339: 5764.7618 | K339: 1115.8611
B340: 46235 | C340: ETF - GPCA11 | D340: Renda Fixa | E340: IPCA | F340: Curto | G340: Core | H340: BRL | I340: 0.6 | J340: 3002.076 | K340: 581.09945
B341: 46235 | C341: Tesouro IPCA+ 2032 | D341: Renda Fixa | E341: IPCA | F341: Médio | G341: Core | H341: BRL | I341: 1 | J341: 2986.86 | K341: 578.15416
B342: 46235 | C342: ETF - GPCA11 | D342: Renda Fixa | E342: IPCA | F342: Médio | G342: Core | H342: BRL | I342: 0.4 | J342: 2001.384 | K342: 387.39964
B343: 46235 | C343: ETF - IAUM | D343: Reserva | E343: Commoditie | F343: - | G343: Hedge | H343: USD | I343: 1 | J343: 4695.6773 | K343: 908.92287
B344: 46235 | C344: ETF - SIVR | D344: Renda Variável | E344: Commoditie | F344: - | G344: Satellite | H344: USD | I344: 1 | J344: 908.1069 | K344: 175.7785
B345: 46235 | C345: ETF - VOO | D345: Renda Variável | E345: Ações EUA | F345: - | G345: Core | H345: USD | I345: 1 | J345: 9918.2626 | K345: 1919.8371
... B359: 46235 | C359: Tesouro IPCA Renda+ 2065 | D359: Renda Fixa | E359: IPCA | F359: Longo | G359: Core | H359: BRL | I359: 1 | J359: 11955.66 | K359: 2314.2077

Sheet Cotacoes
A1: Última Atualização
A2: 46214.117
C3: Tabela Cotações
C4: Data | D4: Ticker | E4: Valor | F4: Moeda Base | G4: Tipo
C5: 45078 | D5: USD | E5: 5.007 | F5: USD | G5: FIAT
C6: 45078 | D6: BTC | E6: 135052 | F6: BTC | G6: CRIPTO
C7: 45108 | D7: USD | E7: 4.89 | F7: USD | G7: FIAT
C8: 45108 | D8: BTC | E8: 151373.22 | F8: BTC | G8: CRIPTO
C9: 45200 | D9: USD | E9: 5.05 | F9: USD | G9: FIAT
C10: 45200 | D10: BTC | E10: 174262.84 | F10: BTC | G10: CRIPTO
C11: 45261 | D11: USD | E11: 4.95 | F11: USD | G11: FIAT
C12: 45261 | D12: BTC | E12: 207740.79 | F12: BTC | G12: CRIPTO
C13: 45292 | D13: USD | E13: 4.98 | F13: USD | G13: FIAT
C14: 45292 | D14: BTC | E14: 213280 | F14: BTC | G14: CRIPTO
C15: 45323 | D15: USD | E15: 4.97 | F15: USD | G15: FIAT
C16: 45323 | D16: BTC | E16: 258315 | F16: BTC | G16: CRIPTO
... C148: 46235 | D148: SOL | E148: 398.81 | F148: USD | G148: CRIPTO

Sheet Graficos
O13: % Atual | P13: % Ideal | Q13: R$ Atual | R13: R$ Ideal | S13: Diferença
N14: COMPRAR
N15: Ações EUA | O15: 0.57913666 | P15: 0.5 | Q15: 15660.59 | R15: 21707.273 | S15: -6046.683
N16: Ações - Ex: USA | O16: 0.074176991 | P16: 0.2 | Q16: 2005.84 | R16: 8682.9092 | S16: -6677.0693
N17: Ações BR | O17: 0.24352541 | P17: 0.2 | Q17: 6585.236 | R17: 8682.9092 | S17: -2097.6732
N18: Commoditie | O18: 0.033582259 | P18: 0.045 | Q18: 908.10688 | R18: 1953.6546 | S18: -1045.5477
N19: Imobiliário BR | O19: 0.069578688 | P19: 0.05 | Q19: 1881.496 | R19: 2170.7273 | S19: -289.23131

Sheet Tables_Atual_Ideal
B2: Cenário Atual | J2: Cenário Ideal
C5: Total (R$) | D5: Porcentagem | J5: Classe | K5: Total Ideal | L5: Porcentagem
B6: Caixa | C6: 32403.737 | D6: 0.14927595 | J6: =B6 -> Caixa | K6: =GETPIVOTDATA("Total (R$)",$B$5)*Table_ClasseAtivos[[#This Row],[Porcentagem]] -> 32560.91 | L6: 0.15
B7: Cripto | C7: 100713.94 | D7: 0.46396404 | J7: =B7 -> Cripto | K7: =GETPIVOTDATA("Total (R$)",$B$5)*Table_ClasseAtivos[[#This Row],[Porcentagem]] -> 75975.456 | L7: 0.35
B8: Renda Fixa | C8: 46453.345 | D8: 0.21399899 | J8: =B8 -> Renda Fixa | K8: =GETPIVOTDATA("Total (R$)",$B$5)*Table_ClasseAtivos[[#This Row],[Porcentagem]] -> 54268.183 | L8: 0.25
B9: Renda Variável | C9: 27041.269 | D9: 0.12457239 | J9: =B9 -> Renda Variável | K9: =GETPIVOTDATA("Total (R$)",$B$5)*Table_ClasseAtivos[[#This Row],[Porcentagem]] -> 43414.546 | L9: 0.2
B10: Reserva | C10: 10460.439 | D10: 0.048188637 | J10: =B10 -> Reserva | K10: =GETPIVOTDATA("Total (R$)",$B$5)*Table_ClasseAtivos[[#This Row],[Porcentagem]] -> 10853.637 | L10: 0.05
B11: Grand Total | C11: 217072.73 | D11: 1 | J11: Total | K11: =SUBTOTAL(109,Table_ClasseAtivos[Total Ideal]) -> 217072.73 | L11: =SUBTOTAL(109,Table_ClasseAtivos[Porcentagem]) -> 1
B14: Porcentage
C15: Caixa | D15: Cripto | E15: Renda Fixa | F15: Renda Variável | G15: Reserva | J15: Moeda | K15: Caixa | L15: Cripto | M15: Renda Fixa | N15: Renda Variável | O15: Reserva
B16: BRL | C16: 0.088791208 | D16: 0 | E16: 0.21399899 | F16: 0.059589636 | G16: 0 | J16: =B16 -> BRL | K16: 0.1 | L16: 0 | M16: 0.25 | N16: 0.04 | O16: 0
B17: BTC | C17: 0 | D17: 0.45274583 | E17: 0 | F17: 0 | G17: 0 | J17: =B17 -> BTC | K17: 0 | L17: 0.325 | M17: 0 | N17: 0 | O17: 0
B18: USD | C18: 0.060484738 | D18: 0.011218208 | E18: 0 | F18: 0.064982754 | G18: 0.048188637 | J18: =B18 -> USD | K18: 0.05 | L18: 0.025 | M18: 0 | N18: 0.16 | O18: 0.05
B19: Grand Total | C19: 0.14927595 | D19: 0.46396404 | E19: 0.21399899 | F19: 0.12457239 | G19: 0.048188637 | J19: Total | K19: =SUBTOTAL(109,Table_ClasseAtivosXMoeda[Caixa]) -> 0.15 | L19: =SUBTOTAL(109,Table_ClasseAtivosXMoeda[Cripto]) -> 0.35 | M19: =SUBTOTAL(109,Table_ClasseAtivosXMoeda[Renda Fixa]) -> 0.25 | N19: =SUBTOTAL(109,Table_ClasseAtivosXMoeda[Renda Variável]) -> 0.2 | O19: =SUBTOTAL(109,Table_ClasseAtivosXMoeda[Reserva]) -> 0.05
C22: Total (R$) | D22: Porcentagem | J22: Moeda | K22: Total Ideal | L22: Porcentagem
B23: BRL | C23: 78662.78 | D23: 0.36237983 | J23: =B23 -> BRL | K23: =GETPIVOTDATA("Total (R$)",$B$22)*Table_Moeda[[#This Row],[Porcentagem]] -> 84658.365 | L23: 0.39
B24: BTC | C24: 98278.774 | D24: 0.45274583 | J24: =B24 -> BTC | K24: =GETPIVOTDATA("Total (R$)",$B$22)*Table_Moeda[[#This Row],[Porcentagem]] -> 70548.638 | L24: 0.325
B25: USD | C25: 40131.177 | D25: 0.18487434 | J25: =B25 -> USD | K25: =GETPIVOTDATA("Total (R$)",$B$22)*Table_Moeda[[#This Row],[Porcentagem]] -> 61865.728 | L25: 0.285
B26: Grand Total | C26: 217072.73 | D26: 1 | J26: Total | K26: =SUBTOTAL(109,Table_Moeda[Total Ideal]) -> 217072.73 | L26: =SUBTOTAL(109,Table_Moeda[Porcentagem]) -> 1
C29: Total (R$) | D29: Porcentagem | J29: Estratégia | K29: Total Ideal | L29: Porcentagem
B30: Core | C30: 103716.47 | D30: 0.47779594 | J30: =B30 -> Core | K30: =Table_Estrategia[[#This Row],[Porcentagem]]*GETPIVOTDATA("Total (R$)",Tables_Atual_Ideal!$B$29) -> 119390 | L30: 0.55
B31: Core-Satellite | C31: 98278.774 | D31: 0.45274583 | J31: =B31 -> Core-Satellite | K31: =Table_Estrategia[[#This Row],[Porcentagem]]*GETPIVOTDATA("Total (R$)",Tables_Atual_Ideal!$B$29) -> 75975.456 | L31: 0.35
B32: Hedge | C32: 10460.439 | D32: 0.048188637 | J32: =B32 -> Hedge | K32: =Table_Estrategia[[#This Row],[Porcentagem]]*GETPIVOTDATA("Total (R$)",Tables_Atual_Ideal!$B$29) -> 10853.637 | L32: 0.05
B33: Satellite | C33: 4617.0483 | D33: 0.021269591 | J33: =B33 -> Satellite | K33: =Table_Estrategia[[#This Row],[Porcentagem]]*GETPIVOTDATA("Total (R$)",Tables_Atual_Ideal!$B$29) -> 10853.637 | L33: 0.05
B34: Grand Total | C34: 217072.73 | D34: 1 | J34: Total | L34: =SUBTOTAL(109,Table_Estrategia[Porcentagem]) -> 1
B37: Classe | C37: Renda Fixa
B39: Sum of Total (R$)
C40: Curto | D40: Médio | E40: Longo | J40: Subclasse | K40: Curto | L40: Médio | M40: Longo
B41: IPCA | C41: 0.064625615 | D41: 0.1073818 | E41: 0.25736919 | J41: =B41 -> IPCA | K41: 0.15 | L41: 0.25 | M41: 0.15
B42: Pós-fixado | C42: 0.21133273 | D42: 0.25803337 | E42: 0.10125729 | J42: =B42 -> Pós-fixado | K42: 0.1 | L42: 0.25 | M42: 0.1
B43: Grand Total | C43: 0.27595834 | D43: 0.36541517 | E43: 0.35862649 | J43: Total | K43: =SUBTOTAL(109,Table_RendaFixaXDuration[Curto]) -> 0.25 | L43: =SUBTOTAL(109,Table_RendaFixaXDuration[Médio]) -> 0.5 | M43: =SUBTOTAL(109,Table_RendaFixaXDuration[Longo]) -> 0.25
B46: Classe | C46: Renda Variável
C48: Porcentagem | J48: Subclasse | K48: Porcentagem
B49: Ações EUA | C49: 0.57913666 | J49: =B49 -> Ações EUA | K49: 0.5
B50: Ações - Ex: USA | C50: 0.074176991 | J50: =B50 -> Ações - Ex: USA | K50: 0.2
B51: Ações BR | C51: 0.24352541 | J51: =B51 -> Ações BR | K51: 0.2
B52: Commoditie | C52: 0.033582259 | J52: =B52 -> Commoditie | K52: 0.045
B53: Imobiliário BR | C53: 0.069578688 | J53: =B53 -> Imobiliário BR | K53: 0.05
B54: Grand Total | C54: 1 | J54: Total | K54: =SUBTOTAL(109,Table_RendaVariavel[Porcentagem]) -> 0.995
B58: Classe | C58: Renda Variável
B60: Sum of Total (R$) | J60: Tipo | K60: Classificação | L60: Subclassificação | M60: Percentual Atual | N60: Total Atual | O60: Percentual Ideal | P60: Total Ideal | Q60: Diferenca | R60: Acao
C61: Ações - Ex: USA | D61: Ações BR | E61: Ações EUA | F61: Commoditie | G61: Imobiliário BR | J61: Reserva | K61: 1- Geral | L61: 1- Classe | M61: =GETPIVOTDATA("Porcentagem",$B$5,"Classe","Reserva") -> 0.048188637 | N61: =GETPIVOTDATA("Total (R$)",$B$5,"Classe","Reserva") -> 10460.439 | O61: =Tables_Atual_Ideal!L10 -> 0.05 | P61: =Tables_Atual_Ideal!K10 -> 10853.637 | Q61: =Table17[[#This Row],[Total Atual]]-Table17[[#This Row],[Total Ideal]] -> -393.19745 | R61: =IF(Table17[[#This Row],[Diferenca]]>0,"VENDER","COMPRAR") -> COMPRAR
B62: BRL | C62: 0 | D62: 0.24352541 | E62: 0.16524938 | F62: 0 | G62: 0.069578688 | J62: Caixa | K62: 1- Geral | L62: 1- Classe | M62: =GETPIVOTDATA("Porcentagem",$B$5,"Classe","Caixa") -> 0.14927595 | N62: =GETPIVOTDATA("Total (R$)",$B$5,"Classe","Caixa") -> 32403.737 | O62: =Tables_Atual_Ideal!L6 -> 0.15 | P62: =Tables_Atual_Ideal!K6 -> 32560.91 | Q62: =Table17[[#This Row],[Total Atual]]-Table17[[#This Row],[Total Ideal]] -> -157.17231 | R62: =IF(Table17[[#This Row],[Diferenca]]>0,"VENDER","COMPRAR") -> COMPRAR
B63: USD | C63: 0.074176991 | D63: 0 | E63: 0.41388727 | F63: 0.033582259 | G63: 0 | J63: Renda Variável | K63: 1- Geral | L63: 1- Classe | M63: =GETPIVOTDATA("Porcentagem",$B$5,"Classe","Renda Variável") -> 0.12457239 | N63: =GETPIVOTDATA("Total (R$)",$B$5,"Classe","Renda Variável") -> 27041.269 | O63: =Tables_Atual_Ideal!L9 -> 0.2 | P63: =Tables_Atual_Ideal!K9 -> 43414.546 | Q63: =Table17[[#This Row],[Total Atual]]-Table17[[#This Row],[Total Ideal]] -> -16373.277 | R63: =IF(Table17[[#This Row],[Diferenca]]>0,"VENDER","COMPRAR") -> COMPRAR
B64: Grand Total | C64: 0.074176991 | D64: 0.24352541 | E64: 0.57913666 | F64: 0.033582259 | G64: 0.069578688 | J64: Renda Fixa | K64: 1- Geral | L64: 1- Classe | M64: =GETPIVOTDATA("Porcentagem",$B$5,"Classe","Renda Fixa") -> 0.21399899 | N64: =GETPIVOTDATA("Total (R$)",$B$5,"Classe","Renda Fixa") -> 46453.345 | O64: =Tables_Atual_Ideal!L8 -> 0.25 | P64: =Tables_Atual_Ideal!K8 -> 54268.183 | Q64: =Table17[[#This Row],[Total Atual]]-Table17[[#This Row],[Total Ideal]] -> -7814.8377 | R64: =IF(Table17[[#This Row],[Diferenca]]>0,"VENDER","COMPRAR") -> COMPRAR
J65: Cripto | K65: 1- Geral | L65: 1- Classe | M65: =GETPIVOTDATA("Porcentagem",$B$5,"Classe","Cripto") -> 0.46396404 | N65: =GETPIVOTDATA("Total (R$)",$B$5,"Classe","Cripto") -> 100713.94 | O65: =Tables_Atual_Ideal!L7 -> 0.35 | P65: =Tables_Atual_Ideal!K7 -> 75975.456 | Q65: =Table17[[#This Row],[Total Atual]]-Table17[[#This Row],[Total Ideal]] -> 24738.485 | R65: =IF(Table17[[#This Row],[Diferenca]]>0,"VENDER","COMPRAR") -> VENDER
J66: USD | K66: 1- Geral | L66: 2- Moeda | M66: =GETPIVOTDATA("Porcentagem",$B$22,"Moeda Base","USD") -> 0.18487434 | N66: =GETPIVOTDATA("Total (R$)",$B$22,"Moeda Base","USD") -> 40131.177 | O66: =Tables_Atual_Ideal!L25 -> 0.285 | P66: =Tables_Atual_Ideal!K25 -> 61865.728 | Q66: =Table17[[#This Row],[Total Atual]]-Table17[[#This Row],[Total Ideal]] -> -21734.551 | R66: =IF(Table17[[#This Row],[Diferenca]]>0,"VENDER","COMPRAR") -> COMPRAR
J67: BTC | K67: 1- Geral | L67: 2- Moeda | M67: =GETPIVOTDATA("Porcentagem",$B$22,"Moeda Base","BTC") -> 0.45274583 | N67: =GETPIVOTDATA("Total (R$)",$B$22,"Moeda Base","BTC") -> 98278.774 | O67: =Tables_Atual_Ideal!L24 -> 0.325 | P67: =Tables_Atual_Ideal!K24 -> 70548.638 | Q67: =Table17[[#This Row],[Total Atual]]-Table17[[#This Row],[Total Ideal]] -> 27730.136 | R67: =IF(Table17[[#This Row],[Diferenca]]>0,"VENDER","COMPRAR") -> VENDER
B68: Mês Base | C68: Sum of Total (R$) | J68: BRL | K68: 1- Geral | L68: 2- Moeda | M68: =GETPIVOTDATA("Porcentagem",$B$22,"Moeda Base","BRL") -> 0.36237983 | N68: =GETPIVOTDATA("Total (R$)",$B$22,"Moeda Base","BRL") -> 78662.78 | O68: =Tables_Atual_Ideal!L23 -> 0.39 | P68: =Tables_Atual_Ideal!K23 -> 84658.365 | Q68: =Table17[[#This Row],[Total Atual]]-Table17[[#This Row],[Total Ideal]] -> -5995.5851 | R68: =IF(Table17[[#This Row],[Diferenca]]>0,"VENDER","COMPRAR") -> COMPRAR
B69: 45870 | C69: 220555.64 | J69: Hedge | K69: 1- Geral | L69: 3- Estratégia | M69: =GETPIVOTDATA("Porcentagem",$B$29,"Estratégia","Hedge") -> 0.048188637 | N69: =GETPIVOTDATA("Total (R$)",$B$29,"Estratégia","Hedge") -> 10460.439 | O69: =Tables_Atual_Ideal!L32 -> 0.05 | P69: =Tables_Atual_Ideal!K32 -> 10853.637 | Q69: =Table17[[#This Row],[Total Atual]]-Table17[[#This Row],[Total Ideal]] -> -393.19745 | R69: =IF(Table17[[#This Row],[Diferenca]]>0,"VENDER","COMPRAR") -> COMPRAR
B70: 45901 | C70: 225232.88 | J70: Satellite | K70: 1- Geral | L70: 3- Estratégia | M70: =GETPIVOTDATA("Porcentagem",$B$29,"Estratégia","Satellite") -> 0.021269591 | N70: =GETPIVOTDATA("Total (R$)",$B$29,"Estratégia","Satellite") -> 4617.0483 | O70: =Tables_Atual_Ideal!L33 -> 0.05 | P70: =Tables_Atual_Ideal!K33 -> 10853.637 | Q70: =Table17[[#This Row],[Total Atual]]-Table17[[#This Row],[Total Ideal]] -> -6236.5883 | R70: =IF(Table17[[#This Row],[Diferenca]]>0,"VENDER","COMPRAR") -> COMPRAR
B71: 45931 | C71: 231459.57 | J71: Core-Satellite | K71: 1- Geral | L71: 3- Estratégia | M71: =GETPIVOTDATA("Porcentagem",$B$29,"Estratégia","Core-Satellite") -> 0.45274583 | N71: =GETPIVOTDATA("Total (R$)",$B$29,"Estratégia","Core-Satellite") -> 98278.774 | O71: =Tables_Atual_Ideal!L31 -> 0.35 | P71: =Tables_Atual_Ideal!K31 -> 75975.456 | Q71: =Table17[[#This Row],[Total Atual]]-Table17[[#This Row],[Total Ideal]] -> 22303.318 | R71: =IF(Table17[[#This Row],[Diferenca]]>0,"VENDER","COMPRAR") -> VENDER
B72: 45962 | C72: 232057.07 | J72: Core | K72: 1- Geral | L72: 3- Estratégia | M72: =GETPIVOTDATA("Porcentagem",$B$29,"Estratégia","Core") -> 0.47779594 | N72: =GETPIVOTDATA("Total (R$)",$B$29,"Estratégia","Core") -> 103716.47 | O72: =Tables_Atual_Ideal!L30 -> 0.55 | P72: =Tables_Atual_Ideal!K30 -> 119390 | Q72: =Table17[[#This Row],[Total Atual]]-Table17[[#This Row],[Total Ideal]] -> -15673.532 | R72: =IF(Table17[[#This Row],[Diferenca]]>0,"VENDER","COMPRAR") -> COMPRAR
B73: 45992 | C73: 214211.34 | J73: Caixa (USD) | K73: 2- Caixa | L73: 1- Moeda | M73: =GETPIVOTDATA("Total (R$)2",$B$14,"Classe","Caixa","Moeda Base","USD") -> 0.060484738 | N73: =Table17[[#This Row],[Percentual Atual]]*GETPIVOTDATA("Total (R$)",$B$5) -> 13129.587 | O73: =$K$18 -> 0.05 | P73: =Table17[[#This Row],[Percentual Ideal]]*Table_ClasseAtivos[[#Totals],[Total Ideal]] -> 10853.637 | Q73: =Table17[[#This Row],[Total Atual]]-Table17[[#This Row],[Total Ideal]] -> 2275.9508 | R73: =IF(Table17[[#This Row],[Diferenca]]>0,"VENDER","COMPRAR") -> VENDER
B74: 46023 | C74: 215929.94 | J74: Caixa (R$) | K74: 2- Caixa | L74: 1- Moeda | M74: =GETPIVOTDATA("Total (R$)2",$B$14,"Classe","Caixa","Moeda Base","BRL") -> 0.088791208 | N74: =Table17[[#This Row],[Percentual Atual]]*GETPIVOTDATA("Total (R$)",$B$5) -> 19274.15 | O74: =$K$16 -> 0.1 | P74: =Table17[[#This Row],[Percentual Ideal]]*Table_ClasseAtivos[[#Totals],[Total Ideal]] -> 21707.273 | Q74: =Table17[[#This Row],[Total Atual]]-Table17[[#This Row],[Total Ideal]] -> -2433.1231 | R74: =IF(Table17[[#This Row],[Diferenca]]>0,"VENDER","COMPRAR") -> COMPRAR
B75: 46054 | C75: 187954.69 | J75: Pós-fixado - Curto | K75: 2- Renda Fixa | L75: 1- Subclasse | M75: =GETPIVOTDATA("Total (R$)",$B$39,"Subclasse","Pós-fixado","Duração","Curto") -> 0.21133273 | N75: =Table17[[#This Row],[Percentual Atual]]*GETPIVOTDATA("Total (R$)",$B$5,"Classe","Renda Fixa") -> 9817.112 | O75: =Tables_Atual_Ideal!K42 -> 0.1 | P75: =Table17[[#This Row],[Percentual Ideal]]*$K$8 -> 5426.8183 | Q75: =Table17[[#This Row],[Total Atual]]-Table17[[#This Row],[Total Ideal]] -> 4390.2937 | R75: =IF(Table17[[#This Row],[Diferenca]]>0,"VENDER","COMPRAR") -> VENDER
B76: 46082 | C76: 199651.29 | J76: Pós-fixado - Longo | K76: 2- Renda Fixa | L76: 1- Subclasse | M76: =GETPIVOTDATA("Total (R$)",$B$39,"Subclasse","Pós-fixado","Duração","Longo") -> 0.10125729 | N76: =Table17[[#This Row],[Percentual Atual]]*GETPIVOTDATA("Total (R$)",$B$5,"Classe","Renda Fixa") -> 4703.74 | O76: =Tables_Atual_Ideal!M42 -> 0.1 | P76: =Table17[[#This Row],[Percentual Ideal]]*$K$8 -> 5426.8183 | Q76: =Table17[[#This Row],[Total Atual]]-Table17[[#This Row],[Total Ideal]] -> -723.07827 | R76: =IF(Table17[[#This Row],[Diferenca]]>0,"VENDER","COMPRAR") -> COMPRAR
B77: 46113 | C77: 207017.15 | J77: IPCA - Curto | K77: 2- Renda Fixa | L77: 1- Subclasse | M77: =GETPIVOTDATA("Total (R$)",$B$39,"Subclasse","IPCA","Duração","Curto") -> 0.064625615 | N77: =Table17[[#This Row],[Percentual Atual]]*GETPIVOTDATA("Total (R$)",$B$5,"Classe","Renda Fixa") -> 3002.076 | O77: =Tables_Atual_Ideal!K41 -> 0.15 | P77: =Table17[[#This Row],[Percentual Ideal]]*$K$8 -> 8140.2274 | Q77: =Table17[[#This Row],[Total Atual]]-Table17[[#This Row],[Total Ideal]] -> -5138.1514 | R77: =IF(Table17[[#This Row],[Diferenca]]>0,"VENDER","COMPRAR") -> COMPRAR
B78: 46143 | C78: 219505.54 | J78: IPCA - Longo | K78: 2- Renda Fixa | L78: 1- Subclasse | M78: =GETPIVOTDATA("Total (R$)",$B$39,"Subclasse","IPCA","Duração","Longo") -> 0.25736919 | N78: =Table17[[#This Row],[Percentual Atual]]*GETPIVOTDATA("Total (R$)",$B$5,"Classe","Renda Fixa") -> 11955.66 | O78: =Tables_Atual_Ideal!M41 -> 0.15 | P78: =Table17[[#This Row],[Percentual Ideal]]*$K$8 -> 8140.2274 | Q78: =Table17[[#This Row],[Total Atual]]-Table17[[#This Row],[Total Ideal]] -> 3815.4326 | R78: =IF(Table17[[#This Row],[Diferenca]]>0,"VENDER","COMPRAR") -> VENDER
B79: 46174 | C79: 197861.66 | J79: IPCA - Médio | K79: 2- Renda Fixa | L79: 1- Subclasse | M79: =GETPIVOTDATA("Total (R$)",$B$39,"Subclasse","IPCA","Duração","Médio") -> 0.1073818 | N79: =Table17[[#This Row],[Percentual Atual]]*GETPIVOTDATA("Total (R$)",$B$5,"Classe","Renda Fixa") -> 4988.244 | O79: =Tables_Atual_Ideal!L41 -> 0.25 | P79: =Table17[[#This Row],[Percentual Ideal]]*$K$8 -> 13567.046 | Q79: =Table17[[#This Row],[Total Atual]]-Table17[[#This Row],[Total Ideal]] -> -8578.8017 | R79: =IF(Table17[[#This Row],[Diferenca]]>0,"VENDER","COMPRAR") -> COMPRAR
B80: 46204 | C80: 217072.73 | J80: Pós-fixado - Médio | K80: 2- Renda Fixa | L80: 1- Subclasse | M80: =GETPIVOTDATA("Total (R$)",$B$39,"Subclasse","Pós-fixado","Duração","Médio") -> 0.25803337 | N80: =Table17[[#This Row],[Percentual Atual]]*GETPIVOTDATA("Total (R$)",$B$5,"Classe","Renda Fixa") -> 11986.513 | O80: =Tables_Atual_Ideal!L42 -> 0.25 | P80: =Table17[[#This Row],[Percentual Ideal]]*$K$8 -> 13567.046 | Q80: =Table17[[#This Row],[Total Atual]]-Table17[[#This Row],[Total Ideal]] -> -1580.5327 | R80: =IF(Table17[[#This Row],[Diferenca]]>0,"VENDER","COMPRAR") -> COMPRAR
J81: Renda Variável (R$) | K81: 3- Renda Variável | L81: 1- Moeda | M81: =GETPIVOTDATA("Total (R$)2",$B$14,"Classe","Renda Variável","Moeda Base","BRL") -> 0.059589636 | N81: =Table17[[#This Row],[Percentual Atual]]*GETPIVOTDATA("Total (R$)",$B$5) -> 12935.285 | O81: =$N$16 -> 0.04 | P81: =Table17[[#This Row],[Percentual Ideal]]*Table_ClasseAtivos[[#Totals],[Total Ideal]] -> 8682.9092 | Q81: =Table17[[#This Row],[Total Atual]]-Table17[[#This Row],[Total Ideal]] -> 4252.3758 | R81: =IF(Table17[[#This Row],[Diferenca]]>0,"VENDER","COMPRAR") -> VENDER
J82: Renda Variável (USD) | K82: 3- Renda Variável | L82: 1- Moeda | M82: =GETPIVOTDATA("Total (R$)2",$B$14,"Classe","Renda Variável","Moeda Base","USD") -> 0.064982754 | N82: =Table17[[#This Row],[Percentual Atual]]*GETPIVOTDATA("Total (R$)",$B$5) -> 14105.984 | O82: =$N$18 -> 0.16 | P82: =Table17[[#This Row],[Percentual Ideal]]*Table_ClasseAtivos[[#Totals],[Total Ideal]] -> 34731.637 | Q82: =Table17[[#This Row],[Total Atual]]-Table17[[#This Row],[Total Ideal]] -> -20625.653 | R82: =IF(Table17[[#This Row],[Diferenca]]>0,"VENDER","COMPRAR") -> COMPRAR
J83: Commoditie | K83: 3- Renda Variável | L83: 2- Subclasse | M83: =GETPIVOTDATA("Total (R$)",$B$48,"Subclasse","Commoditie") -> 0.033582259 | N83: =Table17[[#This Row],[Percentual Atual]]*GETPIVOTDATA("Total (R$)",$B$5,"Classe","Renda Variável") -> 908.10688 | O83: =Tables_Atual_Ideal!K52 -> 0.045 | P83: =Table17[[#This Row],[Percentual Ideal]]*$K$9 -> 1953.6546 | Q83: =Table17[[#This Row],[Total Atual]]-Table17[[#This Row],[Total Ideal]] -> -1045.5477 | R83: =IF(Table17[[#This Row],[Diferenca]]>0,"VENDER","COMPRAR") -> COMPRAR
J84: Imobiliário BR | K84: 3- Renda Variável | L84: 2- Subclasse | M84: =GETPIVOTDATA("Total (R$)",$B$48,"Subclasse","Imobiliário BR") -> 0.069578688 | N84: =Table17[[#This Row],[Percentual Atual]]*GETPIVOTDATA("Total (R$)",$B$5,"Classe","Renda Variável") -> 1881.496 | O84: =Tables_Atual_Ideal!K53 -> 0.05 | P84: =Table17[[#This Row],[Percentual Ideal]]*$K$9 -> 2170.7273 | Q84: =Table17[[#This Row],[Total Atual]]-Table17[[#This Row],[Total Ideal]] -> -289.23131 | R84: =IF(Table17[[#This Row],[Diferenca]]>0,"VENDER","COMPRAR") -> COMPRAR
J85: Ações - Ex: USA | K85: 3- Renda Variável | L85: 2- Subclasse | M85: =GETPIVOTDATA("Total (R$)",$B$48,"Subclasse","Ações - Ex: USA") -> 0.074176991 | N85: =Table17[[#This Row],[Percentual Atual]]*GETPIVOTDATA("Total (R$)",$B$5,"Classe","Renda Variável") -> 2005.84 | O85: =Tables_Atual_Ideal!K50 -> 0.2 | P85: =Table17[[#This Row],[Percentual Ideal]]*$K$9 -> 8682.9092 | Q85: =Table17[[#This Row],[Total Atual]]-Table17[[#This Row],[Total Ideal]] -> -6677.0693 | R85: =IF(Table17[[#This Row],[Diferenca]]>0,"VENDER","COMPRAR") -> COMPRAR
J86: Ações BR | K86: 3- Renda Variável | L86: 2- Subclasse | M86: =GETPIVOTDATA("Total (R$)",$B$48,"Subclasse","Ações BR") -> 0.24352541 | N86: =Table17[[#This Row],[Percentual Atual]]*GETPIVOTDATA("Total (R$)",$B$5,"Classe","Renda Variável") -> 6585.236 | O86: =Tables_Atual_Ideal!K51 -> 0.2 | P86: =Table17[[#This Row],[Percentual Ideal]]*$K$9 -> 8682.9092 | Q86: =Table17[[#This Row],[Total Atual]]-Table17[[#This Row],[Total Ideal]] -> -2097.6732 | R86: =IF(Table17[[#This Row],[Diferenca]]>0,"VENDER","COMPRAR") -> COMPRAR
J87: Ações EUA | K87: 3- Renda Variável | L87: 2- Subclasse | M87: =GETPIVOTDATA("Total (R$)",$B$48,"Subclasse","Ações EUA") -> 0.57913666 | N87: =Table17[[#This Row],[Percentual Atual]]*GETPIVOTDATA("Total (R$)",$B$5,"Classe","Renda Variável") -> 15660.59 | O87: =Tables_Atual_Ideal!K49 -> 0.5 | P87: =Table17[[#This Row],[Percentual Ideal]]*$K$9 -> 21707.273 | Q87: =Table17[[#This Row],[Total Atual]]-Table17[[#This Row],[Total Ideal]] -> -6046.683 | R87: =IF(Table17[[#This Row],[Diferenca]]>0,"VENDER","COMPRAR") -> COMPRAR

Sheet Gastos_Mensais
C3: Entradas | F3: Saídas | J3: Resumo | L3: Custo de Vida Mensal
B4: Mês | C4: Salário Líquido + Extras | D4: VA/VR | E4: Entrada Total | F4: Gasto - Cartão | G4: Gasto - PIX | H4: Gasto - VA/VR | I4: Saída Total | J4: Balanço Mensal | L4: Gasto | M4: Valor | N4: Tipo
B5: 46023 | C5: 7769.88 | D5: 660 | E5: =Table12[[#This Row],[Salário Líquido + Extras]]+Table12[[#This Row],[VA/VR]] -> 8429.88 | F5: 999.34 | G5: 1660.75 | H5: 612.12 | I5: =Table12[[#This Row],[Gasto - PIX]]+Table12[[#This Row],[Gasto - VA/VR]]+Table12[[#This Row],[Gasto - Cartão]] -> 3272.21 | J5: =Table12[[#This Row],[Entrada Total]]-Table12[[#This Row],[Saída Total]] -> 5157.67 | L5: Whey | M5: 323.48 | N5: PIX
B6: 46054 | C6: 8246.39 | D6: 1100 | E6: =Table12[[#This Row],[Salário Líquido + Extras]]+Table12[[#This Row],[VA/VR]] -> 9346.39 | F6: 551.69 | G6: 2025.25 | H6: 1100 | I6: =Table12[[#This Row],[Gasto - PIX]]+Table12[[#This Row],[Gasto - VA/VR]]+Table12[[#This Row],[Gasto - Cartão]] -> 3676.94 | J6: =Table12[[#This Row],[Entrada Total]]-Table12[[#This Row],[Saída Total]] -> 5669.45 | L6: Academia | M6: 119.9 | N6: Cartão
B7: 46082 | C7: =8741.99+467 -> 9208.99 | D7: 1100 | E7: =Table12[[#This Row],[Salário Líquido + Extras]]+Table12[[#This Row],[VA/VR]] -> 10308.99 | F7: 1637 | G7: 2156.71 | H7: 1100 | I7: =Table12[[#This Row],[Gasto - PIX]]+Table12[[#This Row],[Gasto - VA/VR]]+Table12[[#This Row],[Gasto - Cartão]] -> 4893.71 | J7: =Table12[[#This Row],[Entrada Total]]-Table12[[#This Row],[Saída Total]] -> 5415.28 | L7: Apple | M7: 5.9 | N7: Cartão
B8: 46113 | C8: 8008.13 | D8: 1100 | E8: =Table12[[#This Row],[Salário Líquido + Extras]]+Table12[[#This Row],[VA/VR]] -> 9108.13 | F8: 1779.84 | G8: 573.68 | H8: 1000 | I8: =Table12[[#This Row],[Gasto - PIX]]+Table12[[#This Row],[Gasto - VA/VR]]+Table12[[#This Row],[Gasto - Cartão]] -> 3353.52 | J8: =Table12[[#This Row],[Entrada Total]]-Table12[[#This Row],[Saída Total]] -> 5754.61 | L8: Celular | M8: 30 | N8: Cartão
B9: 46143 | C9: 8601.74 | D9: 1100 | E9: =Table12[[#This Row],[Salário Líquido + Extras]]+Table12[[#This Row],[VA/VR]] -> 9701.74 | F9: 2205.55 | G9: =10.8+1110+128+267.5+4-(106-213.3-46-50) -> 1723.6 | H9: 1000 | I9: =Table12[[#This Row],[Gasto - PIX]]+Table12[[#This Row],[Gasto - VA/VR]]+Table12[[#This Row],[Gasto - Cartão]] -> 4929.15 | J9: =Table12[[#This Row],[Entrada Total]]-Table12[[#This Row],[Saída Total]] -> 4772.59 | L9: Ifood | M9: 7.95 | N9: Cartão
B10: 46174 | C10: =11642.46+3201.53+5653.71 -> 20497.7 | D10: 1100 | E10: =Table12[[#This Row],[Salário Líquido + Extras]]+Table12[[#This Row],[VA/VR]] -> 21597.7 | F10: 2839.55 | G10: =579.87+216 -> 795.87 | H10: 1000 | I10: =Table12[[#This Row],[Gasto - PIX]]+Table12[[#This Row],[Gasto - VA/VR]]+Table12[[#This Row],[Gasto - Cartão]] -> 4635.42 | J10: =Table12[[#This Row],[Entrada Total]]-Table12[[#This Row],[Saída Total]] -> 16962.28 | L10: Marcelo Nutri | M10: 366.66667 | N10: PIX
B11: 46204 | D11: 1100 | E11: =Table12[[#This Row],[Salário Líquido + Extras]]+Table12[[#This Row],[VA/VR]] -> 1100 | H11: 1000 | I11: =Table12[[#This Row],[Gasto - PIX]]+Table12[[#This Row],[Gasto - VA/VR]]+Table12[[#This Row],[Gasto - Cartão]] -> 1000 | J11: =Table12[[#This Row],[Entrada Total]]-Table12[[#This Row],[Saída Total]] -> 100
B12: 46235 | J12: =Table12[[#This Row],[Entrada Total]]-Table12[[#This Row],[Saída Total]] -> 0
B13: 46266 | J13: =Table12[[#This Row],[Entrada Total]]-Table12[[#This Row],[Saída Total]] -> 0
B14: Total | E14: =SUBTOTAL(109,Table12[Entrada Total]) -> 69592.83 | I14: =SUBTOTAL(109,Table12[Saída Total]) -> 25760.95 | J14: =SUBTOTAL(109,Table12[Balanço Mensal]) -> 43831.88 | L14: Total | M14: =SUBTOTAL(109,Table5[Valor]) -> 853.89667
L17: Controle
L18: Tipo | M18: PIX
L19: PIX | M19: =SUMIF(Table5[Tipo],Table8[[#This Row],[Tipo]],Table5[Valor]) -> 690.14667
L20: Cartão | M20: =SUMIF(Table5[Tipo],Table8[[#This Row],[Tipo]],Table5[Valor]) -> 163.75
L21: Total | M21: =SUBTOTAL(109,Table8[PIX]) -> 853.89667

Sheet Previdencia
C2: Resumo
C3: Informações | D3: Valores
C4: 12% Renda Tributável | D4: =12%*Table1[[#Totals],[Renda Tributável]] -> 8587.314
C5: Investimento Pendente | D5: =D4-Table25[[#Totals],[Valor]] -> -1412.686
C7: Parcelas Investidas
C8: Nº Parela | D8: Data | E8: Valor
C9: 1 | D9: 45877 | E9: 5100
C10: =C9+1 -> 2 | D10: 45999 | E10: 7280
C11: =C10+1 -> 3 | D11: 46093 | E11: 4000
C12: =C11+1 -> 4 | D12: 46127 | E12: 3000
C13: 5 | D13: 46182 | E13: 1000
C14: 6 | D14: 46209 | E14: 2000
D15: Total | E15: =SUBTOTAL(109,Table25[Valor]) -> 10000
C17: Meses Trabalhados
C18: Mês Base | D18: Empresa | E18: Data Incial | F18: Data Final | G18: Dias Trabalhados | H18: Necessario Calcular | I18: Salário Base Bruto | J18: Saário Por dia | K18: Renda Tributável
C19: 45658 | D19: Accenture | E19: 45658 | F19: 45688 | G19: =_xlfn.DAYS(Previdencia!$F19,Previdencia!$E19)+1 -> 31 | H19: Não | I19: 3282.5 | J19: =Previdencia!$I19/30 -> 109.41667 | K19: =IF(Previdencia!$H19="Sim",Previdencia!$J19*Previdencia!$G19,Previdencia!$I19) -> 3282.5
C20: 45689 | D20: Accenture | E20: 45689 | F20: 45716 | G20: =_xlfn.DAYS(Previdencia!$F20,Previdencia!$E20)+1 -> 28 | H20: Não | I20: 3282.5 | J20: =Previdencia!$I20/30 -> 109.41667 | K20: =IF(Previdencia!$H20="Sim",Previdencia!$J20*Previdencia!$G20,Previdencia!$I20) -> 3282.5
C21: 45717 | D21: Accenture | E21: 45717 | F21: 45718 | G21: =_xlfn.DAYS(Previdencia!$F21,Previdencia!$E21)+1 -> 2 | H21: Sim | I21: 3282.5 | J21: =Previdencia!$I21/30 -> 109.41667 | K21: =IF(Previdencia!$H21="Sim",Previdencia!$J21*Previdencia!$G21,Previdencia!$I21) -> 218.83333
C22: 45717 | D22: NTT DATA | E22: 45719 | F22: 45747 | G22: =_xlfn.DAYS(Previdencia!$F22,Previdencia!$E22)+1 -> 29 | H22: Sim | I22: 7000 | J22: =Previdencia!$I22/30 -> 233.33333 | K22: =IF(Previdencia!$H22="Sim",Previdencia!$J22*Previdencia!$G22,Previdencia!$I22) -> 6766.6667
C23: 45748 | D23: NTT DATA | E23: 45748 | F23: 45777 | G23: =_xlfn.DAYS(Previdencia!$F23,Previdencia!$E23)+1 -> 30 | H23: Não | I23: 7000 | J23: =Previdencia!$I23/30 -> 233.33333 | K23: =IF(Previdencia!$H23="Sim",Previdencia!$J23*Previdencia!$G23,Previdencia!$I23) -> 7000
C24: 45778 | D24: NTT DATA | E24: 45778 | F24: 45786 | G24: =_xlfn.DAYS(Previdencia!$F24,Previdencia!$E24)+1 -> 9 | H24: Sim | I24: 7000 | J24: =Previdencia!$I24/30 -> 233.33333 | K24: =IF(Previdencia!$H24="Sim",Previdencia!$J24*Previdencia!$G24,Previdencia!$I24) -> 2100
C25: 45778 | D25: AMARIS | E25: 45789 | F25: 45808 | G25: =_xlfn.DAYS(Previdencia!$F25,Previdencia!$E25)+1 -> 20 | H25: Sim | I25: 10500 | J25: =Previdencia!$I25/30 -> 350 | K25: =IF(Previdencia!$H25="Sim",Previdencia!$J25*Previdencia!$G25,Previdencia!$I25) -> 7000
C26: 45809 | D26: AMARIS | E26: 45809 | F26: 45838 | G26: =_xlfn.DAYS(Previdencia!$F26,Previdencia!$E26)+1 -> 30 | H26: Não | I26: 10500 | J26: =Previdencia!$I26/30 -> 350 | K26: =IF(Previdencia!$H26="Sim",Previdencia!$J26*Previdencia!$G26,Previdencia!$I26) -> 10500
C27: 45839 | D27: AMARIS | E27: 45839 | F27: 45869 | G27: =_xlfn.DAYS(Previdencia!$F27,Previdencia!$E27)+1 -> 31 | H27: Não | I27: 10500 | J27: =Previdencia!$I27/30 -> 350 | K27: =IF(Previdencia!$H27="Sim",Previdencia!$J27*Previdencia!$G27,Previdencia!$I27) -> 10500
C28: 45870 | D28: AMARIS | E28: 45870 | F28: 45900 | G28: =_xlfn.DAYS(Previdencia!$F28,Previdencia!$E28)+1 -> 31 | H28: Não | I28: 10500 | J28: =Previdencia!$I28/30 -> 350 | K28: =IF(Previdencia!$H28="Sim",Previdencia!$J28*Previdencia!$G28,Previdencia!$I28) -> 10500
C29: 45901 | D29: AMARIS | E29: 45901 | F29: 45930 | G29: =_xlfn.DAYS(Previdencia!$F29,Previdencia!$E29)+1 -> 30 | H29: Não | I29: 10500 | J29: =Previdencia!$I29/30 -> 350 | K29: =IF(Previdencia!$H29="Sim",Previdencia!$J29*Previdencia!$G29,Previdencia!$I29) -> 10500
C30: 45931 | D30: AMARIS | E30: 45931 | F30: 45961 | G30: =_xlfn.DAYS(Previdencia!$F30,Previdencia!$E30)+1 -> 31 | H30: Não | I30: 10500 | J30: =Previdencia!$I30/30 -> 350 | K30: =IF(Previdencia!$H30="Sim",Previdencia!$J30*Previdencia!$G30,Previdencia!$I30) -> 10500
... C38: 46174 | D38: AMARIS | E38: 46174 | F38: 46203 | G38: =_xlfn.DAYS(Previdencia!$F38,Previdencia!$E38)+1 -> 30 | H38: Não | I38: 15793.22 | J38: =Previdencia!$I38/30 -> 526.44067 | K38: =IF(Previdencia!$H38="Sim",Previdencia!$J38*Previdencia!$G38,Previdencia!$I38) -> 15793.22
C39: Total | K39: =SUBTOTAL(109,Table1[Renda Tributável]) -> 71560.95
